Workbook

Sheet Startegy Changes Mod or Fun (QT
A3: Fund or Model | B3: Strategy Detail | C3: Portfolios name | D3: Flows mln 1Q € | E3: Sum of % Change Flows | F3: Difference In AUM mln Q1 €
A4: Fund | D4: -519.25036 | E4: -0.12505604 | F4: -350.87
B5: Bond | D5: -2.9774607 | E5: -0.04010165 | F5: -2.9849541
B6: Conservative | D6: -7.3841967 | E6: -0.028701929 | F6: -5.1672111
B7: Equity | D7: -14.921085 | E7: -0.12510663 | F7: -18.078061
B8: Flexible | D8: -26.306785 | E8: -0.071493562 | F8: -32.02505
B9: Growth | D9: 25.096397 | E9: 0.1442819 | F9: 27.735835
B10: Income | D10: -11.006052 | E10: -0.037418931 | F10: -16.633531
B11: Moderate | D11: -9.826379 | E11: -0.022059036 | F11: -1.6296295
B12: Risk Accumulation | D12: -335.01257 | E12: -0.18945034 | F12: -420.76862
B13: Thematic | D13: -136.91224 | E13: -0.21014083 | F13: 118.68122
A14: Model | D14: -307.44577 | E14: -0.035126256 | F14: -88.065456
B15: Capital Guaranteed | D15: -65.534486 | E15: -0.054219271 | F15: -44.165264
B16: Capital Protection | D16: -0.0873133 | E16: -0.012552394 | F16: -0.01984
B17: Conservative | D17: -20.27235 | E17: -0.030977101 | F17: -17.236822
B18: Equity | D18: -35.848827 | E18: -0.011128298 | F18: 100.7319
B19: Flexible | D19: -130.64609 | E19: -0.10657308 | F19: -120.7386
B20: Growth | D20: -11.94981 | E20: -0.026006461 | F20: 4.694794
B21: Income | D21: -54.349645 | E21: -0.086591532 | F21: -57.063289
B22: Moderate | D22: -3.712064 | E22: -0.021657603 | F22: -2.638989
B23: Risk Accumulation | D23: -0.6752106 | E23: -0.14351059 | F23: -0.468905
B24: Thematic | D24: 15.630024 | E24: 0.013336587 | F24: 48.83956
A25: Grand Total | D25: -826.69614 | E25: -0.064061467 | F25: -438.93546

Sheet Startegy Changes (QTD)
A3: Strategy Detail | B3: Flows mln Q1 € | C3: Difference In AUM mln Q1 €
A4: Bond | B4: -2.9774607 | C4: -2.9849541
A5: Capital Guaranteed | B5: -65.534486 | C5: -44.165264
A6: Capital Protection | B6: -0.0873133 | C6: -0.01984
A7: Conservative | B7: -27.656547 | C7: -22.404033
A8: Equity | B8: -50.769913 | C8: 82.653837
A9: Flexible | B9: -156.95288 | C9: -152.76365
A10: Growth | B10: 13.146587 | C10: 32.430629
A11: Income | B11: -65.355696 | C11: -73.69682
A12: Moderate | B12: -13.538443 | C12: -4.2686185
A13: Risk Accumulation | B13: -335.68778 | C13: -421.23752
A14: Thematic | B14: -121.28221 | C14: 167.52078
A15: Grand Total | B15: -826.69614 | C15: -438.93546

Sheet Total Flows File (QTD)
A3: Portfolio Names | B3: Q123 Flows mln | C3: Q123 Difference In AUM | D3: Total Aum mln
A4: Capital Guaranteed | B4: -65.534486 | C4: -44.165264 | D4: 1208.6936
A5: ASSET ALLOCATION MODEL PROTETTO 80 | B5: -3.0901017 | C5: -2.123896 | D5: 105.97773
A6: CNP Dynamic Protection 80 | B6: -16.088829 | C6: -15.428341 | D6: 116.83255
A7: CNP THEMATIC PROTECTION 80 | B7: -10.521304 | C7: -6.386983 | D7: 195.36411
A8: CRV Dynamic Protection 80 | B8: -25.728394 | C8: -24.41432 | D8: 279.29356
A9: CRV THEMATIC PROTECTION 80 | B9: -11.494401 | C9: -4.918099 | D9: 307.50581
A10: CNP Protection 80 | B10: 0.36790654 | C10: 3.955401 | D10: 96.897819
A11: CRV Protection 80 | B11: 1.0206376 | C11: 5.150974 | D11: 106.82203
A12: Conservative | B12: -27.656547 | C12: -22.404033 | D12: 911.70197
A13: AMUNDI FUND SOLUTIONS - CONSERVATIVE | B13: -6.5852741 | C13: -4.3407969 | D13: 242.8063
A14: AMUNDI FUND SOLUTIONS - SABADELL URQUIJO ACUMULACION | B14: 0 | C14: 0 | D14: 6.9702262
A15: AMUNDI UNICREDIT PREM PORT- PRUDENTIAL | B15: -0.79892258 | C15: -0.82641419 | D15: 7.4952658
... A19: CAM STEP ONE | B19: 0 | C19: 0.001073 | D19: 0.078465
A20: CAM TREND 20 | B20: 0 | C20: 0 | D20: 0.023564 | H20: Funds | I20: Sum of Flows QTD mln | J20: Sum of Difference In AUM
A21: Life Program Bond | B21: -4.0474815 | C21: -3.214771 | D21: 86.278219 | H21: Univalore Stars Growth | I21: -176.18718 | J21: 117.43585
A22: PL Euro Bond 1 to 3 years | B22: -4.6289986 | C22: -3.879674 | D22: 87.573063 | H22: UNICREDIT EVOLUZIONE - REDDITO - A | I22: -50.325316 | J22: -51.999433
A23: PL Euro Bond over 3 years | B23: -0.18858553 | C23: 0.682015 | D23: 122.52132 | H23: CNP Dynamic Protection 80 | I23: -45.267894 | J23: -28.503755
A24: UL CAUTA | B24: -0.52380645 | C24: -0.286322 | D24: 27.311192 | H24: Unit Linked Multi Thematic Global Eq | I24: 10.325451 | J24: 212.69368
A25: UL PRUDENTE | B25: -0.66876387 | C25: -0.65926 | D25: 12.030736 | H25: AFS - BALANCED | I25: 13.817207 | J25: 21.290272
A26: UL PRUDENTE PIU | B26: -0.67315085 | C26: -0.613315 | D26: 15.554245 | H26: CRV THEMATIC PROTECTION 80 | I26: 17.180496 | J26: 26.976359
A27: UL_Prudente ERGO | B27: 0 | C27: 0 | D27: 0 | H27: AFS- CONSERVATIVE | I27: 41.471599 | J27: 39.459762
A28: UL_Prudente_+ ERGO | B28: 0 | C28: 0 | D28: 0 | H28: AFS - SABADELL URQUIJO CRECIMIENTO | I28: 43.818986 | J28: 44.247378
A29: UNIT LINKED E2 NEW | B29: -0.35063568 | C29: -0.30473 | D29: 7.616069 | H29: AFS - SABADELL URQUIJO ACUMULACION | I29: 104.94957 | J29: 98.074561
A30: UNIT LINKED E3 NEW | B30: -1.3791577 | C30: -1.380437 | D30: 72.484395 | H30: CNP Dynamic Protection 80 | I30: -45.267894 | J30: -28.503755
A31: Unit Linked OLD 4 | B31: -0.18290859 | C31: -0.182213 | D31: 1.067361 | H31: CRV Dynamic Protection 80 | I31: -145.17129 | J31: -109.32928
A32: SAXO EUROPE | B32: -7.0611691 | C32: -7.0611691 | D32: 192.19966 | H32: UL Life Income | I32: -78.218518 | J32: -75.150979
A33: AFS ICAV Planet ESG Conservative | H33: AMUNDI ELITE THEMATIC MA | I33: 325.57582 | J33: 325.57582
A34: Equity | B34: -50.769913 | C34: 82.653837 | D34: 3340.6785 | H34: UL Life Income 360 | I34: -155.45426 | J34: -174.27421
A35: Life Program Azionario Pacifico | B35: -0.07499342 | C35: -3.400871 | D35: 46.360523 | H35: Grand Total | I35: =SUM(I21:I34) -> -138.75323 | J35: =SUM(J21:J34) -> 417.99226
A36: PI INVESTMENT FUNDS - TACTICAL ALLOCATION FUND - H | B36: -0.44665158 | C36: -3.6036269 | D36: 53.160978
A37: UL Global Equity Dividend & Subordinated | B37: -32.352755 | C37: 23.919048 | D37: 1901.2516
A38: Unidiamond + Azionaria America | B38: 1.0081119 | C38: 79.886841 | D38: 1100.0065
A39: Unidiamond + Azionaria Intl | B39: -4.4291905 | C39: 0.32688 | D39: 173.7929
A40: Amundi Env and Climate Change Sol Fund | B40: -14.474434 | C40: -14.474434 | D40: 66.105969
A41: Flexible | B41: -156.95288 | C41: -152.76365 | D41: 1593.8429
A42: Amundi Invensys Broad Bond Portfolio | B42: 0 | C42: 3.4298218 | D42: 169.20099
A43: Life Program Flessibile | B43: -0.91659172 | C43: -0.811947 | D43: 24.819922
A44: PI INVESTMENT FUNDS - DYNAMIC ALLOCATION FUND - E | B44: -26.306785 | C44: -35.454872 | D44: 198.7592
A45: PL Income Clock | B45: -0.37310856 | C45: -0.299069 | D45: 33.652386
A46: Unit Linked A TR UNIPLAN | B46: -0.64437376 | C46: -0.616815 | D46: 12.28045 | H46: 1997 | I46: 2022 | J46: =I46-H46 -> 25
A47: Univalore E Strategia 20 | B47: -1.6527144 | C47: -1.465146 | D47: 23.044548
A48: Univalore E Strategia 30 | B48: -17.940994 | C48: -16.022861 | D48: 234.65801 | J48: 55
A49: Univalore E Strategia 40 | B49: -1.6815718 | C49: -1.488772 | D49: 17.723615
A50: Univalore E Strategia 70 | B50: -40.659051 | C50: -37.621934 | D50: 328.85118
A51: Univalore Stars Balanced | B51: -66.777687 | C51: -62.412056 | D51: 550.8526
A52: Growth | B52: 13.146587 | C52: 32.430629 | D52: 633.43394
A53: AMUNDI FUND SOLUTIONS - DIVERSIFIED GROWTH - A | B53: -1.1998128 | C53: -1.8619051 | D53: 83.823204
A54: AMUNDI FUND SOLUTIONS - SABADELL URQUIJO CRECIMIENTO | B54: 0 | C54: 0 | D54: 3.9275611
A55: AMUNDI UNICREDIT PREMIUM PORT - DYNAMIC | B55: -1.6565681 | C55: 1.6449617 | D55: 58.236487
A56: CAM ARES RISPARMIO ATTIVO M | B56: -8.0966316 | C56: 9.459997 | D56: 286.17241
A57: CAM CNP - LINEA DINAMICA | B57: -0.44445929 | C57: 0.014288 | D57: 20.379176
A58: CAM CRESCITA | B58: -0.0194731 | C58: 0.032879 | D58: 1.259071
A59: CAM SVILUPPO | B59: 0 | C59: 0 | D59: 0.033771
A60: CNP Linea Protetta Dinamica Plus | B60: -0.03492827 | C60: 0.077644 | D60: 3.991454
... A65: UNIT LINKED G5 NEW | B65: -0.00132301 | C65: 0.002361 | D65: 0.395535
A66: AFS ICAV Planet ESG Dynamic
A67: AMUNDI-FUNDACION CAJA NAVARRA DYNAMIC | B67: 27.952778 | C67: 27.952778 | D67: 27.952778 | H67: Portfolio Names | I67: Flows mln QTD | J67: Difference In AUM | L67: Portfolio Names | M67: Flows mln QTD | N67: Difference In AUM
A68: Income | B68: -65.355696 | C68: -73.69682 | D68: 921.78599 | H68: Flexible | I68: =SUM(I69:I73) -> -91.900916 | J68: =SUM(J69:J73) -> -100.71296 | L68: Flexible | M68: =SUM(M69:M73) -> -56.907447 | N68: =SUM(N69:N73) -> -22.313615
A69: Amundi Fund Solutions - Diversified Income Best Select 2022 | B69: -4.8674647 | C69: -1.3859767 | D69: 136.42864 | H69: Univalore E Strategia 20 | I69: -5.4972224 | J69: -6.991978 | L69: Univalore E Strategia 20 | M69: -3.0360827 | N69: -4.762027
A70: DISCRETIONARY INCOME ORIENTED PRODUCTS 1 | B70: 0 | C70: -0.34146286 | D70: 9.4422889 | H70: Univalore E Strategia 30 | I70: -11.251756 | J70: -12.930476 | L70: Univalore E Strategia 30 | M70: -5.4439499 | N70: -3.134221
A71: DISCRETIONARY INCOME ORIENTED PRODUCTS 2 | B71: 0 | C71: -0.55595298 | D71: 3.3454355 | H71: Univalore E Strategia 40 | I71: -5.9354575 | J71: -6.907175 | L71: Univalore E Strategia 40 | M71: -4.3881463 | N71: -4.425291
A72: DISCRETIONARY INCOME ORIENTED PRODUCTS 3 | B72: 0 | C72: -1.7370528 | D72: 5.2313798 | H72: Univalore E Strategia 70 | I72: -17.398139 | J72: -18.295401 | L72: Univalore E Strategia 70 | M72: -8.6183647 | N72: 10.114461
A73: PI INVESTMENT FUNDS - TACTICAL ALLOCATION PILLAR - E | B73: -6.1385868 | C73: -15.268212 | D73: 59.556669 | H73: Univalore Stars Balanced | I73: -51.818341 | J73: -55.587926 | L73: Univalore Stars Balanced | M73: -35.420903 | N73: -20.106537
A74: UL Life Income | B74: -15.247023 | C74: -15.083516 | D74: 215.40694 | H74: Income | I74: =SUM(I75:I78) -> -224.25022 | J74: =SUM(J75:J78) -> -263.15805 | L74: Income | M74: =SUM(M75:M78) -> -161.78978 | N74: =SUM(N75:N78) -> -211.38995
A75: UL Life Income 360 | B75: -14.572498 | C75: -15.027385 | D75: 154.99134 | H75: UL Life Income | I75: -36.314371 | J75: -44.721212 | L75: UL Life Income | M75: -26.112646 | N75: -35.511463
A76: Univalore Stars Income | B76: -24.530124 | C76: -24.317919 | D76: 239.23804 | H76: UL Life Income 360 | I76: -78.46388 | J76: -97.809182 | L76: UL Life Income 360 | M76: -54.229809 | N76: -76.649979
A77: THE TRUSTHOUSE FDN CPI+4% MULTI-AST PTF | B77: 0 | C77: 0.02065766 | D77: 98.145265 | H77: UNICREDIT EVOLUZIONE - REDDITO - A | I77: -26.976998 | J77: -27.307313 | L77: UNICREDIT EVOLUZIONE - REDDITO - A | M77: -28.44956 | N77: -31.345123
A78: Moderate | B78: -13.538443 | C78: -4.2686185 | D78: 616.85595 | H78: Univalore Stars Income | I78: -82.494971 | J78: -93.320341 | L78: Univalore Stars Income | M78: -52.997766 | N78: -67.88339
A79: AMUNDI FUND SOLUTIONS - BALANCED | B79: -4.4015434 | C79: 0.85909412 | D79: 324.00944 | H79: Risk Accumulation | I79: =SUM(I80:I87) -> 408.51324 | J79: =SUM(J80:J87) -> 442.0125 | L79: Risk Accumulation | M79: =SUM(M80:M88) -> 638.48743 | N79: =SUM(N80:N88) -> 699.49961
A80: AMUNDI UNICREDIT PREM PORT- MULTI ASSET | B80: -5.4248356 | C80: -2.4887237 | D80: 121.44878 | H80: ASI - PA CAMBIAMENTO CLIMATICO - E | I80: -41.104726 | J80: -39.15884 | L80: ASI - PA CAMBIAMENTO CLIMATICO - E | M80: -25.654945 | N80: -17.750439
A81: CAM ARES RISPARMIO BILANCIATO M | B81: -0.91588527 | C81: -0.042336 | D81: 44.621309 | H81: ASI - PA CAMBIAMENTO CLIMATICO (II) - E | I81: -36.189319 | J81: -34.637218 | L81: ASI - PA CAMBIAMENTO CLIMATICO (II) - E | M81: -22.528425 | N81: -17.199873
A82: CAM MEDIUM | B82: 0 | C82: 0.00545 | D82: 0.221348 | H82: ASI - PA MEGATREND - E | I82: -46.231503 | J82: -44.761277 | L82: ASI - PA MEGATREND - E | M82: -65.48769 | N82: -55.49744
A83: UL BILANCIATA | B83: -0.61411252 | C83: -0.597412 | D83: 10.517233 | H83: ASI - PA MEGATREND (II) - E | I83: -31.290276 | J83: -30.5989 | L83: ASI - PA MEGATREND (II) - E | M83: -22.230595 | N83: -16.839461
A84: UL BILANCIATA PIU | B84: -0.5147225 | C84: -0.475381 | D84: 17.25125 | H84: ASI - PA MILLENNIALS | I84: -19.93458 | J84: -0.926019 | L84: ASI - PA MILLENNIALS | M84: -28.80002 | N84: -24.464611
A85: UL_Bilanciata_+ERGO | B85: 0 | C85: 0 | D85: 5.017578 | H85: ASI - PA MILLENNIALS II | I85: -14.712069 | J85: -37.413316 | L85: ASI - PA MILLENNIALS II | M85: -14.701012 | N85: -11.466884
A86: UNIFLEX ACTIVE 1 | B86: -0.00857635 | C86: -0.001129 | D86: 1.363503 | H86: ASI - PA ENERGY TRANSITION | I86: -5.8520781 | J86: 35.320024 | L86: ASI - PA ENERGY TRANSITION | M86: -6.7963248 | N86: 7.18144
A87: UNIFLEX ACTIVE 2 | B87: -0.1555071 | C87: -0.009927 | D87: 26.9458 | H87: ASI - PA ENERGY TRANSITION (II) | I87: 603.82779 | J87: 594.18805 | L87: ASI - PA ENERGY TRANSITION (II) | M87: -2.4812059 | N87: 4.1646526
A88: UNIFLEX ACTIVE 3 | B88: -0.00376165 | C88: 0.001046 | D88: 0.79557 | H88: Thematic | I88: =I89 -> 421.41076 | J88: =J89 -> 430.76333 | L88: ASI - PA INFRASTRUTTURE SOSTENIBILI | M88: 827.16764 | N88: 831.37222
A89: Unit Linked AMix UNIPLAN | B89: -0.01780707 | C89: -0.017422 | D89: 0.255343 | H89: AMUNDI ELITE THEMATIC MA | I89: 421.41076 | J89: 430.76333 | L89: Thematic | M89: =SUM(M90:M92) -> 373.97488 | N89: =SUM(N90:N92) -> 503.04883
A90: UNIT LINKED E4 NEW | B90: -1.4816915 | C90: -1.501878 | D90: 64.408792 | L90: AMUNDI ELITE THEMATIC MA | M90: 282.37396 | N90: 320.95735
A91: AFS ICAV Planet ESG Balanced | L91: Unit Linked Multi Thematic Global Eq | M91: 46.081562 | N91: 133.56962
A92: Risk Accumulation | B92: -335.68778 | C92: -421.23752 | D92: 1773.0447 | L92: Unit Linked UN GOALS | M92: 45.519362 | N92: 48.521855
A93: AMUNDI SOLUZIONI ITALIA - PROGETTO AZIONE CAMBIAMENTO CLIMATICO - E
A94: AMUNDI SOLUZIONI ITALIA - PROGETTO AZIONE CAMBIAMENTO CLIMATICO (II) - E | L94: Totals | M94: =M68+M74+M79+M89 -> 793.76508 | N94: =N68+N74+N79+N89 -> 968.84486
A95: AMUNDI SOLUZIONI ITALIA - PROGETTO AZIONE MEGATREND - E
A96: AMUNDI SOLUZIONI ITALIA - PROGETTO AZIONE MEGATREND (II) - E
A97: STEP CRESCITA | B97: -0.33470783 | C97: 0 | D97: 0
A98: Unit Linked Multi Equity Accumulation | B98: -0.34050277 | C98: -0.468905 | D98: 4.704953
A99: ASI - PROGETTO AZIONE ENERGY TRANSITION | B99: -75.897228 | C99: -103.51484 | D99: 451.98023
A100: ASI - PROGETTO AZIONE ENERGY TRANSITION (II) | B100: -47.534278 | C100: -63.884148 | D100: 277.93822
A101: AMUNDI SOLUZIONI ITALIA - PROGETTO AZIONE INFRASTRUTTURE SOSTENIBILI | B101: -114.98841 | C101: -138.67363 | D101: 335.14686
A102: AMUNDI SOLUZIONI ITALIA - PROGETTO AZIONE INFRASTRUTTURE SOSTENIBILI (II) | B102: -68.314788 | C102: -89.223301 | D102: 319.41249
A103: AMUNDI SENTIERO SOSTENIBILE | B103: -10.126505 | C103: -7.3314559 | D103: 290.32318
A104: ASI - PROGETTO AZIONE FUTURO GREEN | B104: -18.151357 | C104: -18.141244 | D104: 93.538758
A105: Thematic | B105: -121.28221 | C105: 167.52078 | D105: 1823.4919
A106: AMUNDI ELITE THEMATIC MA | B106: -136.91224 | C106: 118.68122 | D106: 651.52609
A107: DISCRETIONARY INCOME ORIENTED PRODUCTS 4 | B107: 0 | C107: -4.6429407 | D107: 9.5423505
A108: Unit Linked Multi Thematic Global Eq | B108: 0 | C108: 0 | D108: 0
... A112: Unit Linked Future Trend | B112: 0.22689129 | C112: 0 | D112: 0

Sheet Startegy Changes Mod or Fun
A3: Fund or Model | B3: Strategy Detail | C3: Flows mln QTD Sept 24 € | D3: Difference In AUM mln QTD Nov 24 €
A4: Fund | C4: -519.25036 | D4: -350.87
B5: Bond | C5: -2.9774607 | D5: -2.9849541
B6: Conservative | C6: -7.3841967 | D6: -5.1672111
B7: Equity | C7: -14.921085 | D7: -18.078061
B8: Flexible | C8: -26.306785 | D8: -32.02505
B9: Growth | C9: 25.096397 | D9: 27.735835
B10: Income | C10: -11.006052 | D10: -16.633531
B11: Moderate | C11: -9.826379 | D11: -1.6296295
B12: Risk Accumulation | C12: -335.01257 | D12: -420.76862
B13: Thematic | C13: -136.91224 | D13: 118.68122
A14: Model | C14: -307.44577 | D14: -88.065456
B15: Capital Guaranteed | C15: -65.534486 | D15: -44.165264
B16: Capital Protection | C16: -0.0873133 | D16: -0.01984
B17: Conservative | C17: -20.27235 | D17: -17.236822
B18: Equity | C18: -35.848827 | D18: 100.7319
B19: Flexible | C19: -130.64609 | D19: -120.7386
B20: Growth | C20: -11.94981 | D20: 4.694794
B21: Income | C21: -54.349645 | D21: -57.063289
B22: Moderate | C22: -3.712064 | D22: -2.638989
B23: Risk Accumulation | C23: -0.6752106 | D23: -0.468905
B24: Thematic | C24: 15.630024 | D24: 48.83956
A25: Grand Total | C25: -826.69614 | D25: -438.93546

Sheet Total Flows File
A3: Portfolio Names | B3: QTD Sept 24 Flows mln | C3: QTD Sept 24 Difference In AUM | D3: QTD Sept 24 Total Aum mln
A4: Bond | B4: -2.9774607 | C4: -2.9849541 | D4: 74.247836
A5: PI INVESTMENT FUNDS - TACTICAL ALLOCATION BOND FUND - H | B5: -2.9774607 | C5: -2.9849541 | D5: 74.247836
A6: Capital Guaranteed | B6: -65.534486 | C6: -44.165264 | D6: 1208.6936
A7: ASSET ALLOCATION MODEL PROTETTO 80 | B7: -3.0901017 | C7: -2.123896 | D7: 105.97773
A8: CNP Dynamic Protection 80 | B8: -16.088829 | C8: -15.428341 | D8: 116.83255
A9: CNP THEMATIC PROTECTION 80 | B9: -10.521304 | C9: -6.386983 | D9: 195.36411
A10: CRV Dynamic Protection 80 | B10: -25.728394 | C10: -24.41432 | D10: 279.29356
A11: CRV THEMATIC PROTECTION 80 | B11: -11.494401 | C11: -4.918099 | D11: 307.50581
A12: CNP Protection 80 | B12: 0.36790654 | C12: 3.955401 | D12: 96.897819
A13: CRV Protection 80 | B13: 1.0206376 | C13: 5.150974 | D13: 106.82203
A14: Capital Protection | B14: -0.0873133 | C14: -0.01984 | D14: 6.955908
A15: CAM Agosto | B15: -0.00162516 | C15: -0.000375 | D15: 0.142698
... A19: CAM Gennaio | B19: -0.00174022 | C19: -0.000137 | D19: 0.187778
A20: CAM Giugno | B20: -0.00275801 | C20: 0.002991 | D20: 0.634676 | H20: Funds | I20: Sum of Flows QTD mln | J20: Sum of Difference In AUM
A21: CAM Luglio | B21: 0 | C21: -0.000775 | D21: 0.077561 | H21: Univalore Stars Growth | I21: -176.18718 | J21: 117.43585
A22: CAM Maggio | B22: -0.0016057 | C22: -0.000323 | D22: 0.134904 | H22: UNICREDIT EVOLUZIONE - REDDITO - A | I22: -50.325316 | J22: -51.999433
A23: CAM Marzo | B23: -0.00164449 | C23: -0.000266 | D23: 0.154948 | H23: CNP Dynamic Protection 80 | I23: -45.267894 | J23: -28.503755
A24: CAM Novembre | B24: -0.00195811 | C24: 0.000944 | D24: 0.279016 | H24: Unit Linked Multi Thematic Global Eq | I24: 10.325451 | J24: 212.69368
A25: CAM Ottobre | B25: -0.001209 | C25: -0.000946 | D25: 0.028074 | H25: AFS - BALANCED | I25: 13.817207 | J25: 21.290272
A26: CAM Settembre | B26: -0.00057969 | C26: -0.000434 | D26: 0.016557 | H26: CRV THEMATIC PROTECTION 80 | I26: 17.180496 | J26: 26.976359
A27: Conservative | B27: -27.656547 | C27: -22.404033 | D27: 911.70197 | H27: AFS- CONSERVATIVE | I27: 41.471599 | J27: 39.459762
A28: AMUNDI FUND SOLUTIONS - CONSERVATIVE | B28: -6.5852741 | C28: -4.3407969 | D28: 242.8063 | H28: AFS - SABADELL URQUIJO CRECIMIENTO | I28: 43.818986 | J28: 44.247378
A29: AMUNDI FUND SOLUTIONS - SABADELL URQUIJO ACUMULACION | B29: 0 | C29: 0 | D29: 6.9702262 | H29: AFS - SABADELL URQUIJO ACUMULACION | I29: 104.94957 | J29: 98.074561
A30: AMUNDI UNICREDIT PREM PORT- PRUDENTIAL | B30: -0.79892258 | C30: -0.82641419 | D30: 7.4952658 | H30: CNP Dynamic Protection 80 | I30: -45.267894 | J30: -28.503755
A31: CAM ARES RISPARMIO OBBLIGAZ. M | B31: -0.56769213 | C31: -0.338342 | D31: 29.605967 | H31: CRV Dynamic Protection 80 | I31: -145.17129 | J31: -109.32928
A32: CAM OBBLIGAZIONARIA EURO | B32: 0 | C32: 0 | D32: 0.002649 | H32: UL Life Income | I32: -78.218518 | J32: -75.150979
... A34: CAM STEP ONE | B34: 0 | C34: 0.001073 | D34: 0.078465 | H34: UL Life Income 360 | I34: -155.45426 | J34: -174.27421
A35: CAM TREND 20 | B35: 0 | C35: 0 | D35: 0.023564 | H35: Grand Total | I35: =SUM(I21:I34) -> -138.75323 | J35: =SUM(J21:J34) -> 417.99226
A36: Life Program Bond | B36: -4.0474815 | C36: -3.214771 | D36: 86.278219
A37: PL Euro Bond 1 to 3 years | B37: -4.6289986 | C37: -3.879674 | D37: 87.573063
A38: PL Euro Bond over 3 years | B38: -0.18858553 | C38: 0.682015 | D38: 122.52132
A39: UL CAUTA | B39: -0.52380645 | C39: -0.286322 | D39: 27.311192
A40: UL PRUDENTE | B40: -0.66876387 | C40: -0.65926 | D40: 12.030736
A41: UL PRUDENTE PIU | B41: -0.67315085 | C41: -0.613315 | D41: 15.554245
A42: UL_Prudente ERGO | B42: 0 | C42: 0 | D42: 0
A43: UL_Prudente_+ ERGO | B43: 0 | C43: 0 | D43: 0
A44: UNIT LINKED E2 NEW | B44: -0.35063568 | C44: -0.30473 | D44: 7.616069
A45: UNIT LINKED E3 NEW | B45: -1.3791577 | C45: -1.380437 | D45: 72.484395
A46: Unit Linked OLD 4 | B46: -0.18290859 | C46: -0.182213 | D46: 1.067361 | H46: 1997 | I46: 2022 | J46: =I46-H46 -> 25
A47: SAXO EUROPE | B47: -7.0611691 | C47: -7.0611691 | D47: 192.19966
A48: AFS ICAV Planet ESG Conservative | J48: 55
A49: Equity | B49: -50.769913 | C49: 82.653837 | D49: 3340.6785
A50: Life Program Azionario Pacifico | B50: -0.07499342 | C50: -3.400871 | D50: 46.360523
A51: PI INVESTMENT FUNDS - TACTICAL ALLOCATION FUND - H | B51: -0.44665158 | C51: -3.6036269 | D51: 53.160978
A52: UL Global Equity Dividend & Subordinated | B52: -32.352755 | C52: 23.919048 | D52: 1901.2516
A53: Unidiamond + Azionaria America | B53: 1.0081119 | C53: 79.886841 | D53: 1100.0065
A54: Unidiamond + Azionaria Intl | B54: -4.4291905 | C54: 0.32688 | D54: 173.7929
A55: Amundi Env and Climate Change Sol Fund | B55: -14.474434 | C55: -14.474434 | D55: 66.105969
A56: Flexible | B56: -156.95288 | C56: -152.76365 | D56: 1593.8429
A57: Amundi Invensys Broad Bond Portfolio | B57: 0 | C57: 3.4298218 | D57: 169.20099
A58: Life Program Flessibile | B58: -0.91659172 | C58: -0.811947 | D58: 24.819922
A59: PI INVESTMENT FUNDS - DYNAMIC ALLOCATION FUND - E | B59: -26.306785 | C59: -35.454872 | D59: 198.7592
A60: PL Income Clock | B60: -0.37310856 | C60: -0.299069 | D60: 33.652386
... A66: Univalore Stars Balanced | B66: -66.777687 | C66: -62.412056 | D66: 550.8526
A67: Growth | B67: 13.146587 | C67: 32.430629 | D67: 633.43394 | H67: Portfolio Names | I67: Flows mln QTD | J67: Difference In AUM | L67: Portfolio Names | M67: Flows mln QTD | N67: Difference In AUM
A68: AMUNDI FUND SOLUTIONS - DIVERSIFIED GROWTH - A | B68: -1.1998128 | C68: -1.8619051 | D68: 83.823204 | H68: Flexible | I68: =SUM(I69:I73) -> -91.900916 | J68: =SUM(J69:J73) -> -100.71296 | L68: Flexible | M68: =SUM(M69:M73) -> -56.907447 | N68: =SUM(N69:N73) -> -22.313615
A69: AMUNDI FUND SOLUTIONS - SABADELL URQUIJO CRECIMIENTO | B69: 0 | C69: 0 | D69: 3.9275611 | H69: Univalore E Strategia 20 | I69: -5.4972224 | J69: -6.991978 | L69: Univalore E Strategia 20 | M69: -3.0360827 | N69: -4.762027
A70: AMUNDI UNICREDIT PREMIUM PORT - DYNAMIC | B70: -1.6565681 | C70: 1.6449617 | D70: 58.236487 | H70: Univalore E Strategia 30 | I70: -11.251756 | J70: -12.930476 | L70: Univalore E Strategia 30 | M70: -5.4439499 | N70: -3.134221
A71: CAM ARES RISPARMIO ATTIVO M | B71: -8.0966316 | C71: 9.459997 | D71: 286.17241 | H71: Univalore E Strategia 40 | I71: -5.9354575 | J71: -6.907175 | L71: Univalore E Strategia 40 | M71: -4.3881463 | N71: -4.425291
A72: CAM CNP - LINEA DINAMICA | B72: -0.44445929 | C72: 0.014288 | D72: 20.379176 | H72: Univalore E Strategia 70 | I72: -17.398139 | J72: -18.295401 | L72: Univalore E Strategia 70 | M72: -8.6183647 | N72: 10.114461
A73: CAM CRESCITA | B73: -0.0194731 | C73: 0.032879 | D73: 1.259071 | H73: Univalore Stars Balanced | I73: -51.818341 | J73: -55.587926 | L73: Univalore Stars Balanced | M73: -35.420903 | N73: -20.106537
A74: CAM SVILUPPO | B74: 0 | C74: 0 | D74: 0.033771 | H74: Income | I74: =SUM(I75:I78) -> -224.25022 | J74: =SUM(J75:J78) -> -263.15805 | L74: Income | M74: =SUM(M75:M78) -> -161.78978 | N74: =SUM(N75:N78) -> -211.38995
A75: CNP Linea Protetta Dinamica Plus | B75: -0.03492827 | C75: 0.077644 | D75: 3.991454 | H75: UL Life Income | I75: -36.314371 | J75: -44.721212 | L75: UL Life Income | M75: -26.112646 | N75: -35.511463
A76: UL DINAMICA | B76: -0.90587481 | C76: -0.950039 | D76: 18.063937 | H76: UL Life Income 360 | I76: -78.46388 | J76: -97.809182 | L76: UL Life Income 360 | M76: -54.229809 | N76: -76.649979
A77: UL_Dinamica ERGO | B77: 0 | C77: 0 | D77: 0 | H77: UNICREDIT EVOLUZIONE - REDDITO - A | I77: -26.976998 | J77: -27.307313 | L77: UNICREDIT EVOLUZIONE - REDDITO - A | M77: -28.44956 | N77: -31.345123
A78: UNIT LINKED E6 NEW | B78: -2.4464384 | C78: -3.946471 | D78: 128.7875 | H78: Univalore Stars Income | I78: -82.494971 | J78: -93.320341 | L78: Univalore Stars Income | M78: -52.997766 | N78: -67.88339
A79: UNIT LINKED G4 NEW | B79: -0.00068171 | C79: 0.004135 | D79: 0.411051 | H79: Risk Accumulation | I79: =SUM(I80:I87) -> 408.51324 | J79: =SUM(J80:J87) -> 442.0125 | L79: Risk Accumulation | M79: =SUM(M80:M88) -> 638.48743 | N79: =SUM(N80:N88) -> 699.49961
A80: UNIT LINKED G5 NEW | B80: -0.00132301 | C80: 0.002361 | D80: 0.395535 | H80: ASI - PA CAMBIAMENTO CLIMATICO - E | I80: -41.104726 | J80: -39.15884 | L80: ASI - PA CAMBIAMENTO CLIMATICO - E | M80: -25.654945 | N80: -17.750439
A81: AFS ICAV Planet ESG Dynamic | H81: ASI - PA CAMBIAMENTO CLIMATICO (II) - E | I81: -36.189319 | J81: -34.637218 | L81: ASI - PA CAMBIAMENTO CLIMATICO (II) - E | M81: -22.528425 | N81: -17.199873
A82: AMUNDI-FUNDACION CAJA NAVARRA DYNAMIC | B82: 27.952778 | C82: 27.952778 | D82: 27.952778 | H82: ASI - PA MEGATREND - E | I82: -46.231503 | J82: -44.761277 | L82: ASI - PA MEGATREND - E | M82: -65.48769 | N82: -55.49744
A83: Income | B83: -65.355696 | C83: -73.69682 | D83: 921.78599 | H83: ASI - PA MEGATREND (II) - E | I83: -31.290276 | J83: -30.5989 | L83: ASI - PA MEGATREND (II) - E | M83: -22.230595 | N83: -16.839461
A84: Amundi Fund Solutions - Diversified Income Best Select 2022 | B84: -4.8674647 | C84: -1.3859767 | D84: 136.42864 | H84: ASI - PA MILLENNIALS | I84: -19.93458 | J84: -0.926019 | L84: ASI - PA MILLENNIALS | M84: -28.80002 | N84: -24.464611
A85: DISCRETIONARY INCOME ORIENTED PRODUCTS 1 | B85: 0 | C85: -0.34146286 | D85: 9.4422889 | H85: ASI - PA MILLENNIALS II | I85: -14.712069 | J85: -37.413316 | L85: ASI - PA MILLENNIALS II | M85: -14.701012 | N85: -11.466884
A86: DISCRETIONARY INCOME ORIENTED PRODUCTS 2 | B86: 0 | C86: -0.55595298 | D86: 3.3454355 | H86: ASI - PA ENERGY TRANSITION | I86: -5.8520781 | J86: 35.320024 | L86: ASI - PA ENERGY TRANSITION | M86: -6.7963248 | N86: 7.18144
A87: DISCRETIONARY INCOME ORIENTED PRODUCTS 3 | B87: 0 | C87: -1.7370528 | D87: 5.2313798 | H87: ASI - PA ENERGY TRANSITION (II) | I87: 603.82779 | J87: 594.18805 | L87: ASI - PA ENERGY TRANSITION (II) | M87: -2.4812059 | N87: 4.1646526
A88: PI INVESTMENT FUNDS - TACTICAL ALLOCATION PILLAR - E | B88: -6.1385868 | C88: -15.268212 | D88: 59.556669 | H88: Thematic | I88: =I89 -> 421.41076 | J88: =J89 -> 430.76333 | L88: ASI - PA INFRASTRUTTURE SOSTENIBILI | M88: 827.16764 | N88: 831.37222
A89: UL Life Income | B89: -15.247023 | C89: -15.083516 | D89: 215.40694 | H89: AMUNDI ELITE THEMATIC MA | I89: 421.41076 | J89: 430.76333 | L89: Thematic | M89: =SUM(M90:M92) -> 373.97488 | N89: =SUM(N90:N92) -> 503.04883
A90: UL Life Income 360 | B90: -14.572498 | C90: -15.027385 | D90: 154.99134 | L90: AMUNDI ELITE THEMATIC MA | M90: 282.37396 | N90: 320.95735
A91: Univalore Stars Income | B91: -24.530124 | C91: -24.317919 | D91: 239.23804 | L91: Unit Linked Multi Thematic Global Eq | M91: 46.081562 | N91: 133.56962
A92: THE TRUSTHOUSE FDN CPI+4% MULTI-AST PTF | B92: 0 | C92: 0.02065766 | D92: 98.145265 | L92: Unit Linked UN GOALS | M92: 45.519362 | N92: 48.521855
A93: Moderate | B93: -13.538443 | C93: -4.2686185 | D93: 616.85595
A94: AMUNDI FUND SOLUTIONS - BALANCED | B94: -4.4015434 | C94: 0.85909412 | D94: 324.00944 | L94: Totals | M94: =M68+M74+M79+M89 -> 793.76508 | N94: =N68+N74+N79+N89 -> 968.84486
A95: AMUNDI UNICREDIT PREM PORT- MULTI ASSET | B95: -5.4248356 | C95: -2.4887237 | D95: 121.44878
A96: CAM ARES RISPARMIO BILANCIATO M | B96: -0.91588527 | C96: -0.042336 | D96: 44.621309
A97: CAM MEDIUM | B97: 0 | C97: 0.00545 | D97: 0.221348
A98: UL BILANCIATA | B98: -0.61411252 | C98: -0.597412 | D98: 10.517233
A99: UL BILANCIATA PIU | B99: -0.5147225 | C99: -0.475381 | D99: 17.25125
A100: UL_Bilanciata_+ERGO | B100: 0 | C100: 0 | D100: 5.017578
A101: UNIFLEX ACTIVE 1 | B101: -0.00857635 | C101: -0.001129 | D101: 1.363503
A102: UNIFLEX ACTIVE 2 | B102: -0.1555071 | C102: -0.009927 | D102: 26.9458
A103: UNIFLEX ACTIVE 3 | B103: -0.00376165 | C103: 0.001046 | D103: 0.79557
A104: Unit Linked AMix UNIPLAN | B104: -0.01780707 | C104: -0.017422 | D104: 0.255343
A105: UNIT LINKED E4 NEW | B105: -1.4816915 | C105: -1.501878 | D105: 64.408792
A106: AFS ICAV Planet ESG Balanced
A107: Risk Accumulation | B107: -335.68778 | C107: -421.23752 | D107: 1773.0447
A108: AMUNDI SOLUZIONI ITALIA - PROGETTO AZIONE CAMBIAMENTO CLIMATICO - E
A109: AMUNDI SOLUZIONI ITALIA - PROGETTO AZIONE CAMBIAMENTO CLIMATICO (II) - E
A110: AMUNDI SOLUZIONI ITALIA - PROGETTO AZIONE MEGATREND - E
A111: AMUNDI SOLUZIONI ITALIA - PROGETTO AZIONE MEGATREND (II) - E
...

Sheet Startegy Changes
A3: Fund or Model | B3: Strategy Detail | C3: Portfolios name | D3: Flows mln € | E3: Sum of % Change Flows | F3: Change In AUM mln € | G3: Total AUM
A4: Fund | D4: -519.25036 | E4: -0.12505604 | F4: -350.87 | G4: 4152.1414
B5: Bond | D5: -2.9774607 | E5: -0.04010165 | F5: -2.9849541 | G5: 74.247836
C6: PI INVESTMENT FUNDS - TACTICAL ALLOCATION BOND FUND - H | D6: -2.9774607 | E6: -0.04010165 | F6: -2.9849541 | G6: 74.247836
B7: Conservative | D7: -7.3841967 | E7: -0.028701929 | F7: -5.1672111 | G7: 257.27179
C8: AFS ICAV Planet ESG Conservative | E8: #DIV/0!
C9: AMUNDI FUND SOLUTIONS - CONSERVATIVE | D9: -6.5852741 | E9: -0.027121513 | F9: -4.3407969 | G9: 242.8063
C10: AMUNDI FUND SOLUTIONS - SABADELL URQUIJO ACUMULACION | D10: 0 | E10: 0 | F10: 0 | G10: 6.9702262
C11: AMUNDI UNICREDIT PREM PORT- PRUDENTIAL | D11: -0.79892258 | E11: -0.10659029 | F11: -0.82641419 | G11: 7.4952658
B12: Equity | D12: -14.921085 | E12: -0.12510663 | F12: -18.078061 | G12: 119.26695
C13: Amundi Env and Climate Change Sol Fund | D13: -14.474434 | E13: -0.21895804 | F13: -14.474434 | G13: 66.105969
C14: PI INVESTMENT FUNDS - TACTICAL ALLOCATION FUND - H | D14: -0.44665158 | E14: -0.0084018691 | F14: -3.6036269 | G14: 53.160978
B15: Flexible | D15: -26.306785 | E15: -0.071493562 | F15: -32.02505 | G15: 367.9602
C16: Amundi Invensys Broad Bond Portfolio | D16: 0 | E16: 0 | F16: 3.4298218 | G16: 169.20099
C17: PI INVESTMENT FUNDS - DYNAMIC ALLOCATION FUND - E | D17: -26.306785 | E17: -0.13235506 | F17: -35.454872 | G17: 198.7592
B18: Growth | D18: 25.096397 | E18: 0.1442819 | F18: 27.735835 | G18: 173.94003
C19: AFS ICAV Planet ESG Dynamic | E19: #DIV/0!
C20: AMUNDI FUND SOLUTIONS - DIVERSIFIED GROWTH - A | D20: -1.1998128 | E20: -0.014313611 | F20: -1.8619051 | G20: 83.823204
C21: AMUNDI FUND SOLUTIONS - SABADELL URQUIJO CRECIMIENTO | D21: 0 | E21: 0 | F21: 0 | G21: 3.9275611
C22: AMUNDI UNICREDIT PREMIUM PORT - DYNAMIC | D22: -1.6565681 | E22: -0.028445535 | F22: 1.6449617 | G22: 58.236487
C23: AMUNDI-FUNDACION CAJA NAVARRA DYNAMIC | D23: 27.952778 | E23: 1 | F23: 27.952778 | G23: 27.952778
B24: Income | D24: -11.006052 | E24: -0.037418931 | F24: -16.633531 | G24: 294.13057
C25: Amundi Fund Solutions - Diversified Income Best Select 2022 | D25: -4.8674647 | E25: -0.035677734 | F25: -1.3859767 | G25: 136.42864
C26: PI INVESTMENT FUNDS - TACTICAL ALLOCATION PILLAR - E | D26: -6.1385868 | E26: -0.10307136 | F26: -15.268212 | G26: 59.556669
C27: THE TRUSTHOUSE FDN CPI+4% MULTI-AST PTF | D27: 0 | E27: 0 | F27: 0.02065766 | G27: 98.145265
B28: Moderate | D28: -9.826379 | E28: -0.022059036 | F28: -1.6296295 | G28: 445.45822
C29: AFS ICAV Planet ESG Balanced | E29: #DIV/0!
C30: AMUNDI FUND SOLUTIONS - BALANCED | D30: -4.4015434 | E30: -0.013584615 | F30: 0.85909412 | G30: 324.00944
C31: AMUNDI UNICREDIT PREM PORT- MULTI ASSET | D31: -5.4248356 | E31: -0.044667682 | F31: -2.4887237 | G31: 121.44878
B32: Risk Accumulation | D32: -335.01257 | E32: -0.18945034 | F32: -420.76862 | G32: 1768.3397
C33: AMUNDI SENTIERO SOSTENIBILE | D33: -10.126505 | E33: -0.034880113 | F33: -7.3314559 | G33: 290.32318
C34: AMUNDI SOLUZIONI ITALIA - PROGETTO AZIONE CAMBIAMENTO CLIMATICO - E | E34: #DIV/0!
C35: AMUNDI SOLUZIONI ITALIA - PROGETTO AZIONE CAMBIAMENTO CLIMATICO (II) - E | E35: #DIV/0!
C36: AMUNDI SOLUZIONI ITALIA - PROGETTO AZIONE INFRASTRUTTURE SOSTENIBILI | D36: -114.98841 | E36: -0.34309857 | F36: -138.67363 | G36: 335.14686
C37: AMUNDI SOLUZIONI ITALIA - PROGETTO AZIONE INFRASTRUTTURE SOSTENIBILI (II) | D37: -68.314788 | E37: -0.21387638 | F37: -89.223301 | G37: 319.41249
C38: AMUNDI SOLUZIONI ITALIA - PROGETTO AZIONE MEGATREND - E | E38: #DIV/0!
C39: AMUNDI SOLUZIONI ITALIA - PROGETTO AZIONE MEGATREND (II) - E | E39: #DIV/0!
C40: ASI - PROGETTO AZIONE ENERGY TRANSITION | D40: -75.897228 | E40: -0.16792157 | F40: -103.51484 | G40: 451.98023
C41: ASI - PROGETTO AZIONE ENERGY TRANSITION (II) | D41: -47.534278 | E41: -0.17102462 | F41: -63.884148 | G41: 277.93822
C42: ASI - PROGETTO AZIONE FUTURO GREEN | D42: -18.151357 | E42: -0.19405172 | F42: -18.141244 | G42: 93.538758
B43: Thematic | D43: -136.91224 | E43: -0.21014083 | F43: 118.68122 | G43: 651.52609
C44: AMUNDI ELITE THEMATIC MULTI ASSET | D44: -136.91224 | E44: -0.21014083 | F44: 118.68122 | G44: 651.52609
A45: Model | D45: -307.44577 | E45: -0.035126256 | F45: -88.065456 | G45: 8752.5917
B46: Capital Guaranteed | D46: -65.534486 | E46: -0.054219271 | F46: -44.165264 | G46: 1208.6936
C47: ASSET ALLOCATION MODEL PROTETTO 80 | D47: -3.0901017 | E47: -0.029158027 | F47: -2.123896 | G47: 105.97773
C48: CNP Dynamic Protection 80 | D48: -16.088829 | E48: -0.13770845 | F48: -15.428341 | G48: 116.83255
C49: CNP Protection 80 | D49: 0.36790654 | E49: 0.0037968506 | F49: 3.955401 | G49: 96.897819
C50: CNP THEMATIC PROTECTION 80 | D50: -10.521304 | E50: -0.053854848 | F50: -6.386983 | G50: 195.36411
C51: CRV Dynamic Protection 80 | D51: -25.728394 | E51: -0.092119539 | F51: -24.41432 | G51: 279.29356
C52: CRV Protection 80 | D52: 1.0206376 | E52: 0.0095545613 | F52: 5.150974 | G52: 106.82203
C53: CRV THEMATIC PROTECTION 80 | D53: -11.494401 | E53: -0.037379459 | F53: -4.918099 | G53: 307.50581
B54: Capital Protection | D54: -0.0873133 | E54: -0.012552394 | F54: -0.01984 | G54: 6.955908
C55: CAM Agosto | D55: -0.00162516 | E55: -0.011388807 | F55: -0.000375 | G55: 0.142698
C56: CAM Aprile | D56: -0.00150589 | E56: -0.017266411 | F56: -0.000764 | G56: 0.087215
C57: CAM Dicembre | D57: -0.0705992 | E57: -0.014493048 | F57: -0.020159 | G57: 4.871246
C58: CAM Febbraio | D58: -0.00208783 | E58: -0.0061184521 | F58: 0.000404 | G58: 0.341235
C59: CAM Gennaio | D59: -0.00174022 | E59: -0.0092674328 | F59: -0.000137 | G59: 0.187778
C60: CAM Giugno | D60: -0.00275801 | E60: -0.0043455401 | F60: 0.002991 | G60: 0.634676
C61: CAM Luglio | D61: 0 | E61: 0 | F61: -0.000775 | G61: 0.077561
C62: CAM Maggio | D62: -0.0016057 | E62: -0.011902538 | F62: -0.000323 | G62: 0.134904
C63: CAM Marzo | D63: -0.00164449 | E63: -0.010613173 | F63: -0.000266 | G63: 0.154948
C64: CAM Novembre | D64: -0.00195811 | E64: -0.007017913 | F64: 0.000944 | G64: 0.279016
C65: CAM Ottobre | D65: -0.001209 | E65: -0.043064757 | F65: -0.000946 | G65: 0.028074
C66: CAM Settembre | D66: -0.00057969 | E66: -0.035011777 | F66: -0.000434 | G66: 0.016557
B67: Conservative | D67: -20.27235 | E67: -0.030977101 | F67: -17.236822 | G67: 654.43018
C68: CAM ARES RISPARMIO OBBLIGAZ. M | D68: -0.56769213 | E68: -0.019174923 | F68: -0.338342 | G68: 29.605967
C69: CAM OBBLIGAZIONARIA EURO | D69: 0 | E69: 0 | F69: 0 | G69: 0.002649
C70: CAM REDDITO | D70: 0 | E70: 0 | F70: 0.000323 | G70: 0.083275
C71: CAM STEP ONE | D71: 0 | E71: 0 | F71: 0.001073 | G71: 0.078465
C72: CAM TREND 20 | D72: 0 | E72: 0 | F72: 0 | G72: 0.023564
C73: Life Program Bond | D73: -4.0474815 | E73: -0.046911973 | F73: -3.214771 | G73: 86.278219
C74: PL Euro Bond 1 to 3 years | D74: -4.6289986 | E74: -0.052858704 | F74: -3.879674 | G74: 87.573063
C75: PL Euro Bond over 3 years | D75: -0.18858553 | E75: -0.0015392059 | F75: 0.682015 | G75: 122.52132
C76: SAXO EUROPE | D76: -7.0611691 | E76: -0.036738718 | F76: -7.0611691 | G76: 192.19966
C77: UL CAUTA | D77: -0.52380645 | E77: -0.019179187 | F77: -0.286322 | G77: 27.311192
C78: UL PRUDENTE | D78: -0.66876387 | E78: -0.055587943 | F78: -0.65926 | G78: 12.030736
C79: UL PRUDENTE PIU | D79: -0.67315085 | E79: -0.043277629 | F79: -0.613315 | G79: 15.554245
C80: UL_Prudente ERGO | D80: 0 | E80: #DIV/0! | F80: 0 | G80: 0
C81: UL_Prudente_+ ERGO | D81: 0 | E81: #DIV/0! | F81: 0 | G81: 0
C82: UNIT LINKED E2 NEW | D82: -0.35063568 | E82: -0.046038932 | F82: -0.30473 | G82: 7.616069
C83: UNIT LINKED E3 NEW | D83: -1.3791577 | E83: -0.01902696 | F83: -1.380437 | G83: 72.484395
C84: Unit Linked OLD 4 | D84: -0.18290859 | E84: -0.17136526 | F84: -0.182213 | G84: 1.067361
B85: Equity | D85: -35.848827 | E85: -0.011128298 | F85: 100.7319 | G85: 3221.4115
C86: Life Program Azionario Pacifico | D86: -0.07499342 | E86: -0.0016176138 | F86: -3.400871 | G86: 46.360523
C87: UL Global Equity Dividend & Subordinated | D87: -32.352755 | E87: -0.017016556 | F87: 23.919048 | G87: 1901.2516
C88: Unidiamond + Azionaria America | D88: 1.0081119 | E88: 0.00091645996 | F88: 79.886841 | G88: 1100.0065
C89: Unidiamond + Azionaria Intl | D89: -4.4291905 | E89: -0.025485451 | F89: 0.32688 | G89: 173.7929
B90: Flexible | D90: -130.64609 | E90: -0.10657308 | F90: -120.7386 | G90: 1225.8827
C91: Life Program Flessibile | D91: -0.91659172 | E91: -0.036929678 | F91: -0.811947 | G91: 24.819922
C92: PL Income Clock | D92: -0.37310856 | E92: -0.011087135 | F92: -0.299069 | G92: 33.652386
C93: Unit Linked A TR UNIPLAN | D93: -0.64437376 | E93: -0.05247151 | F93: -0.616815 | G93: 12.28045
C94: Univalore E Strategia 20 | D94: -1.6527144 | E94: -0.071718237 | F94: -1.465146 | G94: 23.044548
C95: Univalore E Strategia 30 | D95: -17.940994 | E95: -0.076455918 | F95: -16.022861 | G95: 234.65801
C96: Univalore E Strategia 40 | D96: -1.6815718 | E96: -0.094877472 | F96: -1.488772 | G96: 17.723615
C97: Univalore E Strategia 70 | D97: -40.659051 | E97: -0.12363967 | F97: -37.621934 | G97: 328.85118
C98: Univalore Stars Balanced | D98: -66.777687 | E98: -0.12122605 | F98: -62.412056 | G98: 550.8526
B99: Growth | D99: -11.94981 | E99: -0.026006461 | F99: 4.694794 | G99: 459.49391
C100: CAM ARES RISPARMIO ATTIVO M | D100: -8.0966316 | E100: -0.028292845 | F100: 9.459997 | G100: 286.17241
C101: CAM CNP - LINEA DINAMICA | D101: -0.44445929 | E101: -0.021809483 | F101: 0.014288 | G101: 20.379176
C102: CAM CRESCITA | D102: -0.0194731 | E102: -0.015466245 | F102: 0.032879 | G102: 1.259071
...

Sheet Startegy Changes (Model Fund)
A3: Fund or Model | B3: Strategy Detail | C3: Flows mln € | D3: % Change Flows | E3: Change In AUM mlnl €
A4: Fund | C4: -519.25036 | D4: -0.12505604 | E4: -350.87
B5: Bond | C5: -2.9774607 | D5: -0.04010165 | E5: -2.9849541
B6: Conservative | C6: -7.3841967 | D6: -0.028701929 | E6: -5.1672111
B7: Equity | C7: -14.921085 | D7: -0.12510663 | E7: -18.078061
B8: Flexible | C8: -26.306785 | D8: -0.071493562 | E8: -32.02505
B9: Growth | C9: 25.096397 | D9: 0.1442819 | E9: 27.735835
B10: Income | C10: -11.006052 | D10: -0.037418931 | E10: -16.633531
B11: Moderate | C11: -9.826379 | D11: -0.022059036 | E11: -1.6296295
B12: Risk Accumulation | C12: -335.01257 | D12: -0.18945034 | E12: -420.76862
B13: Thematic | C13: -136.91224 | D13: -0.21014083 | E13: 118.68122
A14: Model | C14: -307.44577 | D14: -0.035126256 | E14: -88.065456
B15: Capital Guaranteed | C15: -65.534486 | D15: -0.054219271 | E15: -44.165264
B16: Capital Protection | C16: -0.0873133 | D16: -0.012552394 | E16: -0.01984
B17: Conservative | C17: -20.27235 | D17: -0.030977101 | E17: -17.236822
B18: Equity | C18: -35.848827 | D18: -0.011128298 | E18: 100.7319
B19: Flexible | C19: -130.64609 | D19: -0.10657308 | E19: -120.7386
B20: Growth | C20: -11.94981 | D20: -0.026006461 | E20: 4.694794
B21: Income | C21: -54.349645 | D21: -0.086591532 | E21: -57.063289
B22: Moderate | C22: -3.712064 | D22: -0.021657603 | E22: -2.638989
B23: Risk Accumulation | C23: -0.6752106 | D23: -0.14351059 | E23: -0.468905
B24: Thematic | C24: 15.630024 | D24: 0.013336587 | E24: 48.83956
A25: Grand Total | C25: -826.69614 | D25: -0.064061467 | E25: -438.93546

Sheet Startegy Changes (List)
A3: Strategy Detail | B3: Portfolios name | C3: Flows mln € | D3: Sum of % Change Flows | E3: Difference In AUM mln € | F3: Total AUM | I3: FILTER?
A4: Bond | C4: -2.9774607 | D4: -0.04010165 | E4: -2.9849541 | F4: 74.247836
A5: Capital Guaranteed | C5: -65.534486 | D5: -0.054219271 | E5: -44.165264 | F5: 1208.6936
A6: Conservative | C6: -14.969172 | D6: -0.031862019 | E6: -12.514702 | F6: 469.81242
A7: Equity | C7: -47.273841 | D7: -0.023396885 | E7: 5.8409874 | F7: 2020.5186
A8: Flexible | C8: -155.0188 | D8: -0.11449889 | E8: -154.46564 | F8: 1353.8892
A9: Growth | C9: 24.190522 | D9: 0.12862072 | E9: 26.785796 | F9: 188.07641
A10: Income | C10: -65.355696 | D10: -0.072314772 | E10: -71.062351 | F10: 903.76689
A11: Moderate | C11: -10.440492 | D11: -0.022897047 | E11: -2.2270415 | F11: 455.97545
A12: Risk Accumulation | C12: -335.35307 | D12: -0.18913966 | E12: -421.23752 | F12: 1773.0447
A13: Thematic | C13: -121.28221 | D13: -0.066860853 | E13: 172.16372 | F13: 1813.9495
N56: 6.7471388e+08
N57: 7.0898621e+08
N58: =N56-N57 -> -34272339

Sheet AUM Data Sheet Dublin
A1: Original | B1: Added | C1: Original | D1: Added | E1: Added | F1: Added | G1: Added | H1: Added | I1: Added | J1: Added | K1: Original | L1: Original | M1: Original | N1: Original | O1: Original | P1: Added | Q1: Added | R1: Added | S1: Added | T1: Added | U1: Added | Y1: Added
A2: Decalog ID | B2: Yes or No | C2: Portfolios name | D2: Fund or Model | E2: On Original Risk List or Added by Ronan? | F2: On a List? | G2: Strategy Type | H2: Strategy Detail | I2: Macro Process | J2: Micro Process | K2: Investment team | L2: Portfolio Manager | M2: Family of Investment strategy | N2: Micro risk process name | O2: AuM in Audit File | P2: AUM from our AUM 30 April 2020 file | Q2: Ronan Comment | R2: Aum from Jun file Old | S2: Aum from Jun file | T2: Flows April | U2: AUM from our AUM 31st March 2020 file | V2: AUM from our AUM Feb 2020 file in mln * | W2: Difference | X2: Difference final | Y2: AUM from our AUM April 2020 file in mln* | Z2: Difference In AUM | AA2: Flows April mln | AB2: AUM from our AUM April 2020 file Test | AC2: AUM from our AUM Feb 2019 file Test | AD2: Difference Between Feb 2019 - April 2020
A3: E142 | B3: Yes | C3: AMUNDI FUND SOLUTIONS - BALANCED | D3: Fund | E3: On Original Risk List | F3: =VLOOKUP($A3,'[1]Dublin funds'!$B$2:$AS$153,2,FALSE) -> From Risk - Fund Responsibility - Dublin Funds | G3: =VLOOKUP($A3,'[2]Total AUM Data'!$A:$I,5,FALSE) -> Allocation Driven Strategies | H3: =VLOOKUP($A3,'[2]Total AUM Data'!$A:$I,6,FALSE) -> Moderate | I3: =VLOOKUP($A3,'[1]Dublin funds'!$B$2:$AS$153,3,FALSE) -> BAL Multimanagement | J3: =VLOOKUP($A3,'[1]Dublin funds'!$B$2:$AS$153,4,FALSE) -> DUB BAL Multimanagement SDA Fds de Fds | K3: AMUNDI.IRL/INV/MAS | L3: O'TOOLE JOHN | M3: Global - Global Balanced 50 | N3: DUB BAL Multimanagement SDA Fds de Fds | O3: =VLOOKUP(A3,'Audit AUM File'!A:B,2,FALSE) -> 1.7612646e+08 | P3: =VLOOKUP(A3,[3]AUM!$A$3:$B$131,2,0) -> 3.2400944e+08 | R3: =+IF(D3="",VLOOKUP(A3,'[2]Pivot for Jun AUM'!$A$5:$B$121,2,FALSE)) -> FALSE | S3: =+IF(D3<>"",VLOOKUP(A3,'[2]Total AUM Data'!$A$2:$G$48,7,FALSE)) -> 1.6934677e+08 | T3: =VLOOKUP(A3,[4]Flows!$A$3:$D$1206,4,0) -> -4401543.4 | U3: =VLOOKUP(A3,'[3]Last Aum File'!$A$2:$B$128,2,0) -> 3.2315034e+08 | V3: =+U3/1000000 -> 323.15034 | W3: =+IF(OR(A3="HF11",A3="PACIFAI"),0,IF(A3="MUSG",P3-U3/2,P3-U3)) -> 859094.12 | X3: =+IF(ISNA(W3),0,W3) -> 859094.12 | Y3: =P3/1000000 -> 324.00944 | Z3: =X3/1000000 -> 0.85909412 | AA3: =T3/1000000 -> -4.4015434 | AB3: =VLOOKUP(A3,[3]AUM!$A$3:$B$131,2,0)/1000000 -> 324.00944 | AC3: =VLOOKUP(A3,'[3]Last Aum File'!$A$2:$B$126,2,0)/1000000 -> 323.15034 | AD3: =AB3-AC3 -> 0.85909412
A4: E143 | B4: Yes | C4: AMUNDI FUND SOLUTIONS - CONSERVATIVE | D4: Fund | E4: On Original Risk List | F4: =VLOOKUP(A4,'[1]Dublin funds'!$B$2:$AS$153,2,FALSE) -> From Risk - Fund Responsibility - Dublin Funds | G4: =VLOOKUP($A4,'[2]Total AUM Data'!$A:$I,5,FALSE) -> Allocation Driven Strategies | H4: =VLOOKUP($A4,'[2]Total AUM Data'!$A:$I,6,FALSE) -> Conservative | I4: =VLOOKUP($A4,'[1]Dublin funds'!$B$2:$AS$153,3,FALSE) -> BAL Multimanagement | J4: =VLOOKUP($A4,'[1]Dublin funds'!$B$2:$AS$153,4,FALSE) -> DUB BAL Multimanagement SDA Fds de Fds | K4: AMUNDI.IRL/INV/MAS | L4: O'TOOLE JOHN | M4: Global - Balanced Global Defensive 20 | N4: DUB BAL Multimanagement SDA Fds de Fds | O4: =VLOOKUP(A4,'Audit AUM File'!A:B,2,FALSE) -> 2.0056959e+08 | P4: =VLOOKUP(A4,[3]AUM!$A$3:$B$131,2,0) -> 2.428063e+08 | R4: =+IF(D4="",VLOOKUP(A4,'[2]Pivot for Jun AUM'!$A$5:$B$121,2,FALSE)) -> FALSE | S4: =+IF(D4<>"",VLOOKUP(A4,'[2]Total AUM Data'!$A$2:$G$48,7,FALSE)) -> 1.9155414e+08 | T4: =VLOOKUP(A4,[4]Flows!$A$3:$D$1206,4,0) -> -6585274.1 | U4: =VLOOKUP(A4,'[3]Last Aum File'!$A$2:$B$128,2,0) -> 2.471471e+08 | V4: =+U4/1000000 -> 247.1471 | W4: =+IF(OR(A4="HF11",A4="PACIFAI"),0,IF(A4="MUSG",P4-U4/2,P4-U4)) -> -4340796.9 | X4: =+IF(ISNA(W4),0,W4) -> -4340796.9 | Y4: =P4/1000000 -> 242.8063 | Z4: =X4/1000000 -> -4.3407969 | AA4: =T4/1000000 -> -6.5852741 | AB4: =VLOOKUP(A4,[3]AUM!$A$3:$B$131,2,0)/1000000 -> 242.8063 | AC4: =VLOOKUP(A4,'[3]Last Aum File'!$A$2:$B$126,2,0)/1000000 -> 247.1471 | AD4: =AB4-AC4 -> -4.3407969
A5: E144 | B5: Yes | C5: AMUNDI FUND SOLUTIONS - DIVERSIFIED GROWTH - A | D5: Fund | E5: On Original Risk List | F5: =VLOOKUP(A5,'[1]Dublin funds'!$B$2:$AS$153,2,FALSE) -> From Risk - Fund Responsibility - Dublin Funds | G5: =VLOOKUP($A5,'[2]Total AUM Data'!$A:$I,5,FALSE) -> Allocation Driven Strategies | H5: =VLOOKUP($A5,'[2]Total AUM Data'!$A:$I,6,FALSE) -> Growth | I5: =VLOOKUP($A5,'[1]Dublin funds'!$B$2:$AS$153,3,FALSE) -> BAL Multimanagement | J5: =VLOOKUP($A5,'[1]Dublin funds'!$B$2:$AS$153,4,FALSE) -> AMU BAL SDA Fds de Fds (used some absolute limits with High Rik with Equity exposure 0/120% and currency exposure up to 100% | K5: AMUNDI.IRL/INV/MAS | L5: O'TOOLE JOHN | M5: Multi Asset - Diversified Growth | N5: DUB BAL Multimanagement SDA Fds de Fds | O5: =VLOOKUP(A5,'Audit AUM File'!A:B,2,FALSE) -> 68345862 | P5: =VLOOKUP(A5,[3]AUM!$A$3:$B$131,2,0) -> 83823204 | R5: =+IF(D5="",VLOOKUP(A5,'[2]Pivot for Jun AUM'!$A$5:$B$121,2,FALSE)) -> FALSE | S5: =+IF(D5<>"",VLOOKUP(A5,'[2]Total AUM Data'!$A$2:$G$48,7,FALSE)) -> 66139609 | T5: =VLOOKUP(A5,[4]Flows!$A$3:$D$1206,4,0) -> -1199812.8 | U5: =VLOOKUP(A5,'[3]Last Aum File'!$A$2:$B$128,2,0) -> 85685109 | V5: =+U5/1000000 -> 85.685109 | W5: =+IF(OR(A5="HF11",A5="PACIFAI"),0,IF(A5="MUSG",P5-U5/2,P5-U5)) -> -1861905.1 | X5: =+IF(ISNA(W5),0,W5) -> -1861905.1 | Y5: =P5/1000000 -> 83.823204 | Z5: =X5/1000000 -> -1.8619051 | AA5: =T5/1000000 -> -1.1998128 | AB5: =VLOOKUP(A5,[3]AUM!$A$3:$B$131,2,0)/1000000 -> 83.823204 | AC5: =VLOOKUP(A5,'[3]Last Aum File'!$A$2:$B$126,2,0)/1000000 -> 85.685109 | AD5: =AB5-AC5 -> -1.8619051
A6: PF101376 | B6: Yes | C6: AFS ICAV Planet ESG Balanced | D6: Fund | E6: On Original Risk List | F6: From Risk - Fund Responsibility - Dublin Funds | G6: Allocation Driven Strategies | H6: Moderate | I6: BAL Multimanagement | J6: DUB BAL Multimanagement SDA Fds de Fds | K6: AMUNDI.IRL/INV/MAS | L6: O'TOOLE JOHN | M6: Global - Global Balanced 50 | N6: DUB BAL Multimanagement SDA Fds de Fds | R6: =+IF(D6="",VLOOKUP(A6,'[2]Pivot for Jun AUM'!$A$5:$B$121,2,FALSE)) -> FALSE
A7: PF101372 | B7: Yes | C7: AFS ICAV Planet ESG Conservative | D7: Fund | E7: On Original Risk List | F7: From Risk - Fund Responsibility - Dublin Funds | G7: Allocation Driven Strategies | H7: Conservative | I7: BAL Multimanagement | J7: DUB BAL Multimanagement SDA Fds de Fds | K7: AMUNDI.IRL/INV/MAS | L7: O'TOOLE JOHN | M7: Global - Balanced Global Defensive 20 | N7: DUB BAL Multimanagement SDA Fds de Fds | R7: =+IF(D7="",VLOOKUP(A7,'[2]Pivot for Jun AUM'!$A$5:$B$121,2,FALSE)) -> FALSE
A8: PF101380 | B8: Yes | C8: AFS ICAV Planet ESG Dynamic | D8: Fund | E8: On Original Risk List | F8: From Risk - Fund Responsibility - Dublin Funds | G8: Allocation Driven Strategies | H8: Growth | I8: BAL Multimanagement | J8: AMU BAL SDA Fds de Fds (used some absolute limits with High Rik with Equity exposure 0/120% and currency exposure up to 100% | K8: AMUNDI.IRL/INV/MAS | L8: O'TOOLE JOHN | M8: Multi Asset - Diversified Growth | N8: DUB BAL Multimanagement SDA Fds de Fds | R8: =+IF(D8="",VLOOKUP(A8,'[2]Pivot for Jun AUM'!$A$5:$B$121,2,FALSE)) -> FALSE
A9: PF78195 | B9: Yes | C9: AMUNDI SOLUZIONI ITALIA - PROGETTO AZIONE CAMBIAMENTO CLIMATICO - E | D9: Fund | E9: On Original Risk List | F9: =VLOOKUP(A9,'[1]Dublin funds'!$B$2:$AS$153,2,FALSE) -> From Risk - Fund Responsibility - Dublin Funds | G9: =VLOOKUP($A9,'[2]Total AUM Data'!$A:$I,5,FALSE) -> Outcome Oriented Strategies | H9: =VLOOKUP($A9,'[2]Total AUM Data'!$A:$I,6,FALSE) -> Risk Accumulation | I9: =VLOOKUP($A9,'[1]Dublin funds'!$B$2:$AS$153,3,FALSE) -> EFI Absolute Return | J9: =VLOOKUP($A9,'[1]Dublin funds'!$B$2:$AS$153,4,FALSE) -> DUB EFI Absolute Return Aggregate | K9: AMUNDI.IRL/INV/MAS | L9: O'TOOLE JOHN | M9: To be Affected | N9: DUB EFI Absolute Return Aggregate | O9: =VLOOKUP(A9,'Audit AUM File'!A:B,2,FALSE) -> 3.362137e+08 | R9: =+IF(D9="",VLOOKUP(A9,'[2]Pivot for Jun AUM'!$A$5:$B$121,2,FALSE)) -> FALSE | S9: =+IF(D9<>"",VLOOKUP(A9,'[2]Total AUM Data'!$A$2:$G$48,7,FALSE)) -> 3.3503735e+08
A10: PF103025 | B10: Yes | C10: ASI - PROGETTO AZIONE FUTURO GREEN | D10: Fund | E10: On Original Risk List | F10: From Risk - Fund Responsibility - Dublin Funds | G10: Outcome Oriented Strategies | H10: Risk Accumulation | K10: AMUNDI.IRL/INV/MAS/PMG/PMG | L10: CASEY RICHARD | M10: To be Affected | P10: =VLOOKUP(A10,[3]AUM!$A$3:$B$131,2,0) -> 93538758 | T10: =VLOOKUP(A10,[4]Flows!$A$3:$D$1206,4,0) -> -18151357 | U10: =VLOOKUP(A10,'[3]Last Aum File'!$A$2:$B$128,2,0) -> 1.1168e+08 | V10: =+U10/1000000 -> 111.68 | W10: =+IF(OR(A10="HF11",A10="PACIFAI"),0,IF(A10="MUSG",P10-U10/2,P10-U10)) -> -18141244 | X10: =+IF(ISNA(W10),0,W10) -> -18141244 | Y10: =P10/1000000 -> 93.538758 | Z10: =X10/1000000 -> -18.141244 | AA10: =T10/1000000 -> -18.151357 | AB10: =VLOOKUP(A10,[3]AUM!$A$3:$B$131,2,0)/1000000 -> 93.538758
A11: E118 | B11: Yes | C11: AMUNDI UNICREDIT PREM PORT- PRUDENTIAL | D11: Fund | E11: On Original Risk List | F11: =VLOOKUP(A11,'[1]Dublin funds'!$B$2:$AS$153,2,FALSE) -> From Risk - Fund Responsibility - Dublin Funds | G11: =VLOOKUP($A11,'[2]Total AUM Data'!$A:$I,5,FALSE) -> Allocation Driven Strategies | H11: =VLOOKUP($A11,'[2]Total AUM Data'!$A:$I,6,FALSE) -> Conservative | I11: =VLOOKUP($A11,'[1]Dublin funds'!$B$2:$AS$153,3,FALSE) -> BAL Multimanagement | J11: =VLOOKUP($A11,'[1]Dublin funds'!$B$2:$AS$153,4,FALSE) -> DUB BAL Multimanagement SDA Fds de Fds | K11: AMUNDI.IRL/INV/MAS | L11: O'TOOLE JOHN | M11: Bond - myNext | N11: DUB BAL Multimanagement SDA Fds de Fds | O11: =VLOOKUP(A11,'Audit AUM File'!A:B,2,FALSE) -> 31835018 | P11: =VLOOKUP(A11,[3]AUM!$A$3:$B$131,2,0) -> 7495265.8 | R11: =+IF(D11="",VLOOKUP(A11,'[2]Pivot for Jun AUM'!$A$5:$B$121,2,FALSE)) -> FALSE | S11: =+IF(D11<>"",VLOOKUP(A11,'[2]Total AUM Data'!$A$2:$G$48,7,FALSE)) -> 33826169 | T11: =VLOOKUP(A11,[4]Flows!$A$3:$D$1206,4,0) -> -798922.58 | U11: =VLOOKUP(A11,'[3]Last Aum File'!$A$2:$B$128,2,0) -> 8321680 | V11: =+U11/1000000 -> 8.32168 | W11: =+IF(OR(A11="HF11",A11="PACIFAI"),0,IF(A11="MUSG",P11-U11/2,P11-U11)) -> -826414.19 | X11: =+IF(ISNA(W11),0,W11) -> -826414.19 | Y11: =P11/1000000 -> 7.4952658 | Z11: =X11/1000000 -> -0.82641419 | AA11: =T11/1000000 -> -0.79892258 | AB11: =VLOOKUP(A11,[3]AUM!$A$3:$B$131,2,0)/1000000 -> 7.4952658 | AC11: =VLOOKUP(A11,'[3]Last Aum File'!$A$2:$B$126,2,0)/1000000 -> 8.32168 | AD11: =AB11-AC11 -> -0.82641419
A12: E119 | B12: Yes | C12: AMUNDI UNICREDIT PREMIUM PORT - DYNAMIC | D12: Fund | E12: On Original Risk List | F12: =VLOOKUP(A12,'[1]Dublin funds'!$B$2:$AS$153,2,FALSE) -> From Risk - Fund Responsibility - Dublin Funds | G12: =VLOOKUP($A12,'[2]Total AUM Data'!$A:$I,5,FALSE) -> Allocation Driven Strategies | H12: =VLOOKUP($A12,'[2]Total AUM Data'!$A:$I,6,FALSE) -> Growth | I12: =VLOOKUP($A12,'[1]Dublin funds'!$B$2:$AS$153,3,FALSE) -> BAL Multimanagement | J12: =VLOOKUP($A12,'[1]Dublin funds'!$B$2:$AS$153,4,FALSE) -> DUB BAL Multimanagement SDA Fds de Fds | K12: AMUNDI.IRL/INV/MAS | L12: O'TOOLE JOHN | M12: Equity - myNext | N12: DUB BAL Multimanagement SDA Fds de Fds | O12: =VLOOKUP(A12,'Audit AUM File'!A:B,2,FALSE) -> 96972832 | P12: =VLOOKUP(A12,[3]AUM!$A$3:$B$131,2,0) -> 58236487 | R12: =+IF(D12="",VLOOKUP(A12,'[2]Pivot for Jun AUM'!$A$5:$B$121,2,FALSE)) -> FALSE | S12: =+IF(D12<>"",VLOOKUP(A12,'[2]Total AUM Data'!$A$2:$G$48,7,FALSE)) -> 1.0325593e+08 | T12: =VLOOKUP(A12,[4]Flows!$A$3:$D$1206,4,0) -> -1656568.1 | U12: =VLOOKUP(A12,'[3]Last Aum File'!$A$2:$B$128,2,0) -> 56591526 | V12: =+U12/1000000 -> 56.591526 | W12: =+IF(OR(A12="HF11",A12="PACIFAI"),0,IF(A12="MUSG",P12-U12/2,P12-U12)) -> 1644961.7 | X12: =+IF(ISNA(W12),0,W12) -> 1644961.7 | Y12: =P12/1000000 -> 58.236487 | Z12: =X12/1000000 -> 1.6449617 | AA12: =T12/1000000 -> -1.6565681 | AB12: =VLOOKUP(A12,[3]AUM!$A$3:$B$131,2,0)/1000000 -> 58.236487 | AC12: =VLOOKUP(A12,'[3]Last Aum File'!$A$2:$B$126,2,0)/1000000 -> 56.591526 | AD12: =AB12-AC12 -> 1.6449617
A13: E120 | B13: Yes | C13: AMUNDI UNICREDIT PREM PORT- MULTI ASSET | D13: Fund | E13: On Original Risk List | F13: =VLOOKUP(A13,'[1]Dublin funds'!$B$2:$AS$153,2,FALSE) -> From Risk - Fund Responsibility - Dublin Funds | G13: =VLOOKUP($A13,'[2]Total AUM Data'!$A:$I,5,FALSE) -> Allocation Driven Strategies | H13: =VLOOKUP($A13,'[2]Total AUM Data'!$A:$I,6,FALSE) -> Moderate | I13: =VLOOKUP($A13,'[1]Dublin funds'!$B$2:$AS$153,3,FALSE) -> BAL Multimanagement | J13: =VLOOKUP($A13,'[1]Dublin funds'!$B$2:$AS$153,4,FALSE) -> DUB BAL Multimanagement SDA Fds de Fds | K13: AMUNDI.IRL/INV/MAS | L13: O'TOOLE JOHN | M13: Multi Asset - myNext | N13: DUB BAL Multimanagement SDA Fds de Fds | O13: =VLOOKUP(A13,'Audit AUM File'!A:B,2,FALSE) -> 2.8861759e+08 | P13: =VLOOKUP(A13,[3]AUM!$A$3:$B$131,2,0) -> 1.2144878e+08 | R13: =+IF(D13="",VLOOKUP(A13,'[2]Pivot for Jun AUM'!$A$5:$B$121,2,FALSE)) -> FALSE | S13: =+IF(D13<>"",VLOOKUP(A13,'[2]Total AUM Data'!$A$2:$G$48,7,FALSE)) -> 3.124575e+08 | T13: =VLOOKUP(A13,[4]Flows!$A$3:$D$1206,4,0) -> -5424835.6 | U13: =VLOOKUP(A13,'[3]Last Aum File'!$A$2:$B$128,2,0) -> 1.2393751e+08 | V13: =+U13/1000000 -> 123.93751 | W13: =+IF(OR(A13="HF11",A13="PACIFAI"),0,IF(A13="MUSG",P13-U13/2,P13-U13)) -> -2488723.7 | X13: =+IF(ISNA(W13),0,W13) -> -2488723.7 | Y13: =P13/1000000 -> 121.44878 | Z13: =X13/1000000 -> -2.4887237 | AA13: =T13/1000000 -> -5.4248356 | AB13: =VLOOKUP(A13,[3]AUM!$A$3:$B$131,2,0)/1000000 -> 121.44878 | AC13: =VLOOKUP(A13,'[3]Last Aum File'!$A$2:$B$126,2,0)/1000000 -> 123.93751 | AD13: =AB13-AC13 -> -2.4887237
A14: PF115036 | C14: THE TRUSTHOUSE FDN CPI+4% MULTI-AST PTF | D14: Fund | G14: Outcome Oriented Strategies | H14: Income | P14: =VLOOKUP(A14,[3]AUM!$A$3:$B$131,2,0) -> 98145265 | T14: =VLOOKUP(A14,[4]Flows!$A$3:$D$1206,4,0) -> 0 | U14: =VLOOKUP(A14,'[3]Last Aum File'!$A$2:$B$1262,2,0) -> 98124607 | V14: =+U14/1000000 -> 98.124607 | W14: =+IF(OR(A14="HF11",A14="PACIFAI"),0,IF(A14="MUSG",P14-U14/2,P14-U14)) -> 20657.66 | X14: =+IF(ISNA(W14),0,W14) -> 20657.66 | Y14: =P14/1000000 -> 98.145265 | Z14: =X14/1000000 -> 0.02065766 | AA14: =T14/1000000 -> 0 | AB14: =VLOOKUP(A14,[3]AUM!$A$3:$B$131,2,0)/1000000 -> 98.145265 | AC14: =VLOOKUP(A14,'[3]Last Aum File'!$A$2:$B$126,2,0)/1000000 -> 98.124607 | AD14: =AB14-AC14 -> 0.02065766
A15: PF204806 | C15: AMUNDI-FUNDACION CAJA NAVARRA DYNAMIC | D15: Fund | G15: Allocation Driven Strategies | H15: Growth | P15: =VLOOKUP(A15,[3]AUM!$A$3:$B$131,2,0) -> 27952778 | T15: =P15 -> 27952778 | V15: =+U15/1000000 -> 0 | W15: =+IF(OR(A15="HF11",A15="PACIFAI"),0,IF(A15="MUSG",P15-U15/2,P15-U15)) -> 27952778 | X15: =+IF(ISNA(W15),0,W15) -> 27952778 | Y15: =P15/1000000 -> 27.952778 | Z15: =X15/1000000 -> 27.952778 | AA15: =T15/1000000 -> 27.952778 | AB15: =VLOOKUP(A15,[3]AUM!$A$3:$B$131,2,0)/1000000 -> 27.952778 | AD15: =AB15-AC15 -> 27.952778
A16: PF88524 | B16: Yes | C16: AMUNDI ELITE THEMATIC MULTI ASSET | D16: Fund | E16: On Original Risk List | F16: From Risk - Fund Responsibility - Dublin Funds | G16: Outcome Oriented Strategies | H16: Thematic | I16: BAL Multimanagement | J16: AMU BAL SDA Fds de Fds (used absolute limits High risk) | K16: AMUNDI.IRL/INV/MAS | L16: O'TOOLE JOHN | M16: AMUNDI ELITE THEMATIC MULTI ASSET | N16: DUB BAL Multimanagement SDA Fds de Fds | P16: =VLOOKUP(A16,[3]AUM!$A$3:$B$131,2,0) -> 6.5152609e+08 | R16: =+IF(D16="",VLOOKUP(A16,'[2]Pivot for Jun AUM'!$A$5:$B$121,2,FALSE)) -> FALSE | T16: =VLOOKUP(A16,[4]Flows!$A$3:$D$1206,4,0) -> -1.3691224e+08 | U16: =VLOOKUP(A16,'[3]Last Aum File'!$A$2:$B$128,2,0) -> 5.3284487e+08 | V16: =+U16/1000000 -> 532.84487 | W16: =+IF(OR(A16="HF11",A16="PACIFAI"),0,IF(A16="MUSG",P16-U16/2,P16-U16)) -> 1.1868122e+08 | X16: =+IF(ISNA(W16),0,W16) -> 1.1868122e+08 | Y16: =P16/1000000 -> 651.52609 | Z16: =X16/1000000 -> 118.68122 | AA16: =T16/1000000 -> -136.91224 | AB16: =VLOOKUP(A16,[3]AUM!$A$3:$B$131,2,0)/1000000 -> 651.52609 | AC16: =VLOOKUP(A16,'[3]Last Aum File'!$A$2:$B$126,2,0)/1000000 -> 532.84487 | AD16: =AB16-AC16 -> 118.68122
A17: E209 | B17: Yes | C17: PI INVESTMENT FUNDS - DYNAMIC ALLOCATION FUND - E | D17: Fund | E17: On Original Risk List | F17: =VLOOKUP(A17,'[1]Dublin funds'!$B$2:$AS$153,2,FALSE) -> From Risk - Fund Responsibility - Dublin Funds | G17: =VLOOKUP($A17,'[2]Total AUM Data'!$A:$I,5,FALSE) -> Service Fund | H17: =VLOOKUP($A17,'[2]Total AUM Data'!$A:$I,6,FALSE) -> Flexible | I17: =VLOOKUP($A17,'[1]Dublin funds'!$B$2:$AS$153,3,FALSE) -> TBD | J17: =VLOOKUP($A17,'[1]Dublin funds'!$B$2:$AS$153,4,FALSE) -> Agreed a light touch with VaR and Leverage limits | K17: AMUNDI.IRL/INV/MAS/PMG | L17: BUONO SALVATORE | M17: To be Affected | N17: To Be Determined | O17: =VLOOKUP(A17,'Audit AUM File'!A:B,2,FALSE) -> 6.2364273e+08 | P17: =VLOOKUP(A17,[3]AUM!$A$3:$B$131,2,0) -> 1.987592e+08 | R17: =+IF(D17="",VLOOKUP(A17,'[2]Pivot for Jun AUM'!$A$5:$B$121,2,FALSE)) -> FALSE | S17: =+IF(D17<>"",VLOOKUP(A17,'[2]Total AUM Data'!$A$2:$G$48,7,FALSE)) -> 4.0254202e+08 | T17: =VLOOKUP(A17,[4]Flows!$A$3:$D$1206,4,0) -> -26306785 | U17: =VLOOKUP(A17,'[3]Last Aum File'!$A$2:$B$128,2,0) -> 2.3421407e+08 | V17: =+U17/1000000 -> 234.21407 | W17: =+IF(OR(A17="HF11",A17="PACIFAI"),0,IF(A17="MUSG",P17-U17/2,P17-U17)) -> -35454872 | X17: =+IF(ISNA(W17),0,W17) -> -35454872 | Y17: =P17/1000000 -> 198.7592 | Z17: =X17/1000000 -> -35.454872 | AA17: =T17/1000000 -> -26.306785 | AB17: =VLOOKUP(A17,[3]AUM!$A$3:$B$131,2,0)/1000000 -> 198.7592 | AC17: =VLOOKUP(A17,'[3]Last Aum File'!$A$2:$B$126,2,0)/1000000 -> 234.21407 | AD17: =AB17-AC17 -> -35.454872
A18: PF87100 | B18: Yes | C18: AMUNDI FUND SOLUTIONS - SABADELL URQUIJO ACUMULACION | D18: Fund | E18: On Original Risk List | F18: From Risk - Fund Responsibility - Dublin Funds | G18: Allocation Driven Strategies | H18: Conservative | I18: BAL Multimanagement | J18: DUB BAL Multimanagement SDA Fds de Fds | K18: AMUNDI.IRL/INV/MAS | L18: O'TOOLE JOHN | M18: Global - Balanced Global Defensive 20 | N18: DUB BAL Multimanagement SDA Fds de Fds | P18: =VLOOKUP(A18,[3]AUM!$A$3:$B$131,2,0) -> 6970226.2 | R18: =+IF(D18="",VLOOKUP(A18,'[2]Pivot for Jun AUM'!$A$5:$B$121,2,FALSE)) -> FALSE | T18: =VLOOKUP(A18,[4]Flows!$A$3:$D$1206,4,0) -> 0 | U18: =VLOOKUP(A18,'[3]Last Aum File'!$A$2:$B$128,2,0) -> 6970226.2 | V18: =+U18/1000000 -> 6.9702262 | W18: =+IF(OR(A18="HF11",A18="PACIFAI"),0,IF(A18="MUSG",P18-U18/2,P18-U18)) -> 0 | X18: =+IF(ISNA(W18),0,W18) -> 0 | Y18: =P18/1000000 -> 6.9702262 | Z18: =X18/1000000 -> 0 | AA18: =T18/1000000 -> 0 | AB18: =VLOOKUP(A18,[3]AUM!$A$3:$B$131,2,0)/1000000 -> 6.9702262 | AC18: =VLOOKUP(A18,'[3]Last Aum File'!$A$2:$B$126,2,0)/1000000 -> 6.9702262 | AD18: =AB18-AC18 -> 0
A19: PF87115 | B19: Yes | C19: AMUNDI FUND SOLUTIONS - SABADELL URQUIJO CRECIMIENTO | D19: Fund | E19: On Original Risk List | F19: From Risk - Fund Responsibility - Dublin Funds | G19: Allocation Driven Strategies | H19: Growth | I19: BAL Multimanagement | J19: AMU BAL SDA Fds de Fds (used some absolute limits with High Rik with Equity exposure 0/120% and currency exposure up to 100% | K19: AMUNDI.IRL/INV/MAS | L19: O'TOOLE JOHN | M19: Multi Asset - Diversified Growth | N19: DUB BAL Multimanagement SDA Fds de Fds | P19: =VLOOKUP(A19,[3]AUM!$A$3:$B$131,2,0) -> 3927561.1 | R19: =+IF(D19="",VLOOKUP(A19,'[2]Pivot for Jun AUM'!$A$5:$B$121,2,FALSE)) -> FALSE | T19: =VLOOKUP(A19,[4]Flows!$A$3:$D$1206,4,0) -> 0 | U19: =VLOOKUP(A19,'[3]Last Aum File'!$A$2:$B$128,2,0) -> 3927561.1 | V19: =+U19/1000000 -> 3.9275611 | W19: =+IF(OR(A19="HF11",A19="PACIFAI"),0,IF(A19="MUSG",P19-U19/2,P19-U19)) -> 0 | X19: =+IF(ISNA(W19),0,W19) -> 0 | Y19: =P19/1000000 -> 3.9275611 | Z19: =X19/1000000 -> 0 | AA19: =T19/1000000 -> 0 | AB19: =VLOOKUP(A19,[3]AUM!$A$3:$B$131,2,0)/1000000 -> 3.9275611 | AC19: =VLOOKUP(A19,'[3]Last Aum File'!$A$2:$B$126,2,0)/1000000 -> 3.9275611 | AD19: =AB19-AC19 -> 0
A20: PF92127 | B20: Yes | C20: AMUNDI SOLUZIONI ITALIA - PROGETTO AZIONE INFRASTRUTTURE SOSTENIBILI | D20: Fund | E20: On Original Risk List | F20: From Risk - Fund Responsibility - Dublin Funds | G20: Outcome Oriented Strategies | H20: Risk Accumulation | I20: 0 | J20: 0 | K20: AMUNDI.IRL/INV/MAS/PMG/PMG | L20: CASEY RICHARD | M20: To be Affected | N20: DUB EFI Absolute Return Aggregate | P20: =VLOOKUP(A20,[3]AUM!$A$3:$B$131,2,0) -> 3.3514686e+08 | R20: =+IF(D20="",VLOOKUP(A20,'[2]Pivot for Jun AUM'!$A$5:$B$121,2,FALSE)) -> FALSE | T20: =VLOOKUP(A20,[4]Flows!$A$3:$D$1206,4,0) -> -1.1498841e+08 | U20: =VLOOKUP(A20,'[3]Last Aum File'!$A$2:$B$128,2,0) -> 4.7382049e+08 | V20: =+U20/1000000 -> 473.82049 | W20: =+IF(OR(A20="HF11",A20="PACIFAI"),0,IF(A20="MUSG",P20-U20/2,P20-U20)) -> -1.3867363e+08 | X20: =+IF(ISNA(W20),0,W20) -> -1.3867363e+08 | Y20: =P20/1000000 -> 335.14686 | Z20: =X20/1000000 -> -138.67363 | AA20: =T20/1000000 -> -114.98841 | AB20: =VLOOKUP(A20,[3]AUM!$A$3:$B$131,2,0)/1000000 -> 335.14686 | AC20: =VLOOKUP(A20,'[3]Last Aum File'!$A$2:$B$126,2,0)/1000000 -> 473.82049 | AD20: =AB20-AC20 -> -138.67363
A21: PF95239 | B21: Yes | C21: AMUNDI SOLUZIONI ITALIA - PROGETTO AZIONE INFRASTRUTTURE SOSTENIBILI (II) | D21: Fund | E21: On Original Risk List | F21: From Risk - Fund Responsibility - Dublin Funds | G21: Outcome Oriented Strategies | H21: Risk Accumulation | I21: 0 | J21: 0 | K21: AMUNDI.IRL/INV/MAS/PMG/PMG | L21: CASEY RICHARD | M21: To be Affected | N21: DUB EFI Absolute Return Aggregate | P21: =VLOOKUP(A21,[3]AUM!$A$3:$B$131,2,0) -> 3.1941249e+08 | R21: =+IF(D21="",VLOOKUP(A21,'[2]Pivot for Jun AUM'!$A$5:$B$121,2,FALSE)) -> FALSE | T21: =VLOOKUP(A21,[4]Flows!$A$3:$D$1206,4,0) -> -68314788 | U21: =VLOOKUP(A21,'[3]Last Aum File'!$A$2:$B$128,2,0) -> 4.0863579e+08 | V21: =+U21/1000000 -> 408.63579 | W21: =+IF(OR(A21="HF11",A21="PACIFAI"),0,IF(A21="MUSG",P21-U21/2,P21-U21)) -> -89223301 | X21: =+IF(ISNA(W21),0,W21) -> -89223301 | Y21: =P21/1000000 -> 319.41249 | Z21: =X21/1000000 -> -89.223301 | AA21: =T21/1000000 -> -68.314788 | AB21: =VLOOKUP(A21,[3]AUM!$A$3:$B$131,2,0)/1000000 -> 319.41249 | AC21: =VLOOKUP(A21,'[3]Last Aum File'!$A$2:$B$126,2,0)/1000000 -> 408.63579 | AD21: =AB21-AC21 -> -89.223301
A22: PF201311 | B22: Yes | C22: AMUNDI SENTIERO SOSTENIBILE | D22: Fund | E22: On Original Risk List | F22: From Risk - Fund Responsibility - Dublin Funds | G22: Outcome Oriented Strategies | H22: Risk Accumulation | I22: 0 | J22: 0 | K22: AMUNDI.IRL/INV/MAS/PMG/PMG | L22: CASEY RICHARD | M22: To be Affected | N22: DUB EFI Absolute Return Aggregate | P22: =VLOOKUP(A22,[3]AUM!$A$3:$B$131,2,0) -> 2.9032318e+08 | R22: =+IF(D22="",VLOOKUP(A22,'[2]Pivot for Jun AUM'!$A$5:$B$121,2,FALSE)) -> FALSE | T22: -10126505 | U22: 2.9765464e+08 | V22: =+U22/1000000 -> 297.65464 | W22: =+IF(OR(A22="HF11",A22="PACIFAI"),0,IF(A22="MUSG",P22-U22/2,P22-U22)) -> -7331455.9 | X22: =+IF(ISNA(W22),0,W22) -> -7331455.9 | Y22: =P22/1000000 -> 290.32318 | Z22: =X22/1000000 -> -7.3314559 | AA22: =T22/1000000 -> -10.126505 | AB22: =VLOOKUP(A22,[3]AUM!$A$3:$B$131,2,0)/1000000 -> 290.32318 | AC22: =VLOOKUP(A22,'[3]Last Aum File'!$A$2:$B$126,2,0)/1000000 -> 291.99146 | AD22: =AB22-AC22 -> -1.6682759
A23: SAXO | B23: Yes | C23: SAXO EUROPE | D23: Model | E23: On Original Risk List | F23: From Risk - Fund Responsibility - Dublin Funds | G23: Allocation Driven Strategies | H23: Conservative | I23: BAL Multimanagement | J23: DUB BAL Multimanagement Alt Greenway | K23: AMUNDI.IRL/INV/MAS/PMG/PMG | L23: Jen | M23: To be Affected | N23: DUB BAL Multimanagement Alt Greenway | P23: 1.9219966e+08 | R23: FALSE | S23: 0 | T23: =P23-U23 -> -7061169.1 | U23: 1.9926083e+08 | V23: =+U23/1000000 -> 199.26083 | W23: =+IF(OR(A23="HF11",A23="PACIFAI"),0,IF(A23="MUSG",P23-U23/2,P23-U23)) -> -7061169.1 | X23: =+IF(ISNA(W23),0,W23) -> -7061169.1 | Y23: =P23/1000000 -> 192.19966 | Z23: =X23/1000000 -> -7.0611691 | AA23: =T23/1000000 -> -7.0611691 | AD23: =AB23-AC23 -> 0
A25: PSUKLD1 | B25: Yes | C25: Amundi Invensys Broad Bond Portfolio | D25: Fund | E25: On Original Risk List | F25: =VLOOKUP(A25,'[1]Dublin funds'!$B$2:$AS$153,2,FALSE) -> From Risk - Fund Responsibility - Dublin Funds | G25: =VLOOKUP($A25,'[2]Total AUM Data'!$A:$I,5,FALSE) -> Allocation Driven Strategies | H25: =VLOOKUP($A25,'[2]Total AUM Data'!$A:$I,6,FALSE) -> Flexible | I25: =VLOOKUP($A25,'[1]Dublin funds'!$B$2:$AS$153,3,FALSE) -> BAL Multimanagement | J25: =VLOOKUP($A25,'[1]Dublin funds'!$B$2:$AS$153,4,FALSE) -> AMU BAL SDA Fds de Fds (used some absolute limits with Low Rik) | K25: AMUNDI.IRL/INV/MAS/PMG/PMG | L25: CASEY RICHARD | M25: To be Affected | N25: DUB BAL Multimanagement SDA Fds de Fds | O25: =VLOOKUP(A25,'Audit AUM File'!A:B,2,FALSE) -> 0 | P25: =VLOOKUP(A25,[3]AUM!$A$3:$B$131,2,0)/0.8338 -> 1.6920099e+08 | R25: =+IF(D25="",VLOOKUP(A25,'[2]Pivot for Jun AUM'!$A$5:$B$121,2,FALSE)) -> FALSE | T25: =VLOOKUP(A25,[4]Flows!$A$3:$D$126,4,0) -> 0 | U25: =VLOOKUP(A25,'[3]Last Aum File'!$A$2:$B$128,2,0)/0.8338 -> 1.6577117e+08 | V25: =+U25/1000000 -> 165.77117 | W25: =+IF(OR(A25="HF11",A25="PACIFAI"),0,IF(A25="MUSG",P25-U25/2,P25-U25)) -> 3429821.8 | X25: =+IF(ISNA(W25),0,W25) -> 3429821.8 | Y25: =P25/1000000 -> 169.20099 | Z25: =X25/1000000 -> 3.4298218 | AA25: =T25/1000000 -> 0 | AB25: =VLOOKUP(A25,[3]AUM!$A$3:$B$131,2,0)/1000000 -> 141.07979 | AC25: =VLOOKUP(A25,'[3]Last Aum File'!$A$2:$B$126,2,0)/1000000 -> 138.22 | AD25: =AB25-AC25 -> 2.8597854
A26: PF79139 | B26: Yes | C26: AMUNDI SOLUZIONI ITALIA - PROGETTO AZIONE CAMBIAMENTO CLIMATICO (II) - E | D26: Fund | E26: On Original Risk List | F26: =VLOOKUP(A26,'[1]Dublin funds'!$B$2:$AS$153,2,FALSE) -> From Risk - Fund Responsibility - Dublin Funds | G26: =VLOOKUP($A26,'[2]Total AUM Data'!$A:$I,5,FALSE) -> Outcome Oriented Strategies | H26: =VLOOKUP($A26,'[2]Total AUM Data'!$A:$I,6,FALSE) -> Risk Accumulation | I26: =VLOOKUP($A26,'[1]Dublin funds'!$B$2:$AS$153,3,FALSE) -> 0 | J26: =VLOOKUP($A26,'[1]Dublin funds'!$B$2:$AS$153,4,FALSE) -> 0 | K26: AMUNDI.IRL/INV/MAS/PMG/PMG | L26: CASEY RICHARD | M26: To be Affected | N26: DUB EFI Absolute Return Aggregate | O26: =VLOOKUP(A26,'Audit AUM File'!A:B,2,FALSE) -> 1.4390381e+08 | Q26: Needs a Macro & Micro Process assigned? | R26: =+IF(D26="",VLOOKUP(A26,'[2]Pivot for Jun AUM'!$A$5:$B$121,2,FALSE)) -> FALSE | S26: =+IF(D26<>"",VLOOKUP(A26,'[2]Total AUM Data'!$A$2:$G$48,7,FALSE)) -> 59757670
A27: PF71664 | B27: Yes | C27: AMUNDI SOLUZIONI ITALIA - PROGETTO AZIONE MEGATREND - E | D27: Fund | E27: On Original Risk List | F27: =VLOOKUP(A27,'[1]Dublin funds'!$B$2:$AS$153,2,FALSE) -> From Risk - Fund Responsibility - Dublin Funds | G27: =VLOOKUP($A27,'[2]Total AUM Data'!$A:$I,5,FALSE) -> Outcome Oriented Strategies | H27: =VLOOKUP($A27,'[2]Total AUM Data'!$A:$I,6,FALSE) -> Risk Accumulation | I27: =VLOOKUP($A27,'[1]Dublin funds'!$B$2:$AS$153,3,FALSE) -> EFI Absolute Return | J27: =VLOOKUP($A27,'[1]Dublin funds'!$B$2:$AS$153,4,FALSE) -> DUB EFI Absolute Return Aggregate | K27: AMUNDI.IRL/INV/MAS/PMG/PMG | L27: CASEY RICHARD | M27: To be Affected | N27: DUB EFI Absolute Return Aggregate | O27: =VLOOKUP(A27,'Audit AUM File'!A:B,2,FALSE) -> 4.9375402e+08 | R27: =+IF(D27="",VLOOKUP(A27,'[2]Pivot for Jun AUM'!$A$5:$B$121,2,FALSE)) -> FALSE | S27: =+IF(D27<>"",VLOOKUP(A27,'[2]Total AUM Data'!$A$2:$G$48,7,FALSE)) -> 4.9380701e+08
A28: PF76580 | B28: Yes | C28: AMUNDI SOLUZIONI ITALIA - PROGETTO AZIONE MEGATREND (II) - E | D28: Fund | E28: On Original Risk List | F28: =VLOOKUP(A28,'[1]Dublin funds'!$B$2:$AS$153,2,FALSE) -> From Risk - Fund Responsibility - Dublin Funds | G28: =VLOOKUP($A28,'[2]Total AUM Data'!$A:$I,5,FALSE) -> Outcome Oriented Strategies | H28: =VLOOKUP($A28,'[2]Total AUM Data'!$A:$I,6,FALSE) -> Risk Accumulation | I28: =VLOOKUP($A28,'[1]Dublin funds'!$B$2:$AS$153,3,FALSE) -> EFI Absolute Return | J28: =VLOOKUP($A28,'[1]Dublin funds'!$B$2:$AS$153,4,FALSE) -> DUB EFI Absolute Return Aggregate | K28: AMUNDI.IRL/INV/MAS/PMG/PMG | L28: CASEY RICHARD | M28: To be Affected | N28: DUB EFI Absolute Return Aggregate | O28: =VLOOKUP(A28,'Audit AUM File'!A:B,2,FALSE) -> 2.9118194e+08 | R28: =+IF(D28="",VLOOKUP(A28,'[2]Pivot for Jun AUM'!$A$5:$B$121,2,FALSE)) -> FALSE | S28: =+IF(D28<>"",VLOOKUP(A28,'[2]Total AUM Data'!$A$2:$G$48,7,FALSE)) -> 2.9050311e+08
A29: PF88300 | B29: Yes | C29: ASI - PROGETTO AZIONE ENERGY TRANSITION | D29: Fund | E29: On Original Risk List | F29: From Risk - Fund Responsibility - Dublin Funds | G29: Outcome Oriented Strategies | H29: Risk Accumulation | I29: EFI Absolute Return | K29: AMUNDI.IRL/INV/MAS/PMG/PMG | L29: CASEY RICHARD | M29: To be Affected | N29: DUB EFI Absolute Return Aggregate | O29: 0 | P29: =VLOOKUP(A29,[3]AUM!$A$3:$B$132,2,0) -> 4.5198023e+08 | R29: =+IF(D29="",VLOOKUP(A29,'[2]Pivot for Jun AUM'!$A$5:$B$121,2,FALSE)) -> FALSE | T29: =VLOOKUP(A29,[4]Flows!$A$3:$D$1206,4,0) -> -75897228 | U29: =VLOOKUP(A29,'[3]Last Aum File'!$A$2:$B$128,2,0) -> 5.5549507e+08 | V29: =+U29/1000000 -> 555.49507 | W29: =+IF(OR(A29="HF11",A29="PACIFAI"),0,IF(A29="MUSG",P29-U29/2,P29-U29)) -> -1.0351484e+08 | X29: =+IF(ISNA(W29),0,W29) -> -1.0351484e+08 | Y29: =P29/1000000 -> 451.98023 | Z29: =X29/1000000 -> -103.51484 | AA29: =T29/1000000 -> -75.897228 | AB29: =VLOOKUP(A29,[3]AUM!$A$3:$B$131,2,0)/1000000 -> 451.98023 | AC29: =VLOOKUP(A29,'[3]Last Aum File'!$A$2:$B$126,2,0)/1000000 -> 555.49507 | AD29: =AB29-AC29 -> -103.51484
A30: PF89408 | B30: Yes | C30: ASI - PROGETTO AZIONE ENERGY TRANSITION (II) | D30: Fund | E30: On Original Risk List | F30: From Risk - Fund Responsibility - Dublin Funds | G30: Outcome Oriented Strategies | H30: Risk Accumulation | I30: EFI Absolute Return | K30: AMUNDI.IRL/INV/MAS/PMG/PMG | L30: CASEY RICHARD | M30: To be Affected | N30: DUB EFI Absolute Return Aggregate | O30: 0 | P30: =VLOOKUP(A30,[3]AUM!$A$3:$B$131,2,0) -> 2.7793822e+08 | R30: =+IF(D30="",VLOOKUP(A30,'[2]Pivot for Jun AUM'!$A$5:$B$121,2,FALSE)) -> FALSE | T30: =VLOOKUP(A30,[4]Flows!$A$3:$D$1206,4,0) -> -47534278 | U30: =VLOOKUP(A30,'[3]Last Aum File'!$A$2:$B$128,2,0) -> 3.4182237e+08 | V30: =+U30/1000000 -> 341.82237 | W30: =+IF(OR(A30="HF11",A30="PACIFAI"),0,IF(A30="MUSG",P30-U30/2,P30-U30)) -> -63884148 | X30: =+IF(ISNA(W30),0,W30) -> -63884148 | Y30: =P30/1000000 -> 277.93822 | Z30: =X30/1000000 -> -63.884148 | AA30: =T30/1000000 -> -47.534278 | AB30: =VLOOKUP(A30,[3]AUM!$A$3:$B$131,2,0)/1000000 -> 277.93822 | AC30: =VLOOKUP(A30,'[3]Last Aum File'!$A$2:$B$126,2,0)/1000000 -> 341.82237 | AD30: =AB30-AC30 -> -63.884148
A31: E224 | B31: Yes | C31: PI INVESTMENT FUNDS - TACTICAL ALLOCATION PILLAR - E | D31: Fund | E31: On Original Risk List | F31: =VLOOKUP(A31,'[1]Dublin funds'!$B$2:$AS$153,2,FALSE) -> From Risk - Fund Responsibility - Dublin Funds | G31: =VLOOKUP($A31,'[2]Total AUM Data'!$A:$I,5,FALSE) -> Service Fund | H31: =VLOOKUP($A31,'[2]Total AUM Data'!$A:$I,6,FALSE) -> Income | I31: =VLOOKUP($A31,'[1]Dublin funds'!$B$2:$AS$153,3,FALSE) -> TBD | J31: =VLOOKUP($A31,'[1]Dublin funds'!$B$2:$AS$153,4,FALSE) -> Agreed a light touch with VaR and Leverage limits | K31: AMUNDI.IRL/INV/MAS/PMG/PMG | L31: CASEY RICHARD | M31: To be Affected | N31: To Be Determined | O31: =VLOOKUP(A31,'Audit AUM File'!A:B,2,FALSE) -> 3.365189e+08 | P31: =VLOOKUP(A31,[3]AUM!$A$3:$B$131,2,0) -> 59556669 | R31: =+IF(D31="",VLOOKUP(A31,'[2]Pivot for Jun AUM'!$A$5:$B$121,2,FALSE)) -> FALSE | S31: =+IF(D31<>"",VLOOKUP(A31,'[2]Total AUM Data'!$A$2:$G$48,7,FALSE)) -> 3.6737659e+08 | T31: =VLOOKUP(A31,[4]Flows!$A$3:$D$1206,4,0) -> -6138586.8 | U31: =VLOOKUP(A31,'[3]Last Aum File'!$A$2:$B$128,2,0) -> 74824882 | V31: =+U31/1000000 -> 74.824882 | W31: =+IF(OR(A31="HF11",A31="PACIFAI"),0,IF(A31="MUSG",P31-U31/2,P31-U31)) -> -15268212 | X31: =+IF(ISNA(W31),0,W31) -> -15268212 | Y31: =P31/1000000 -> 59.556669 | Z31: =X31/1000000 -> -15.268212 | AA31: =T31/1000000 -> -6.1385868 | AB31: =VLOOKUP(A31,[3]AUM!$A$3:$B$131,2,0)/1000000 -> 59.556669 | AC31: =VLOOKUP(A31,'[3]Last Aum File'!$A$2:$B$126,2,0)/1000000 -> 74.824882 | AD31: =AB31-AC31 -> -15.268212
A32: E208 | B32: Yes | C32: PI INVESTMENT FUNDS - TACTICAL ALLOCATION BOND FUND - H | D32: Fund | E32: On Original Risk List | F32: =VLOOKUP(A32,'[1]Dublin funds'!$B$2:$AS$153,2,FALSE) -> From Risk - Fund Responsibility - Dublin Funds | G32: =VLOOKUP($A32,'[2]Total AUM Data'!$A:$I,5,FALSE) -> Service Fund | H32: =VLOOKUP($A32,'[2]Total AUM Data'!$A:$I,6,FALSE) -> Bond | I32: =VLOOKUP($A32,'[1]Dublin funds'!$B$2:$AS$153,3,FALSE) -> TBD | J32: =VLOOKUP($A32,'[1]Dublin funds'!$B$2:$AS$153,4,FALSE) -> Agreed a light touch with VaR and Leverage limits | K32: AMUNDI.IRL/INV/MAS/PMG/PMG | L32: PAQUOT BERTRAND | M32: To be Affected | N32: To Be Determined | O32: =VLOOKUP(A32,'Audit AUM File'!A:B,2,FALSE) -> 1.9991382e+08 | P32: =VLOOKUP(A32,[3]AUM!$A$3:$B$131,2,0) -> 74247836 | R32: =+IF(D32="",VLOOKUP(A32,'[2]Pivot for Jun AUM'!$A$5:$B$121,2,FALSE)) -> FALSE | S32: =+IF(D32<>"",VLOOKUP(A32,'[2]Total AUM Data'!$A$2:$G$48,7,FALSE)) -> 4.5036569e+08 | T32: =VLOOKUP(A32,[4]Flows!$A$3:$D$1206,4,0) -> -2977460.7 | U32: =VLOOKUP(A32,'[3]Last Aum File'!$A$2:$B$128,2,0) -> 77232790 | V32: =+U32/1000000 -> 77.23279 | W32: =+IF(OR(A32="HF11",A32="PACIFAI"),0,IF(A32="MUSG",P32-U32/2,P32-U32)) -> -2984954.1 | X32: =+IF(ISNA(W32),0,W32) -> -2984954.1 | Y32: =P32/1000000 -> 74.247836 | Z32: =X32/1000000 -> -2.9849541 | AA32: =T32/1000000 -> -2.9774607 | AB32: =VLOOKUP(A32,[3]AUM!$A$3:$B$131,2,0)/1000000 -> 74.247836 | AC32: =VLOOKUP(A32,'[3]Last Aum File'!$A$2:$B$126,2,0)/1000000 -> 77.23279 | AD32: =AB32-AC32 -> -2.9849541
A33: ULECSTARS | B33: Yes | C33: UL Global Equity Dividend & Subordinated | D33: Model | E33: On Original Risk List | F33: From Risk - Fund Responsibility - Dublin Funds | G33: Allocation Driven Strategies | H33: Equity | I33: TBD | K33: AMUNDI.IRL/INV/MAS/PMG/PMG | L33: PAQUOT BERTRAND | M33: To be Affected | N33: To Be Determined | P33: =VLOOKUP(A33,[3]AUM!$A$3:$B$131,2,0) -> 1901251614 | R33: =+IF(D33="",VLOOKUP(A33,'[2]Pivot for Jun AUM'!$A$5:$B$121,2,FALSE)) -> FALSE | T33: =VLOOKUP(A33,[4]Flows!$A$3:$D$1206,4,0) -> -32352755 | U33: =VLOOKUP(A33,'[3]Last Aum File'!$A$2:$B$1262,2,0) -> 1877332566 | V33: =+U33/1000000 -> 1877.3326 | W33: =+IF(OR(A33="HF11",A33="PACIFAI"),0,IF(A33="MUSG",P33-U33/2,P33-U33)) -> 23919048 | X33: =+IF(ISNA(W33),0,W33) -> 23919048 | Y33: =P33/1000000 -> 1901.2516 | Z33: =X33/1000000 -> 23.919048 | AA33: =T33/1000000 -> -32.352755 | AB33: =VLOOKUP(A33,[3]AUM!$A$3:$B$131,2,0)/1000000 -> 1901.2516 | AC33: =VLOOKUP(A33,'[3]Last Aum File'!$A$2:$B$126,2,0)/1000000 -> 1877.3326 | AD33: =AB33-AC33 -> 23.919048
A34: F100123 | B34: Yes | C34: Amundi Env and Climate Change Sol Fund | D34: Fund | E34: On Original Risk List | F34: From Risk - Fund Responsibility - Dublin Funds | G34: Allocation Driven Strategies | H34: Equity | I34: TBD | K34: AMUNDI.IRL/INV/MAS/PMG/PMG | L34: NICHOLAS POTHIER | M34: To be Affected | N34: To Be Determined | P34: =VLOOKUP(A34,[3]AUM!$A$3:$B$131,2,0)/163 -> 66105969 | R34: =+IF(D34="",VLOOKUP(A34,'[2]Pivot for Jun AUM'!$A$5:$B$121,2,FALSE)) -> FALSE | T34: =P34-U34 -> -14474434 | U34: =VLOOKUP(A34,'[3]Last Aum File'!$A$2:$B$1262,2,0)/163 -> 80580403 | V34: =+U34/1000000 -> 80.580403 | W34: =+IF(OR(A34="HF11",A34="PACIFAI"),0,IF(A34="MUSG",P34-U34/2,P34-U34)) -> -14474434 | X34: =+IF(ISNA(W34),0,W34) -> -14474434 | Y34: =P34/1000000 -> 66.105969 | Z34: =X34/1000000 -> -14.474434 | AA34: =T34/1000000 -> -14.474434 | AB34: =VLOOKUP(A34,[3]AUM!$A$3:$B$131,2,0)/1000000 -> 10775.273 | AC34: =VLOOKUP(A34,'[3]Last Aum File'!$A$2:$B$126,2,0)/1000000 -> 13134.606 | AD34: =AB34-AC34 -> -2359.3327
A35: UDM6 | B35: Yes | C35: Unidiamond + Azionaria America | D35: Model | E35: On Original Risk List | F35: From Risk - Fund Responsibility - Dublin Funds | G35: Allocation Driven Strategies | H35: Equity | I35: TBD | K35: AMUNDI.IRL/INV/MAS/PMG/PMG | L35: PAQUOT BERTRAND | M35: To be Affected | N35: To Be Determined | P35: =VLOOKUP(A35,[3]AUM!$A$3:$B$131,2,0) -> 1100006489 | R35: =+IF(D35="",VLOOKUP(A35,'[2]Pivot for Jun AUM'!$A$5:$B$121,2,FALSE)) -> FALSE | T35: =VLOOKUP(A35,[4]Flows!$A$3:$D$1206,4,0) -> 1008111.9 | U35: =VLOOKUP(A35,'[3]Last Aum File'!$A$2:$B$1262,2,0) -> 1020119648 | V35: =+U35/1000000 -> 1020.1196 | W35: =+IF(OR(A35="HF11",A35="PACIFAI"),0,IF(A35="MUSG",P35-U35/2,P35-U35)) -> 79886841 | X35: =+IF(ISNA(W35),0,W35) -> 79886841 | Y35: =P35/1000000 -> 1100.0065 | Z35: =X35/1000000 -> 79.886841 | AA35: =T35/1000000 -> 1.0081119 | AB35: =VLOOKUP(A35,[3]AUM!$A$3:$B$131,2,0)/1000000 -> 1100.0065 | AC35: =VLOOKUP(A35,'[3]Last Aum File'!$A$2:$B$126,2,0)/1000000 -> 1020.1196 | AD35: =AB35-AC35 -> 79.886841
A36: UDM7 | B36: Yes | C36: Life Program Azionario Pacifico | D36: Model | E36: On Original Risk List | F36: From Risk - Fund Responsibility - Dublin Funds | G36: Allocation Driven Strategies | H36: Equity | I36: TBD | K36: AMUNDI.IRL/INV/MAS/PMG/PMG | L36: PAQUOT BERTRAND | M36: To be Affected | N36: To Be Determined | P36: =VLOOKUP(A36,[3]AUM!$A$3:$B$131,2,0) -> 46360523 | R36: =+IF(D36="",VLOOKUP(A36,'[2]Pivot for Jun AUM'!$A$5:$B$121,2,FALSE)) -> FALSE | T36: =VLOOKUP(A36,[4]Flows!$A$3:$D$1206,4,0) -> -74993.42 | U36: =VLOOKUP(A36,'[3]Last Aum File'!$A$2:$B$1262,2,0) -> 49761394 | V36: =+U36/1000000 -> 49.761394 | W36: =+IF(OR(A36="HF11",A36="PACIFAI"),0,IF(A36="MUSG",P36-U36/2,P36-U36)) -> -3400871 | X36: =+IF(ISNA(W36),0,W36) -> -3400871 | Y36: =P36/1000000 -> 46.360523 | Z36: =X36/1000000 -> -3.400871 | AA36: =T36/1000000 -> -0.07499342 | AB36: =VLOOKUP(A36,[3]AUM!$A$3:$B$131,2,0)/1000000 -> 46.360523 | AC36: =VLOOKUP(A36,'[3]Last Aum File'!$A$2:$B$126,2,0)/1000000 -> 49.761394 | AD36: =AB36-AC36 -> -3.400871
A37: UDM9 | B37: Yes | C37: Unidiamond + Azionaria Intl | D37: Model | E37: On Original Risk List | F37: From Risk - Fund Responsibility - Dublin Funds | G37: Allocation Driven Strategies | H37: Equity | I37: TBD | K37: AMUNDI.IRL/INV/MAS/PMG/PMG | L37: PAQUOT BERTRAND | M37: To be Affected | N37: To Be Determined | P37: =VLOOKUP(A37,[3]AUM!$A$3:$B$131,2,0) -> 173792904 | R37: =+IF(D37="",VLOOKUP(A37,'[2]Pivot for Jun AUM'!$A$5:$B$121,2,FALSE)) -> FALSE | T37: =VLOOKUP(A37,[4]Flows!$A$3:$D$1206,4,0) -> -4429190.5 | U37: =VLOOKUP(A37,'[3]Last Aum File'!$A$2:$B$1262,2,0) -> 173466024 | V37: =+U37/1000000 -> 173.46602 | W37: =+IF(OR(A37="HF11",A37="PACIFAI"),0,IF(A37="MUSG",P37-U37/2,P37-U37)) -> 326880 | X37: =+IF(ISNA(W37),0,W37) -> 326880 | Y37: =P37/1000000 -> 173.7929 | Z37: =X37/1000000 -> 0.32688 | AA37: =T37/1000000 -> -4.4291905 | AB37: =VLOOKUP(A37,[3]AUM!$A$3:$B$131,2,0)/1000000 -> 173.7929 | AC37: =VLOOKUP(A37,'[3]Last Aum File'!$A$2:$B$126,2,0)/1000000 -> 173.46602 | AD37: =AB37-AC37 -> 0.32688
A38: E207 | B38: Yes | C38: PI INVESTMENT FUNDS - TACTICAL ALLOCATION FUND - H | D38: Fund | E38: On Original Risk List | F38: =VLOOKUP(A38,'[1]Dublin funds'!$B$2:$AS$153,2,FALSE) -> From Risk - Fund Responsibility - Dublin Funds | G38: =VLOOKUP($A38,'[2]Total AUM Data'!$A:$I,5,FALSE) -> Service Fund | H38: =VLOOKUP($A38,'[2]Total AUM Data'!$A:$I,6,FALSE) -> Equity | I38: =VLOOKUP($A38,'[1]Dublin funds'!$B$2:$AS$153,3,FALSE) -> TBD | J38: =VLOOKUP($A38,'[1]Dublin funds'!$B$2:$AS$153,4,FALSE) -> Agreed a light touch with VaR and Leverage limits | K38: AMUNDI.IRL/INV/MAS/PMG/PMG | L38: PAQUOT BERTRAND | M38: To be Affected | N38: To Be Determined | O38: =VLOOKUP(A38,'Audit AUM File'!A:B,2,FALSE) -> 1.0311371e+08 | P38: =VLOOKUP(A38,[3]AUM!$A$3:$B$131,2,0) -> 53160978 | R38: =+IF(D38="",VLOOKUP(A38,'[2]Pivot for Jun AUM'!$A$5:$B$121,2,FALSE)) -> FALSE | S38: =+IF(D38<>"",VLOOKUP(A38,'[2]Total AUM Data'!$A$2:$G$48,7,FALSE)) -> 3.1667136e+08 | T38: =VLOOKUP(A38,[4]Flows!$A$3:$D$1206,4,0) -> -446651.58 | U38: =VLOOKUP(A38,'[3]Last Aum File'!$A$2:$B$1262,2,0) -> 56764605 | V38: =+U38/1000000 -> 56.764605 | W38: =+IF(OR(A38="HF11",A38="PACIFAI"),0,IF(A38="MUSG",P38-U38/2,P38-U38)) -> -3603626.9 | X38: =+IF(ISNA(W38),0,W38) -> -3603626.9 | Y38: =P38/1000000 -> 53.160978 | Z38: =X38/1000000 -> -3.6036269 | AA38: =T38/1000000 -> -0.44665158 | AB38: =VLOOKUP(A38,[3]AUM!$A$3:$B$131,2,0)/1000000 -> 53.160978 | AC38: =VLOOKUP(A38,'[3]Last Aum File'!$A$2:$B$126,2,0)/1000000 -> 56.764605 | AD38: =AB38-AC38 -> -3.6036269
A39: E193 | B39: Yes | C39: =VLOOKUP(A39,'[1]Dublin funds'!$B:$AY,7,FALSE) -> Amundi Fund Solutions - Diversified Income Best Select 2022 | D39: Fund | E39: Added by Ronan | F39: =VLOOKUP(A39,'[1]Dublin funds'!$B$2:$AS$153,2,FALSE) -> From Risk - Fund Responsibility - Dublin Funds | G39: =VLOOKUP($A39,'[2]Total AUM Data'!$A:$I,5,FALSE) -> Outcome Oriented Strategies | H39: =VLOOKUP($A39,'[2]Total AUM Data'!$A:$I,6,FALSE) -> Income | I39: =VLOOKUP($A39,'[1]Dublin funds'!$B$2:$AS$153,3,FALSE) -> BAL Multimanagement | J39: =VLOOKUP($A39,'[1]Dublin funds'!$B$2:$AS$153,4,FALSE) -> AMU BAL SDA Fds de Fds (used absolute limits mixed medium/High risk) | P39: =VLOOKUP(A39,[3]AUM!$A$3:$B$131,2,0) -> 1.3642864e+08 | R39: =+IF(D39="",VLOOKUP(A39,'[2]Pivot for Jun AUM'!$A$5:$B$121,2,FALSE)) -> FALSE | S39: =+IF(D39<>"",VLOOKUP(A39,'[2]Total AUM Data'!$A$2:$G$48,7,FALSE)) -> 2.9430834e+08 | T39: =VLOOKUP(A39,[4]Flows!$A$3:$D$1206,4,0) -> -4867464.7 | U39: =VLOOKUP(A39,'[3]Last Aum File'!$A$2:$B$1262,2,0) -> 1.3781462e+08 | V39: =+U39/1000000 -> 137.81462 | W39: =+IF(OR(A39="HF11",A39="PACIFAI"),0,IF(A39="MUSG",P39-U39/2,P39-U39)) -> -1385976.7 | X39: =+IF(ISNA(W39),0,W39) -> -1385976.7 | Y39: =P39/1000000 -> 136.42864 | Z39: =X39/1000000 -> -1.3859767 | AA39: =T39/1000000 -> -4.8674647 | AB39: =VLOOKUP(A39,[3]AUM!$A$3:$B$131,2,0)/1000000 -> 136.42864 | AC39: =VLOOKUP(A39,'[3]Last Aum File'!$A$2:$B$126,2,0)/1000000 -> 137.81462 | AD39: =AB39-AC39 -> -1.3859767
A40: 1PM | B40: Yes | C40: CAM ARES RISPARMIO ATTIVO M | D40: Model | E40: On Original Risk List | F40: =VLOOKUP(A40,'[1]Model portfolios'!$A$2:$L$142,2,FALSE) -> From Risk - Fund Responsibility - Model Portfolios | G40: =VLOOKUP($A40,'[2]Desk mapping'!$G:$L,5,FALSE) -> Allocation Driven Strategies | H40: =VLOOKUP($A40,'[2]Desk mapping'!$G:$L,6,FALSE) -> Growth | K40: AMUNDI.IRL/INV/MAS/PMG | L40: BUONO SALVATORE | M40: To be Affected | O40: =VLOOKUP(A40,'Audit AUM File'!A:B,2,FALSE) -> 2.3288514e+08 | P40: =VLOOKUP(A40,[3]AUM!$A$1:$B$131,2,0) -> 286172410 | R40: =+IF(D40="",VLOOKUP(A40,'[2]Pivot for Jun AUM'!$A$5:$B$121,2,FALSE)) -> FALSE | T40: =VLOOKUP(A40,[4]Flows!$A$3:$D$1206,4,0) -> -8096631.6 | U40: =VLOOKUP(A40,'[3]Last Aum File'!$A$2:$B$1262,2,0) -> 276712413 | V40: =+U40/1000000 -> 276.71241 | W40: =+IF(OR(A40="HF11",A40="PACIFAI"),0,IF(A40="MUSG",P40-U40/2,P40-U40)) -> 9459997 | X40: =+IF(ISNA(W40),0,W40) -> 9459997 | Y40: =P40/1000000 -> 286.17241 | Z40: =X40/1000000 -> 9.459997 | AA40: =T40/1000000 -> -8.0966316 | AB40: =VLOOKUP(A40,[3]AUM!$A$2:$B$131,2,0)/1000000 -> 286.17241 | AC40: =VLOOKUP(A40,'[3]Last Aum File'!$A$2:$B$126,2,0)/1000000 -> 276.71241 | AD40: =AB40-AC40 -> 9.459997
A41: 1QM | B41: Yes | C41: CAM ARES RISPARMIO BILANCIATO M | D41: Model | E41: On Original Risk List | F41: =VLOOKUP(A41,'[1]Model portfolios'!$A$2:$L$142,2,FALSE) -> From Risk - Fund Responsibility - Model Portfolios | G41: =VLOOKUP($A41,'[2]Desk mapping'!$G:$L,5,FALSE) -> Allocation Driven Strategies | H41: =VLOOKUP($A41,'[2]Desk mapping'!$G:$L,6,FALSE) -> Moderate | K41: AMUNDI.IRL/INV/MAS/PMG | L41: BUONO SALVATORE | M41: To be Affected | O41: =VLOOKUP(A41,'Audit AUM File'!A:B,2,FALSE) -> 1.7521559e+08 | P41: =VLOOKUP(A41,[3]AUM!$A$3:$B$131,2,0) -> 44621309 | R41: =+IF(D41="",VLOOKUP(A41,'[2]Pivot for Jun AUM'!$A$5:$B$121,2,FALSE)) -> FALSE | T41: =VLOOKUP(A41,[4]Flows!$A$3:$D$1206,4,0) -> -915885.27 | U41: =VLOOKUP(A41,'[3]Last Aum File'!$A$2:$B$1262,2,0) -> 44663645 | V41: =+U41/1000000 -> 44.663645 | W41: =+IF(OR(A41="HF11",A41="PACIFAI"),0,IF(A41="MUSG",P41-U41/2,P41-U41)) -> -42336 | X41: =+IF(ISNA(W41),0,W41) -> -42336 | Y41: =P41/1000000 -> 44.621309 | Z41: =X41/1000000 -> -0.042336 | AA41: =T41/1000000 -> -0.91588527 | AB41: =VLOOKUP(A41,[3]AUM!$A$3:$B$131,2,0)/1000000 -> 44.621309 | AC41: =VLOOKUP(A41,'[3]Last Aum File'!$A$2:$B$126,2,0)/1000000 -> 44.663645 | AD41: =AB41-AC41 -> -0.042336
A42: 1RM | B42: Yes | C42: CAM ARES RISPARMIO OBBLIGAZ. M | D42: Model | E42: On Original Risk List | F42: =VLOOKUP(A42,'[1]Model portfolios'!$A$2:$L$142,2,FALSE) -> From Risk - Fund Responsibility - Model Portfolios | G42: =VLOOKUP($A42,'[2]Desk mapping'!$G:$L,5,FALSE) -> Allocation Driven Strategies | H42: =VLOOKUP($A42,'[2]Desk mapping'!$G:$L,6,FALSE) -> Conservative | K42: AMUNDI.IRL/INV/MAS/PMG | L42: BUONO SALVATORE | M42: To be Affected | O42: =VLOOKUP(A42,'Audit AUM File'!A:B,2,FALSE) -> 1.5006601e+08 | P42: =VLOOKUP(A42,[3]AUM!$A$3:$B$131,2,0) -> 29605967 | R42: =+IF(D42="",VLOOKUP(A42,'[2]Pivot for Jun AUM'!$A$5:$B$121,2,FALSE)) -> FALSE | T42: =VLOOKUP(A42,[4]Flows!$A$3:$D$1206,4,0) -> -567692.13 | U42: =VLOOKUP(A42,'[3]Last Aum File'!$A$2:$B$1262,2,0) -> 29944309 | V42: =+U42/1000000 -> 29.944309 | W42: =+IF(OR(A42="HF11",A42="PACIFAI"),0,IF(A42="MUSG",P42-U42/2,P42-U42)) -> -338342 | X42: =+IF(ISNA(W42),0,W42) -> -338342 | Y42: =P42/1000000 -> 29.605967 | Z42: =X42/1000000 -> -0.338342 | AA42: =T42/1000000 -> -0.56769213 | AB42: =VLOOKUP(A42,[3]AUM!$A$3:$B$131,2,0)/1000000 -> 29.605967 | AC42: =VLOOKUP(A42,'[3]Last Aum File'!$A$2:$B$126,2,0)/1000000 -> 29.944309 | AD42: =AB42-AC42 -> -0.338342
A43: R1M | B43: Yes | C43: CAM CNP - LINEA DINAMICA | D43: Model | E43: On Original Risk List | F43: =VLOOKUP(A43,'[1]Model portfolios'!$A$2:$L$142,2,FALSE) -> From Risk - Fund Responsibility - Model Portfolios | G43: =VLOOKUP($A43,'[2]Desk mapping'!$G:$L,5,FALSE) -> Allocation Driven Strategies | H43: =VLOOKUP($A43,'[2]Desk mapping'!$G:$L,6,FALSE) -> Growth | K43: AMUNDI.IRL/INV/MAS/PMG | L43: BUONO SALVATORE | M43: To be Affected | O43: =VLOOKUP(A43,'Audit AUM File'!A:B,2,FALSE) -> 1.5535214e+08 | P43: =VLOOKUP(A43,[3]AUM!$A$3:$B$131,2,0) -> 20379176 | R43: =+IF(D43="",VLOOKUP(A43,'[2]Pivot for Jun AUM'!$A$5:$B$121,2,FALSE)) -> FALSE | T43: =VLOOKUP(A43,[4]Flows!$A$3:$D$1206,4,0) -> -444459.29 | U43: =VLOOKUP(A43,'[3]Last Aum File'!$A$2:$B$1262,2,0) -> 20364888 | V43: =+U43/1000000 -> 20.364888 | W43: =+IF(OR(A43="HF11",A43="PACIFAI"),0,IF(A43="MUSG",P43-U43/2,P43-U43)) -> 14288 | X43: =+IF(ISNA(W43),0,W43) -> 14288 | Y43: =P43/1000000 -> 20.379176 | Z43: =X43/1000000 -> 0.014288 | AA43: =T43/1000000 -> -0.44445929 | AB43: =VLOOKUP(A43,[3]AUM!$A$3:$B$131,2,0)/1000000 -> 20.379176 | AC43: =VLOOKUP(A43,'[3]Last Aum File'!$A$2:$B$126,2,0)/1000000 -> 20.364888 | AD43: =AB43-AC43 -> 0.014288
A44: CCRESCITA | B44: Yes | C44: CAM CRESCITA | D44: Model | E44: On Original Risk List | F44: =VLOOKUP(A44,'[1]Model portfolios'!$A$2:$L$142,2,FALSE) -> From Risk - Fund Responsibility - Model Portfolios | G44: =VLOOKUP($A44,'[2]Desk mapping'!$G:$L,5,FALSE) -> Allocation Driven Strategies | H44: =VLOOKUP($A44,'[2]Desk mapping'!$G:$L,6,FALSE) -> Growth | K44: AMUNDI.IRL/INV/MAS/PMG | L44: BUONO SALVATORE | M44: To be Affected | O44: =VLOOKUP(A44,'Audit AUM File'!A:B,2,FALSE) -> 2.4403387e+08 | P44: =VLOOKUP(A44,[3]AUM!$A$3:$B$131,2,0) -> 1259071 | R44: =+IF(D44="",VLOOKUP(A44,'[2]Pivot for Jun AUM'!$A$5:$B$121,2,FALSE)) -> FALSE | T44: =VLOOKUP(A44,[4]Flows!$A$3:$D$1206,4,0) -> -19473.1 | U44: =VLOOKUP(A44,'[3]Last Aum File'!$A$2:$B$1262,2,0) -> 1226192 | V44: =+U44/1000000 -> 1.226192 | W44: =+IF(OR(A44="HF11",A44="PACIFAI"),0,IF(A44="MUSG",P44-U44/2,P44-U44)) -> 32879 | X44: =+IF(ISNA(W44),0,W44) -> 32879 | Y44: =P44/1000000 -> 1.259071 | Z44: =X44/1000000 -> 0.032879 | AA44: =T44/1000000 -> -0.0194731 | AB44: =VLOOKUP(A44,[3]AUM!$A$3:$B$131,2,0)/1000000 -> 1.259071 | AC44: =VLOOKUP(A44,'[3]Last Aum File'!$A$2:$B$126,2,0)/1000000 -> 1.226192 | AD44: =AB44-AC44 -> 0.032879
A45: CMEDIUM | B45: Yes | C45: CAM MEDIUM | D45: Model | E45: On Original Risk List | F45: =VLOOKUP(A45,'[1]Model portfolios'!$A$2:$L$142,2,FALSE) -> From Risk - Fund Responsibility - Model Portfolios | G45: =VLOOKUP($A45,'[2]Desk mapping'!$G:$L,5,FALSE) -> Allocation Driven Strategies | H45: =VLOOKUP($A45,'[2]Desk mapping'!$G:$L,6,FALSE) -> Moderate | K45: AMUNDI.IRL/INV/MAS/PMG | L45: BUONO SALVATORE | M45: To be Affected | O45: =VLOOKUP(A45,'Audit AUM File'!A:B,2,FALSE) -> 1.6409915e+08 | P45: =VLOOKUP(A45,[3]AUM!$A$3:$B$131,2,0) -> 221348 | R45: =+IF(D45="",VLOOKUP(A45,'[2]Pivot for Jun AUM'!$A$5:$B$121,2,FALSE)) -> FALSE | U45: =VLOOKUP(A45,'[3]Last Aum File'!$A$2:$B$1262,2,0) -> 215898 | V45: =+U45/1000000 -> 0.215898 | W45: =+IF(OR(A45="HF11",A45="PACIFAI"),0,IF(A45="MUSG",P45-U45/2,P45-U45)) -> 5450 | X45: =+IF(ISNA(W45),0,W45) -> 5450 | Y45: =P45/1000000 -> 0.221348 | Z45: =X45/1000000 -> 0.00545 | AA45: =T45/1000000 -> 0 | AB45: =VLOOKUP(A45,[3]AUM!$A$3:$B$131,2,0)/1000000 -> 0.221348 | AC45: =VLOOKUP(A45,'[3]Last Aum File'!$A$2:$B$126,2,0)/1000000 -> 0.215898 | AD45: =AB45-AC45 -> 0.00545
A46: COBBLEURO | B46: Yes | C46: CAM OBBLIGAZIONARIA EURO | D46: Model | E46: On Original Risk List | F46: =VLOOKUP(A46,'[1]Model portfolios'!$A$2:$L$142,2,FALSE) -> From Risk - Fund Responsibility - Model Portfolios | G46: =VLOOKUP($A46,'[2]Desk mapping'!$G:$L,5,FALSE) -> Allocation Driven Strategies | H46: =VLOOKUP($A46,'[2]Desk mapping'!$G:$L,6,FALSE) -> Conservative | K46: AMUNDI.IRL/INV/MAS/PMG | L46: BUONO SALVATORE | M46: To be Affected | O46: =VLOOKUP(A46,'Audit AUM File'!A:B,2,FALSE) -> 1.5132725e+08 | P46: =VLOOKUP(A46,[3]AUM!$A$3:$B$131,2,0) -> 2649 | R46: =+IF(D46="",VLOOKUP(A46,'[2]Pivot for Jun AUM'!$A$5:$B$121,2,FALSE)) -> FALSE | U46: =VLOOKUP(A46,'[3]Last Aum File'!$A$2:$B$1262,2,0) -> 2649 | V46: =+U46/1000000 -> 0.002649 | W46: =+IF(OR(A46="HF11",A46="PACIFAI"),0,IF(A46="MUSG",P46-U46/2,P46-U46)) -> 0 | X46: =+IF(ISNA(W46),0,W46) -> 0 | Y46: =P46/1000000 -> 0.002649 | Z46: =X46/1000000 -> 0 | AA46: =T46/1000000 -> 0 | AB46: =VLOOKUP(A46,[3]AUM!$A$3:$B$131,2,0)/1000000 -> 0.002649 | AC46: =VLOOKUP(A46,'[3]Last Aum File'!$A$2:$B$126,2,0)/1000000 -> 0.002649 | AD46: =AB46-AC46 -> 0
A47: CREDDITO | B47: Yes | C47: CAM REDDITO | D47: Model | E47: On Original Risk List | F47: =VLOOKUP(A47,'[1]Model portfolios'!$A$2:$L$142,2,FALSE) -> From Risk - Fund Responsibility - Model Portfolios | G47: =VLOOKUP($A47,'[2]Desk mapping'!$G:$L,5,FALSE) -> Allocation Driven Strategies | H47: =VLOOKUP($A47,'[2]Desk mapping'!$G:$L,6,FALSE) -> Conservative | K47: AMUNDI.IRL/INV/MAS/PMG | L47: BUONO SALVATORE | M47: To be Affected | O47: =VLOOKUP(A47,'Audit AUM File'!A:B,2,FALSE) -> 1.5878576e+08 | P47: =VLOOKUP(A47,[3]AUM!$A$3:$B$131,2,0) -> 83275 | R47: =+IF(D47="",VLOOKUP(A47,'[2]Pivot for Jun AUM'!$A$5:$B$121,2,FALSE)) -> FALSE | U47: =VLOOKUP(A47,'[3]Last Aum File'!$A$2:$B$1262,2,0) -> 82952 | V47: =+U47/1000000 -> 0.082952 | W47: =+IF(OR(A47="HF11",A47="PACIFAI"),0,IF(A47="MUSG",P47-U47/2,P47-U47)) -> 323 | X47: =+IF(ISNA(W47),0,W47) -> 323 | Y47: =P47/1000000 -> 0.083275 | Z47: =X47/1000000 -> 0.000323 | AA47: =T47/1000000 -> 0 | AB47: =VLOOKUP(A47,[3]AUM!$A$3:$B$131,2,0)/1000000 -> 0.083275 | AC47: =VLOOKUP(A47,'[3]Last Aum File'!$A$2:$B$126,2,0)/1000000 -> 0.082952 | AD47: =AB47-AC47 -> 0.000323
A48: STEPONE | B48: Yes | C48: CAM STEP ONE | D48: Model | E48: On Original Risk List | F48: =VLOOKUP(A48,'[1]Model portfolios'!$A$2:$L$142,2,FALSE) -> From Risk - Fund Responsibility - Model Portfolios | G48: =VLOOKUP($A48,'[2]Desk mapping'!$G:$L,5,FALSE) -> Allocation Driven Strategies | H48: =VLOOKUP($A48,'[2]Desk mapping'!$G:$L,6,FALSE) -> Conservative | K48: AMUNDI.IRL/INV/MAS/PMG | L48: BUONO SALVATORE | M48: To be Affected | O48: =VLOOKUP(A48,'Audit AUM File'!A:B,2,FALSE) -> 1.2276648e+08 | P48: =VLOOKUP(A48,[3]AUM!$A$3:$B$131,2,0) -> 78465 | R48: =+IF(D48="",VLOOKUP(A48,'[2]Pivot for Jun AUM'!$A$5:$B$121,2,FALSE)) -> FALSE | U48: =VLOOKUP(A48,'[3]Last Aum File'!$A$2:$B$1262,2,0) -> 77392 | V48: =+U48/1000000 -> 0.077392 | W48: =+IF(OR(A48="HF11",A48="PACIFAI"),0,IF(A48="MUSG",P48-U48/2,P48-U48)) -> 1073 | X48: =+IF(ISNA(W48),0,W48) -> 1073 | Y48: =P48/1000000 -> 0.078465 | Z48: =X48/1000000 -> 0.001073 | AA48: =T48/1000000 -> 0 | AB48: =VLOOKUP(A48,[3]AUM!$A$3:$B$131,2,0)/1000000 -> 0.078465 | AC48: =VLOOKUP(A48,'[3]Last Aum File'!$A$2:$B$126,2,0)/1000000 -> 0.077392 | AD48: =AB48-AC48 -> 0.001073
A49: CSVILUPPO | B49: Yes | C49: CAM SVILUPPO | D49: Model | E49: On Original Risk List | F49: =VLOOKUP(A49,'[1]Model portfolios'!$A$2:$L$142,2,FALSE) -> From Risk - Fund Responsibility - Model Portfolios | G49: =VLOOKUP($A49,'[2]Desk mapping'!$G:$L,5,FALSE) -> Allocation Driven Strategies | H49: =VLOOKUP($A49,'[2]Desk mapping'!$G:$L,6,FALSE) -> Growth | K49: AMUNDI.IRL/INV/MAS/PMG | L49: BUONO SALVATORE | M49: To be Affected | O49: =VLOOKUP(A49,'Audit AUM File'!A:B,2,FALSE) -> 2.2019777e+08 | P49: =VLOOKUP(A49,[3]AUM!$A$3:$B$131,2,0) -> 33771 | R49: =+IF(D49="",VLOOKUP(A49,'[2]Pivot for Jun AUM'!$A$5:$B$121,2,FALSE)) -> FALSE | U49: =VLOOKUP(A49,'[3]Last Aum File'!$A$2:$B$1262,2,0) -> 33771 | V49: =+U49/1000000 -> 0.033771 | W49: =+IF(OR(A49="HF11",A49="PACIFAI"),0,IF(A49="MUSG",P49-U49/2,P49-U49)) -> 0 | X49: =+IF(ISNA(W49),0,W49) -> 0 | Y49: =P49/1000000 -> 0.033771 | Z49: =X49/1000000 -> 0 | AA49: =T49/1000000 -> 0 | AB49: =VLOOKUP(A49,[3]AUM!$A$3:$B$131,2,0)/1000000 -> 0.033771 | AC49: =VLOOKUP(A49,'[3]Last Aum File'!$A$2:$B$126,2,0)/1000000 -> 0.033771 | AD49: =AB49-AC49 -> 0
A50: CTREND_20 | B50: Yes | C50: CAM TREND 20 | D50: Model | E50: On Original Risk List | F50: =VLOOKUP(A50,'[1]Model portfolios'!$A$2:$L$142,2,FALSE) -> From Risk - Fund Responsibility - Model Portfolios | G50: =VLOOKUP($A50,'[2]Desk mapping'!$G:$L,5,FALSE) -> Allocation Driven Strategies | H50: =VLOOKUP($A50,'[2]Desk mapping'!$G:$L,6,FALSE) -> Conservative | K50: AMUNDI.IRL/INV/MAS/PMG | L50: BUONO SALVATORE | M50: To be Affected | O50: =VLOOKUP(A50,'Audit AUM File'!A:B,2,FALSE) -> 1.265202e+08 | P50: =VLOOKUP(A50,[3]AUM!$A$3:$B$131,2,0) -> 23564 | R50: =+IF(D50="",VLOOKUP(A50,'[2]Pivot for Jun AUM'!$A$5:$B$121,2,FALSE)) -> FALSE | U50: =VLOOKUP(A50,'[3]Last Aum File'!$A$2:$B$1262,2,0) -> 23564 | V50: =+U50/1000000 -> 0.023564 | W50: =+IF(OR(A50="HF11",A50="PACIFAI"),0,IF(A50="MUSG",P50-U50/2,P50-U50)) -> 0 | X50: =+IF(ISNA(W50),0,W50) -> 0 | Y50: =P50/1000000 -> 0.023564 | Z50: =X50/1000000 -> 0 | AA50: =T50/1000000 -> 0 | AB50: =VLOOKUP(A50,[3]AUM!$A$3:$B$131,2,0)/1000000 -> 0.023564 | AC50: =VLOOKUP(A50,'[3]Last Aum File'!$A$2:$B$126,2,0)/1000000 -> 0.023564 | AD50: =AB50-AC50 -> 0
A51: MLIFEBND | B51: Yes | C51: Life Program Bond | D51: Model | E51: On Original Risk List | F51: =VLOOKUP(A51,'[1]Model portfolios'!$A$2:$L$142,2,FALSE) -> From Risk - Fund Responsibility - Model Portfolios | G51: =VLOOKUP($A51,'[2]Desk mapping'!$G:$L,5,FALSE) -> Allocation Driven Strategies | H51: =VLOOKUP($A51,'[2]Desk mapping'!$G:$L,6,FALSE) -> Conservative | K51: AMUNDI.IRL/INV/MAS/PMG | L51: BUONO SALVATORE | M51: To be Affected | O51: =VLOOKUP(A51,'Audit AUM File'!A:B,2,FALSE) -> 1.5634431e+08 | P51: =VLOOKUP(A51,[3]AUM!$A$3:$B$131,2,0) -> 86278219 | R51: =+IF(D51="",VLOOKUP(A51,'[2]Pivot for Jun AUM'!$A$5:$B$121,2,FALSE)) -> FALSE | T51: =VLOOKUP(A51,[4]Flows!$A$3:$D$1206,4,0) -> -4047481.5 | U51: =VLOOKUP(A51,'[3]Last Aum File'!$A$2:$B$1262,2,0) -> 89492990 | V51: =+U51/1000000 -> 89.49299 | W51: =+IF(OR(A51="HF11",A51="PACIFAI"),0,IF(A51="MUSG",P51-U51/2,P51-U51)) -> -3214771 | X51: =+IF(ISNA(W51),0,W51) -> -3214771 | Y51: =P51/1000000 -> 86.278219 | Z51: =X51/1000000 -> -3.214771 | AA51: =T51/1000000 -> -4.0474815 | AB51: =VLOOKUP(A51,[3]AUM!$A$3:$B$131,2,0)/1000000 -> 86.278219 | AC51: =VLOOKUP(A51,'[3]Last Aum File'!$A$2:$B$126,2,0)/1000000 -> 89.49299 | AD51: =AB51-AC51 -> -3.214771
A52: MLPFLEX | B52: Yes | C52: Life Program Flessibile | D52: Model | E52: On Original Risk List | F52: =VLOOKUP(A52,'[1]Model portfolios'!$A$2:$L$142,2,FALSE) -> From Risk - Fund Responsibility - Model Portfolios | G52: =VLOOKUP($A52,'[2]Desk mapping'!$G:$L,5,FALSE) -> Allocation Driven Strategies | H52: =VLOOKUP($A52,'[2]Desk mapping'!$G:$L,6,FALSE) -> Flexible | K52: AMUNDI.IRL/INV/MAS/PMG | L52: BUONO SALVATORE | M52: To be Affected | O52: =VLOOKUP(A52,'Audit AUM File'!A:B,2,FALSE) -> 1.2313964e+08 | P52: =VLOOKUP(A52,[3]AUM!$A$3:$B$131,2,0) -> 24819922 | R52: =+IF(D52="",VLOOKUP(A52,'[2]Pivot for Jun AUM'!$A$5:$B$121,2,FALSE)) -> FALSE | T52: =VLOOKUP(A52,[4]Flows!$A$3:$D$1206,4,0) -> -916591.72 | U52: =VLOOKUP(A52,'[3]Last Aum File'!$A$2:$B$1262,2,0) -> 25631869 | V52: =+U52/1000000 -> 25.631869 | W52: =+IF(OR(A52="HF11",A52="PACIFAI"),0,IF(A52="MUSG",P52-U52/2,P52-U52)) -> -811947 | X52: =+IF(ISNA(W52),0,W52) -> -811947 | Y52: =P52/1000000 -> 24.819922 | Z52: =X52/1000000 -> -0.811947 | AA52: =T52/1000000 -> -0.91659172 | AB52: =VLOOKUP(A52,[3]AUM!$A$3:$B$131,2,0)/1000000 -> 24.819922 | AC52: =VLOOKUP(A52,'[3]Last Aum File'!$A$2:$B$126,2,0)/1000000 -> 25.631869 | AD52: =AB52-AC52 -> -0.811947
A53: PP1-3Y | B53: Yes | C53: PL Euro Bond 1 to 3 years | D53: Model | E53: On Original Risk List | F53: =VLOOKUP(A53,'[1]Model portfolios'!$A$2:$L$142,2,FALSE) -> From Risk - Fund Responsibility - Model Portfolios | G53: =VLOOKUP($A53,'[2]Desk mapping'!$G:$L,5,FALSE) -> Allocation Driven Strategies | H53: =VLOOKUP($A53,'[2]Desk mapping'!$G:$L,6,FALSE) -> Conservative | K53: AMUNDI.IRL/INV/MAS/PMG | L53: BUONO SALVATORE | M53: To be Affected | O53: =VLOOKUP(A53,'Audit AUM File'!A:B,2,FALSE) -> 1.2127757e+08 | P53: =VLOOKUP(A53,[3]AUM!$A$3:$B$131,2,0) -> 87573063 | R53: =+IF(D53="",VLOOKUP(A53,'[2]Pivot for Jun AUM'!$A$5:$B$121,2,FALSE)) -> FALSE | T53: =VLOOKUP(A53,[4]Flows!$A$3:$D$1206,4,0) -> -4628998.6 | U53: =VLOOKUP(A53,'[3]Last Aum File'!$A$2:$B$1262,2,0) -> 91452737 | V53: =+U53/1000000 -> 91.452737 | W53: =+IF(OR(A53="HF11",A53="PACIFAI"),0,IF(A53="MUSG",P53-U53/2,P53-U53)) -> -3879674 | X53: =+IF(ISNA(W53),0,W53) -> -3879674 | Y53: =P53/1000000 -> 87.573063 | Z53: =X53/1000000 -> -3.879674 | AA53: =T53/1000000 -> -4.6289986 | AB53: =VLOOKUP(A53,[3]AUM!$A$3:$B$131,2,0)/1000000 -> 87.573063 | AC53: =VLOOKUP(A53,'[3]Last Aum File'!$A$2:$B$126,2,0)/1000000 -> 91.452737 | AD53: =AB53-AC53 -> -3.879674
A54: PLIC | B54: Yes | C54: PL Income Clock | D54: Model | E54: On Original Risk List | F54: =VLOOKUP(A54,'[1]Model portfolios'!$A$2:$L$142,2,FALSE) -> From Risk - Fund Responsibility - Model Portfolios | G54: =VLOOKUP($A54,'[2]Desk mapping'!$G:$L,5,FALSE) -> Allocation Driven Strategies | H54: =VLOOKUP($A54,'[2]Desk mapping'!$G:$L,6,FALSE) -> Flexible | K54: AMUNDI.IRL/INV/MAS/PMG | L54: BUONO SALVATORE | M54: To be Affected | O54: =VLOOKUP(A54,'Audit AUM File'!A:B,2,FALSE) -> 2.0312746e+08 | P54: =VLOOKUP(A54,[3]AUM!$A$3:$B$131,2,0) -> 33652386 | R54: =+IF(D54="",VLOOKUP(A54,'[2]Pivot for Jun AUM'!$A$5:$B$121,2,FALSE)) -> FALSE | T54: =VLOOKUP(A54,[4]Flows!$A$3:$D$1206,4,0) -> -373108.56 | U54: =VLOOKUP(A54,'[3]Last Aum File'!$A$2:$B$1262,2,0) -> 33951455 | V54: =+U54/1000000 -> 33.951455 | W54: =+IF(OR(A54="HF11",A54="PACIFAI"),0,IF(A54="MUSG",P54-U54/2,P54-U54)) -> -299069 | X54: =+IF(ISNA(W54),0,W54) -> -299069 | Y54: =P54/1000000 -> 33.652386 | Z54: =X54/1000000 -> -0.299069 | AA54: =T54/1000000 -> -0.37310856 | AB54: =VLOOKUP(A54,[3]AUM!$A$3:$B$131,2,0)/1000000 -> 33.652386 | AC54: =VLOOKUP(A54,'[3]Last Aum File'!$A$2:$B$126,2,0)/1000000 -> 33.951455 | AD54: =AB54-AC54 -> -0.299069
A55: ULBIL | B55: Yes | C55: UL BILANCIATA | D55: Model | E55: On Original Risk List | F55: =VLOOKUP(A55,'[1]Model portfolios'!$A$2:$L$142,2,FALSE) -> From Risk - Fund Responsibility - Model Portfolios | G55: =VLOOKUP($A55,'[2]Desk mapping'!$G:$L,5,FALSE) -> Allocation Driven Strategies | H55: =VLOOKUP($A55,'[2]Desk mapping'!$G:$L,6,FALSE) -> Moderate | K55: AMUNDI.IRL/INV/MAS/PMG | L55: BUONO SALVATORE | M55: To be Affected | O55: =VLOOKUP(A55,'Audit AUM File'!A:B,2,FALSE) -> 1.7177284e+08 | P55: =VLOOKUP(A55,[3]AUM!$A$3:$B$131,2,0) -> 10517233 | R55: =+IF(D55="",VLOOKUP(A55,'[2]Pivot for Jun AUM'!$A$5:$B$121,2,FALSE)) -> FALSE | T55: =VLOOKUP(A55,[4]Flows!$A$3:$D$1206,4,0) -> -614112.52 | U55: =VLOOKUP(A55,'[3]Last Aum File'!$A$2:$B$1262,2,0) -> 11114645 | V55: =+U55/1000000 -> 11.114645 | W55: =+IF(OR(A55="HF11",A55="PACIFAI"),0,IF(A55="MUSG",P55-U55/2,P55-U55)) -> -597412 | X55: =+IF(ISNA(W55),0,W55) -> -597412 | Y55: =P55/1000000 -> 10.517233 | Z55: =X55/1000000 -> -0.597412 | AA55: =T55/1000000 -> -0.61411252 | AB55: =VLOOKUP(A55,[3]AUM!$A$3:$B$131,2,0)/1000000 -> 10.517233 | AC55: =VLOOKUP(A55,'[3]Last Aum File'!$A$2:$B$126,2,0)/1000000 -> 11.114645 | AD55: =AB55-AC55 -> -0.597412
A56: ULBILPIU | B56: Yes | C56: UL BILANCIATA PIU | D56: Model | E56: On Original Risk List | F56: =VLOOKUP(A56,'[1]Model portfolios'!$A$2:$L$142,2,FALSE) -> From Risk - Fund Responsibility - Model Portfolios | G56: =VLOOKUP($A56,'[2]Desk mapping'!$G:$L,5,FALSE) -> Allocation Driven Strategies | H56: =VLOOKUP($A56,'[2]Desk mapping'!$G:$L,6,FALSE) -> Moderate | K56: AMUNDI.IRL/INV/MAS/PMG | L56: BUONO SALVATORE | M56: To be Affected | O56: =VLOOKUP(A56,'Audit AUM File'!A:B,2,FALSE) -> 1.7381581e+08 | P56: =VLOOKUP(A56,[3]AUM!$A$3:$B$131,2,0) -> 17251250 | R56: =+IF(D56="",VLOOKUP(A56,'[2]Pivot for Jun AUM'!$A$5:$B$121,2,FALSE)) -> FALSE | T56: =VLOOKUP(A56,[4]Flows!$A$3:$D$1206,4,0) -> -514722.5 | U56: =VLOOKUP(A56,'[3]Last Aum File'!$A$2:$B$1262,2,0) -> 17726631 | V56: =+U56/1000000 -> 17.726631 | W56: =+IF(OR(A56="HF11",A56="PACIFAI"),0,IF(A56="MUSG",P56-U56/2,P56-U56)) -> -475381 | X56: =+IF(ISNA(W56),0,W56) -> -475381 | Y56: =P56/1000000 -> 17.25125 | Z56: =X56/1000000 -> -0.475381 | AA56: =T56/1000000 -> -0.5147225 | AB56: =VLOOKUP(A56,[3]AUM!$A$3:$B$131,2,0)/1000000 -> 17.25125 | AC56: =VLOOKUP(A56,'[3]Last Aum File'!$A$2:$B$126,2,0)/1000000 -> 17.726631 | AD56: =AB56-AC56 -> -0.475381
A57: ULDIN | B57: Yes | C57: UL DINAMICA | D57: Model | E57: On Original Risk List | F57: =VLOOKUP(A57,'[1]Model portfolios'!$A$2:$L$142,2,FALSE) -> From Risk - Fund Responsibility - Model Portfolios | G57: =VLOOKUP($A57,'[2]Desk mapping'!$G:$L,5,FALSE) -> Allocation Driven Strategies | H57: =VLOOKUP($A57,'[2]Desk mapping'!$G:$L,6,FALSE) -> Growth | K57: AMUNDI.IRL/INV/MAS/PMG | L57: BUONO SALVATORE | M57: To be Affected | O57: =VLOOKUP(A57,'Audit AUM File'!A:B,2,FALSE) -> 1.7811059e+08 | P57: =VLOOKUP(A57,[3]AUM!$A$3:$B$131,2,0) -> 18063937 | R57: =+IF(D57="",VLOOKUP(A57,'[2]Pivot for Jun AUM'!$A$5:$B$121,2,FALSE)) -> FALSE | T57: =VLOOKUP(A57,[4]Flows!$A$3:$D$1206,4,0) -> -905874.81 | U57: =VLOOKUP(A57,'[3]Last Aum File'!$A$2:$B$1262,2,0) -> 19013976 | V57: =+U57/1000000 -> 19.013976 | W57: =+IF(OR(A57="HF11",A57="PACIFAI"),0,IF(A57="MUSG",P57-U57/2,P57-U57)) -> -950039 | X57: =+IF(ISNA(W57),0,W57) -> -950039 | Y57: =P57/1000000 -> 18.063937 | Z57: =X57/1000000 -> -0.950039 | AA57: =T57/1000000 -> -0.90587481 | AB57: =VLOOKUP(A57,[3]AUM!$A$3:$B$131,2,0)/1000000 -> 18.063937 | AC57: =VLOOKUP(A57,'[3]Last Aum File'!$A$2:$B$126,2,0)/1000000 -> 19.013976 | AD57: =AB57-AC57 -> -0.950039
A58: ULP | B58: Yes | C58: UL PRUDENTE | D58: Model | E58: On Original Risk List | F58: =VLOOKUP(A58,'[1]Model portfolios'!$A$2:$L$142,2,FALSE) -> From Risk - Fund Responsibility - Model Portfolios | G58: =VLOOKUP($A58,'[2]Desk mapping'!$G:$L,5,FALSE) -> Allocation Driven Strategies | H58: =VLOOKUP($A58,'[2]Desk mapping'!$G:$L,6,FALSE) -> Conservative | K58: AMUNDI.IRL/INV/MAS/PMG | L58: BUONO SALVATORE | M58: To be Affected | O58: =VLOOKUP(A58,'Audit AUM File'!A:B,2,FALSE) -> 1.6029224e+08 | P58: =VLOOKUP(A58,[3]AUM!$A$3:$B$131,2,0) -> 12030736 | R58: =+IF(D58="",VLOOKUP(A58,'[2]Pivot for Jun AUM'!$A$5:$B$121,2,FALSE)) -> FALSE | T58: =VLOOKUP(A58,[4]Flows!$A$3:$D$1206,4,0) -> -668763.87 | U58: =VLOOKUP(A58,'[3]Last Aum File'!$A$2:$B$1262,2,0) -> 12689996 | V58: =+U58/1000000 -> 12.689996 | W58: =+IF(OR(A58="HF11",A58="PACIFAI"),0,IF(A58="MUSG",P58-U58/2,P58-U58)) -> -659260 | X58: =+IF(ISNA(W58),0,W58) -> -659260 | Y58: =P58/1000000 -> 12.030736 | Z58: =X58/1000000 -> -0.65926 | AA58: =T58/1000000 -> -0.66876387 | AB58: =VLOOKUP(A58,[3]AUM!$A$3:$B$131,2,0)/1000000 -> 12.030736 | AC58: =VLOOKUP(A58,'[3]Last Aum File'!$A$2:$B$126,2,0)/1000000 -> 12.689996 | AD58: =AB58-AC58 -> -0.65926
A59: ULPRUD | B59: Yes | C59: UL PRUDENTE PIU | D59: Model | E59: On Original Risk List | F59: =VLOOKUP(A59,'[1]Model portfolios'!$A$2:$L$142,2,FALSE) -> From Risk - Fund Responsibility - Model Portfolios | G59: =VLOOKUP($A59,'[2]Desk mapping'!$G:$L,5,FALSE) -> Allocation Driven Strategies | H59: =VLOOKUP($A59,'[2]Desk mapping'!$G:$L,6,FALSE) -> Conservative | K59: AMUNDI.IRL/INV/MAS/PMG | L59: BUONO SALVATORE | M59: To be Affected | O59: =VLOOKUP(A59,'Audit AUM File'!A:B,2,FALSE) -> 1.7016693e+08 | P59: =VLOOKUP(A59,[3]AUM!$A$3:$B$131,2,0) -> 15554245 | R59: =+IF(D59="",VLOOKUP(A59,'[2]Pivot for Jun AUM'!$A$5:$B$121,2,FALSE)) -> FALSE | T59: =VLOOKUP(A59,[4]Flows!$A$3:$D$1206,4,0) -> -673150.85 | U59: =VLOOKUP(A59,'[3]Last Aum File'!$A$2:$B$1262,2,0) -> 16167560 | V59: =+U59/1000000 -> 16.16756 | W59: =+IF(OR(A59="HF11",A59="PACIFAI"),0,IF(A59="MUSG",P59-U59/2,P59-U59)) -> -613315 | X59: =+IF(ISNA(W59),0,W59) -> -613315 | Y59: =P59/1000000 -> 15.554245 | Z59: =X59/1000000 -> -0.613315 | AA59: =T59/1000000 -> -0.67315085 | AB59: =VLOOKUP(A59,[3]AUM!$A$3:$B$131,2,0)/1000000 -> 15.554245 | AC59: =VLOOKUP(A59,'[3]Last Aum File'!$A$2:$B$1026,2,0)/1000000 -> 16.16756 | AD59: =AB59-AC59 -> -0.613315
A60: DINAR1TF | B60: Yes | C60: UNIFLEX ACTIVE 1 | D60: Model | E60: On Original Risk List | F60: =VLOOKUP(A60,'[1]Model portfolios'!$A$2:$L$142,2,FALSE) -> From Risk - Fund Responsibility - Model Portfolios | G60: =VLOOKUP($A60,'[2]Desk mapping'!$G:$L,5,FALSE) -> Allocation Driven Strategies | H60: =VLOOKUP($A60,'[2]Desk mapping'!$G:$L,6,FALSE) -> Moderate | K60: AMUNDI.IRL/INV/MAS/PMG | L60: BUONO SALVATORE | M60: To be Affected | O60: =VLOOKUP(A60,'Audit AUM File'!A:B,2,FALSE) -> 1.4335027e+08 | P60: =VLOOKUP(A60,[3]AUM!$A$3:$B$131,2,0) -> 1363503 | R60: =+IF(D60="",VLOOKUP(A60,'[2]Pivot for Jun AUM'!$A$5:$B$121,2,FALSE)) -> FALSE | T60: =VLOOKUP(A60,[4]Flows!$A$3:$D$1206,4,0) -> -8576.35 | U60: =VLOOKUP(A60,'[3]Last Aum File'!$A$2:$B$1262,2,0) -> 1364632 | V60: =+U60/1000000 -> 1.364632 | W60: =+IF(OR(A60="HF11",A60="PACIFAI"),0,IF(A60="MUSG",P60-U60/2,P60-U60)) -> -1129 | X60: =+IF(ISNA(W60),0,W60) -> -1129 | Y60: =P60/1000000 -> 1.363503 | Z60: =X60/1000000 -> -0.001129 | AA60: =T60/1000000 -> -0.00857635 | AB60: =VLOOKUP(A60,[3]AUM!$A$3:$B$131,2,0)/1000000 -> 1.363503 | AC60: =VLOOKUP(A60,'[3]Last Aum File'!$A$2:$B$126,2,0)/1000000 -> 1.364632 | AD60: =AB60-AC60 -> -0.001129
A61: DINAR2TF | B61: Yes | C61: UNIFLEX ACTIVE 2 | D61: Model | E61: On Original Risk List | F61: =VLOOKUP(A61,'[1]Model portfolios'!$A$2:$L$142,2,FALSE) -> From Risk - Fund Responsibility - Model Portfolios | G61: =VLOOKUP($A61,'[2]Desk mapping'!$G:$L,5,FALSE) -> Allocation Driven Strategies | H61: =VLOOKUP($A61,'[2]Desk mapping'!$G:$L,6,FALSE) -> Moderate | K61: AMUNDI.IRL/INV/MAS/PMG | L61: BUONO SALVATORE | M61: To be Affected | O61: =VLOOKUP(A61,'Audit AUM File'!A:B,2,FALSE) -> 1.5249917e+08 | P61: =VLOOKUP(A61,[3]AUM!$A$3:$B$131,2,0) -> 26945800 | R61: =+IF(D61="",VLOOKUP(A61,'[2]Pivot for Jun AUM'!$A$5:$B$121,2,FALSE)) -> FALSE | T61: =VLOOKUP(A61,[4]Flows!$A$3:$D$1206,4,0) -> -155507.1 | U61: =VLOOKUP(A61,'[3]Last Aum File'!$A$2:$B$1262,2,0) -> 26955727 | V61: =+U61/1000000 -> 26.955727 | W61: =+IF(OR(A61="HF11",A61="PACIFAI"),0,IF(A61="MUSG",P61-U61/2,P61-U61)) -> -9927 | X61: =+IF(ISNA(W61),0,W61) -> -9927 | Y61: =P61/1000000 -> 26.9458 | Z61: =X61/1000000 -> -0.009927 | AA61: =T61/1000000 -> -0.1555071 | AB61: =VLOOKUP(A61,[3]AUM!$A$3:$B$131,2,0)/1000000 -> 26.9458 | AC61: =VLOOKUP(A61,'[3]Last Aum File'!$A$2:$B$126,2,0)/1000000 -> 26.955727 | AD61: =AB61-AC61 -> -0.009927
A62: DINAR3TF | B62: Yes | C62: UNIFLEX ACTIVE 3 | D62: Model | E62: On Original Risk List | F62: =VLOOKUP(A62,'[1]Model portfolios'!$A$2:$L$142,2,FALSE) -> From Risk - Fund Responsibility - Model Portfolios | G62: =VLOOKUP($A62,'[2]Desk mapping'!$G:$L,5,FALSE) -> Allocation Driven Strategies | H62: =VLOOKUP($A62,'[2]Desk mapping'!$G:$L,6,FALSE) -> Moderate | K62: AMUNDI.IRL/INV/MAS/PMG | L62: BUONO SALVATORE | M62: To be Affected | O62: =VLOOKUP(A62,'Audit AUM File'!A:B,2,FALSE) -> 1.5739506e+08 | P62: =VLOOKUP(A62,[3]AUM!$A$3:$B$131,2,0) -> 795570 | R62: =+IF(D62="",VLOOKUP(A62,'[2]Pivot for Jun AUM'!$A$5:$B$121,2,FALSE)) -> FALSE | T62: =VLOOKUP(A62,[4]Flows!$A$3:$D$1206,4,0) -> -3761.65 | U62: =VLOOKUP(A62,'[3]Last Aum File'!$A$2:$B$1262,2,0) -> 794524 | V62: =+U62/1000000 -> 0.794524 | W62: =+IF(OR(A62="HF11",A62="PACIFAI"),0,IF(A62="MUSG",P62-U62/2,P62-U62)) -> 1046 | X62: =+IF(ISNA(W62),0,W62) -> 1046 | Y62: =P62/1000000 -> 0.79557 | Z62: =X62/1000000 -> 0.001046 | AA62: =T62/1000000 -> -0.00376165 | AB62: =VLOOKUP(A62,[3]AUM!$A$3:$B$131,2,0)/1000000 -> 0.79557 | AC62: =VLOOKUP(A62,'[3]Last Aum File'!$A$2:$B$126,2,0)/1000000 -> 0.794524 | AD62: =AB62-AC62 -> 0.001046
A63: MATRUNIP | B63: Yes | C63: Unit Linked A TR UNIPLAN | D63: Model | E63: On Original Risk List | F63: =VLOOKUP(A63,'[1]Model portfolios'!$A$2:$L$142,2,FALSE) -> From Risk - Fund Responsibility - Model Portfolios | G63: =VLOOKUP($A63,'[2]Desk mapping'!$G:$L,5,FALSE) -> Allocation Driven Strategies | H63: =VLOOKUP($A63,'[2]Desk mapping'!$G:$L,6,FALSE) -> Flexible | K63: AMUNDI.IRL/INV/MAS/PMG | L63: BUONO SALVATORE | M63: To be Affected | O63: =VLOOKUP(A63,'Audit AUM File'!A:B,2,FALSE) -> 1.2398675e+08 | P63: =VLOOKUP(A63,[3]AUM!$A$3:$B$131,2,0) -> 12280450 | R63: =+IF(D63="",VLOOKUP(A63,'[2]Pivot for Jun AUM'!$A$5:$B$121,2,FALSE)) -> FALSE | T63: =VLOOKUP(A63,[4]Flows!$A$3:$D$1206,4,0) -> -644373.76 | U63: =VLOOKUP(A63,'[3]Last Aum File'!$A$2:$B$1262,2,0) -> 12897265 | V63: =+U63/1000000 -> 12.897265 | W63: =+IF(OR(A63="HF11",A63="PACIFAI"),0,IF(A63="MUSG",P63-U63/2,P63-U63)) -> -616815 | X63: =+IF(ISNA(W63),0,W63) -> -616815 | Y63: =P63/1000000 -> 12.28045 | Z63: =X63/1000000 -> -0.616815 | AA63: =T63/1000000 -> -0.64437376 | AB63: =VLOOKUP(A63,[3]AUM!$A$3:$B$131,2,0)/1000000 -> 12.28045 | AC63: =VLOOKUP(A63,'[3]Last Aum File'!$A$2:$B$126,2,0)/1000000 -> 12.897265 | AD63: =AB63-AC63 -> -0.616815
A64: MUNIP | B64: Yes | C64: Unit Linked AMix UNIPLAN | D64: Model | E64: On Original Risk List | F64: =VLOOKUP(A64,'[1]Model portfolios'!$A$2:$L$142,2,FALSE) -> From Risk - Fund Responsibility - Model Portfolios | G64: =VLOOKUP($A64,'[2]Desk mapping'!$G:$L,5,FALSE) -> Allocation Driven Strategies | H64: =VLOOKUP($A64,'[2]Desk mapping'!$G:$L,6,FALSE) -> Moderate | K64: AMUNDI.IRL/INV/MAS/PMG | L64: BUONO SALVATORE | M64: To be Affected | O64: =VLOOKUP(A64,'Audit AUM File'!A:B,2,FALSE) -> 1.6239307e+08 | P64: =VLOOKUP(A64,[3]AUM!$A$3:$B$131,2,0) -> 255343 | R64: =+IF(D64="",VLOOKUP(A64,'[2]Pivot for Jun AUM'!$A$5:$B$121,2,FALSE)) -> FALSE | T64: =VLOOKUP(A64,[4]Flows!$A$3:$D$1206,4,0) -> -17807.07 | U64: =VLOOKUP(A64,'[3]Last Aum File'!$A$2:$B$1262,2,0) -> 272765 | V64: =+U64/1000000 -> 0.272765 | W64: =+IF(OR(A64="HF11",A64="PACIFAI"),0,IF(A64="MUSG",P64-U64/2,P64-U64)) -> -17422 | X64: =+IF(ISNA(W64),0,W64) -> -17422 | Y64: =P64/1000000 -> 0.255343 | Z64: =X64/1000000 -> -0.017422 | AA64: =T64/1000000 -> -0.01780707 | AB64: =VLOOKUP(A64,[3]AUM!$A$3:$B$131,2,0)/1000000 -> 0.255343 | AC64: =VLOOKUP(A64,'[3]Last Aum File'!$A$2:$B$126,2,0)/1000000 -> 0.272765 | AD64: =AB64-AC64 -> -0.017422
A65: MEPF2N | B65: Yes | C65: UNIT LINKED E2 NEW | D65: Model | E65: On Original Risk List | F65: =VLOOKUP(A65,'[1]Model portfolios'!$A$2:$L$142,2,FALSE) -> From Risk - Fund Responsibility - Model Portfolios | G65: =VLOOKUP($A65,'[2]Desk mapping'!$G:$L,5,FALSE) -> Allocation Driven Strategies | H65: =VLOOKUP($A65,'[2]Desk mapping'!$G:$L,6,FALSE) -> Conservative | K65: AMUNDI.IRL/INV/MAS/PMG | L65: BUONO SALVATORE | M65: To be Affected | O65: =VLOOKUP(A65,'Audit AUM File'!A:B,2,FALSE) -> 1.5611757e+08 | P65: =VLOOKUP(A65,[3]AUM!$A$3:$B$131,2,0) -> 7616069 | R65: =+IF(D65="",VLOOKUP(A65,'[2]Pivot for Jun AUM'!$A$5:$B$121,2,FALSE)) -> FALSE | T65: =VLOOKUP(A65,[4]Flows!$A$3:$D$1206,4,0) -> -350635.68 | U65: =VLOOKUP(A65,'[3]Last Aum File'!$A$2:$B$1262,2,0) -> 7920799 | V65: =+U65/1000000 -> 7.920799 | W65: =+IF(OR(A65="HF11",A65="PACIFAI"),0,IF(A65="MUSG",P65-U65/2,P65-U65)) -> -304730 | X65: =+IF(ISNA(W65),0,W65) -> -304730 | Y65: =P65/1000000 -> 7.616069 | Z65: =X65/1000000 -> -0.30473 | AA65: =T65/1000000 -> -0.35063568 | AB65: =VLOOKUP(A65,[3]AUM!$A$3:$B$131,2,0)/1000000 -> 7.616069 | AC65: =VLOOKUP(A65,'[3]Last Aum File'!$A$2:$B$126,2,0)/1000000 -> 7.920799 | AD65: =AB65-AC65 -> -0.30473
A66: MEPF5 | B66: Yes | C66: UNIT LINKED E3 NEW | D66: Model | E66: On Original Risk List | F66: =VLOOKUP(A66,'[1]Model portfolios'!$A$2:$L$142,2,FALSE) -> From Risk - Fund Responsibility - Model Portfolios | G66: =VLOOKUP($A66,'[2]Desk mapping'!$G:$L,5,FALSE) -> Allocation Driven Strategies | H66: =VLOOKUP($A66,'[2]Desk mapping'!$G:$L,6,FALSE) -> Conservative | K66: AMUNDI.IRL/INV/MAS/PMG | L66: BUONO SALVATORE | M66: To be Affected | O66: =VLOOKUP(A66,'Audit AUM File'!A:B,2,FALSE) -> 1.661414e+08 | P66: =VLOOKUP(A66,[3]AUM!$A$3:$B$131,2,0) -> 72484395 | R66: =+IF(D66="",VLOOKUP(A66,'[2]Pivot for Jun AUM'!$A$5:$B$121,2,FALSE)) -> FALSE | T66: =VLOOKUP(A66,[4]Flows!$A$3:$D$1206,4,0) -> -1379157.7 | U66: =VLOOKUP(A66,'[3]Last Aum File'!$A$2:$B$1262,2,0) -> 73864832 | V66: =+U66/1000000 -> 73.864832 | W66: =+IF(OR(A66="HF11",A66="PACIFAI"),0,IF(A66="MUSG",P66-U66/2,P66-U66)) -> -1380437 | X66: =+IF(ISNA(W66),0,W66) -> -1380437 | Y66: =P66/1000000 -> 72.484395 | Z66: =X66/1000000 -> -1.380437 | AA66: =T66/1000000 -> -1.3791577 | AB66: =VLOOKUP(A66,[3]AUM!$A$3:$B$131,2,0)/1000000 -> 72.484395 | AC66: =VLOOKUP(A66,'[3]Last Aum File'!$A$2:$B$126,2,0)/1000000 -> 73.864832 | AD66: =AB66-AC66 -> -1.380437
A67: MEPF6 | B67: Yes | C67: UNIT LINKED E4 NEW | D67: Model | E67: On Original Risk List | F67: =VLOOKUP(A67,'[1]Model portfolios'!$A$2:$L$142,2,FALSE) -> From Risk - Fund Responsibility - Model Portfolios | G67: =VLOOKUP($A67,'[2]Desk mapping'!$G:$L,5,FALSE) -> Allocation Driven Strategies | H67: =VLOOKUP($A67,'[2]Desk mapping'!$G:$L,6,FALSE) -> Moderate | K67: AMUNDI.IRL/INV/MAS/PMG | L67: BUONO SALVATORE | M67: To be Affected | O67: =VLOOKUP(A67,'Audit AUM File'!A:B,2,FALSE) -> 1.5811358e+08 | P67: =VLOOKUP(A67,[3]AUM!$A$3:$B$131,2,0) -> 64408792 | R67: =+IF(D67="",VLOOKUP(A67,'[2]Pivot for Jun AUM'!$A$5:$B$121,2,FALSE)) -> FALSE | T67: =VLOOKUP(A67,[4]Flows!$A$3:$D$1206,4,0) -> -1481691.5 | U67: =VLOOKUP(A67,'[3]Last Aum File'!$A$2:$B$1262,2,0) -> 65910670 | V67: =+U67/1000000 -> 65.91067 | W67: =+IF(OR(A67="HF11",A67="PACIFAI"),0,IF(A67="MUSG",P67-U67/2,P67-U67)) -> -1501878 | X67: =+IF(ISNA(W67),0,W67) -> -1501878 | Y67: =P67/1000000 -> 64.408792 | Z67: =X67/1000000 -> -1.501878 | AA67: =T67/1000000 -> -1.4816915 | AB67: =VLOOKUP(A67,[3]AUM!$A$3:$B$131,2,0)/1000000 -> 64.408792 | AC67: =VLOOKUP(A67,'[3]Last Aum File'!$A$2:$B$126,2,0)/1000000 -> 65.91067 | AD67: =AB67-AC67 -> -1.501878
A68: MEPF8 | B68: Yes | C68: UNIT LINKED E6 NEW | D68: Model | E68: On Original Risk List | F68: =VLOOKUP(A68,'[1]Model portfolios'!$A$2:$L$142,2,FALSE) -> From Risk - Fund Responsibility - Model Portfolios | G68: =VLOOKUP($A68,'[2]Desk mapping'!$G:$L,5,FALSE) -> Allocation Driven Strategies | H68: =VLOOKUP($A68,'[2]Desk mapping'!$G:$L,6,FALSE) -> Growth | K68: AMUNDI.IRL/INV/MAS/PMG | L68: BUONO SALVATORE | M68: To be Affected | O68: =VLOOKUP(A68,'Audit AUM File'!A:B,2,FALSE) -> 1.4418415e+08 | P68: =VLOOKUP(A68,[3]AUM!$A$3:$B$131,2,0) -> 128787502 | R68: =+IF(D68="",VLOOKUP(A68,'[2]Pivot for Jun AUM'!$A$5:$B$121,2,FALSE)) -> FALSE | T68: =VLOOKUP(A68,[4]Flows!$A$3:$D$1206,4,0) -> -2446438.4 | U68: =VLOOKUP(A68,'[3]Last Aum File'!$A$2:$B$1262,2,0) -> 132733973 | V68: =+U68/1000000 -> 132.73397 | W68: =+IF(OR(A68="HF11",A68="PACIFAI"),0,IF(A68="MUSG",P68-U68/2,P68-U68)) -> -3946471 | X68: =+IF(ISNA(W68),0,W68) -> -3946471 | Y68: =P68/1000000 -> 128.7875 | Z68: =X68/1000000 -> -3.946471 | AA68: =T68/1000000 -> -2.4464384 | AB68: =VLOOKUP(A68,[3]AUM!$A$3:$B$131,2,0)/1000000 -> 128.7875 | AC68: =VLOOKUP(A68,'[3]Last Aum File'!$A$2:$B$126,2,0)/1000000 -> 132.73397 | AD68: =AB68-AC68 -> -3.946471
A69: ULG4NEW | B69: Yes | C69: UNIT LINKED G4 NEW | D69: Model | E69: On Original Risk List | F69: =VLOOKUP(A69,'[1]Model portfolios'!$A$2:$L$142,2,FALSE) -> From Risk - Fund Responsibility - Model Portfolios | G69: =VLOOKUP($A69,'[2]Desk mapping'!$G:$L,5,FALSE) -> Allocation Driven Strategies | H69: =VLOOKUP($A69,'[2]Desk mapping'!$G:$L,6,FALSE) -> Growth | K69: AMUNDI.IRL/INV/MAS/PMG | L69: BUONO SALVATORE | M69: To be Affected | O69: =VLOOKUP(A69,'Audit AUM File'!A:B,2,FALSE) -> 1.9697072e+08 | P69: =VLOOKUP(A69,[3]AUM!$A$3:$B$131,2,0) -> 411051 | R69: =+IF(D69="",VLOOKUP(A69,'[2]Pivot for Jun AUM'!$A$5:$B$121,2,FALSE)) -> FALSE | T69: =VLOOKUP(A69,[4]Flows!$A$3:$D$1206,4,0) -> -681.71 | U69: =VLOOKUP(A69,'[3]Last Aum File'!$A$2:$B$1262,2,0) -> 406916 | V69: =+U69/1000000 -> 0.406916 | W69: =+IF(OR(A69="HF11",A69="PACIFAI"),0,IF(A69="MUSG",P69-U69/2,P69-U69)) -> 4135 | X69: =+IF(ISNA(W69),0,W69) -> 4135 | Y69: =P69/1000000 -> 0.411051 | Z69: =X69/1000000 -> 0.004135 | AA69: =T69/1000000 -> -0.00068171 | AB69: =VLOOKUP(A69,[3]AUM!$A$3:$B$131,2,0)/1000000 -> 0.411051 | AC69: =VLOOKUP(A69,'[3]Last Aum File'!$A$2:$B$126,2,0)/1000000 -> 0.406916 | AD69: =AB69-AC69 -> 0.004135
A70: MEPF10 | B70: Yes | C70: UNIT LINKED G5 NEW | D70: Model | E70: On Original Risk List | F70: =VLOOKUP(A70,'[1]Model portfolios'!$A$2:$L$142,2,FALSE) -> From Risk - Fund Responsibility - Model Portfolios | G70: =VLOOKUP($A70,'[2]Desk mapping'!$G:$L,5,FALSE) -> Allocation Driven Strategies | H70: =VLOOKUP($A70,'[2]Desk mapping'!$G:$L,6,FALSE) -> Growth | K70: AMUNDI.IRL/INV/MAS/PMG | L70: BUONO SALVATORE | M70: To be Affected | O70: =VLOOKUP(A70,'Audit AUM File'!A:B,2,FALSE) -> 1.639045e+09 | P70: =VLOOKUP(A70,[3]AUM!$A$3:$B$131,2,0) -> 395535 | R70: =+IF(D70="",VLOOKUP(A70,'[2]Pivot for Jun AUM'!$A$5:$B$121,2,FALSE)) -> FALSE | T70: =VLOOKUP(A70,[4]Flows!$A$3:$D$1206,4,0) -> -1323.01 | U70: =VLOOKUP(A70,'[3]Last Aum File'!$A$2:$B$1262,2,0) -> 393174 | V70: =+U70/1000000 -> 0.393174 | W70: =+IF(OR(A70="HF11",A70="PACIFAI"),0,IF(A70="MUSG",P70-U70/2,P70-U70)) -> 2361 | X70: =+IF(ISNA(W70),0,W70) -> 2361 | Y70: =P70/1000000 -> 0.395535 | Z70: =X70/1000000 -> 0.002361 | AA70: =T70/1000000 -> -0.00132301 | AB70: =VLOOKUP(A70,[3]AUM!$A$3:$B$131,2,0)/1000000 -> 0.395535 | AC70: =VLOOKUP(A70,'[3]Last Aum File'!$A$2:$B$126,2,0)/1000000 -> 0.393174 | AD70: =AB70-AC70 -> 0.002361
A71: MEPF4 | B71: Yes | C71: Unit Linked OLD 4 | D71: Model | E71: On Original Risk List | F71: =VLOOKUP(A71,'[1]Model portfolios'!$A$2:$L$142,2,FALSE) -> From Risk - Fund Responsibility - Model Portfolios | G71: =VLOOKUP($A71,'[2]Desk mapping'!$G:$L,5,FALSE) -> Allocation Driven Strategies | H71: =VLOOKUP($A71,'[2]Desk mapping'!$G:$L,6,FALSE) -> Conservative | K71: AMUNDI.IRL/INV/MAS/PMG | L71: BUONO SALVATORE | M71: To be Affected | O71: =VLOOKUP(A71,'Audit AUM File'!A:B,2,FALSE) -> 1.5987907e+08 | P71: =VLOOKUP(A71,[3]AUM!$A$3:$B$131,2,0) -> 1067361 | R71: =+IF(D71="",VLOOKUP(A71,'[2]Pivot for Jun AUM'!$A$5:$B$121,2,FALSE)) -> FALSE | T71: =VLOOKUP(A71,[4]Flows!$A$3:$D$1206,4,0) -> -182908.59 | U71: =VLOOKUP(A71,'[3]Last Aum File'!$A$2:$B$1262,2,0) -> 1249574 | V71: =+U71/1000000 -> 1.249574 | W71: =+IF(OR(A71="HF11",A71="PACIFAI"),0,IF(A71="MUSG",P71-U71/2,P71-U71)) -> -182213 | X71: =+IF(ISNA(W71),0,W71) -> -182213 | Y71: =P71/1000000 -> 1.067361 | Z71: =X71/1000000 -> -0.182213 | AA71: =T71/1000000 -> -0.18290859 | AB71: =VLOOKUP(A71,[3]AUM!$A$3:$B$131,2,0)/1000000 -> 1.067361 | AC71: =VLOOKUP(A71,'[3]Last Aum File'!$A$2:$B$126,2,0)/1000000 -> 1.249574 | AD71: =AB71-AC71 -> -0.182213
... A88: MAM | B88: Yes | C88: CAM Settembre | D88: Model | E88: On Original Risk List | F88: =VLOOKUP(A88,'[1]Model portfolios'!$A$2:$L$142,2,FALSE) -> From Risk - Fund Responsibility - Model Portfolios | G88: =VLOOKUP($A88,'[2]Desk mapping'!$G:$L,5,FALSE) -> Outcome Oriented Strategies | H88: =VLOOKUP($A88,'[2]Desk mapping'!$G:$L,6,FALSE) -> Capital Protection | K88: AMUNDI.IRL/INV/MAS/PMG | L88: BUONO SALVATORE | M88: To be Affected | O88: =VLOOKUP(A88,'Audit AUM File'!A:B,2,FALSE) -> 1.0897799e+08 | P88: =VLOOKUP(A88,[3]AUM!$A$3:$B$131,2,0) -> 16557 | R88: =+IF(D88="",VLOOKUP(A88,'[2]Pivot for Jun AUM'!$A$5:$B$121,2,FALSE)) -> FALSE | T88: =VLOOKUP(A88,[4]Flows!$A$3:$D$1206,4,0) -> -579.69 | U88: =VLOOKUP(A88,'[3]Last Aum File'!$A$2:$B$1262,2,0) -> 16991 | V88: =+U88/1000000 -> 0.016991 | W88: =+IF(OR(A88="HF11",A88="PACIFAI"),0,IF(A88="MUSG",P88-U88/2,P88-U88)) -> -434 | X88: =+IF(ISNA(W88),0,W88) -> -434 | Y88: =P88/1000000 -> 0.016557 | Z88: =X88/1000000 -> -0.000434 | AA88: =T88/1000000 -> -0.00057969 | AB88: =VLOOKUP(A88,[3]AUM!$A$3:$B$131,2,0)/1000000 -> 0.016557 | AC88: =VLOOKUP(A88,'[3]Last Aum File'!$A$2:$B$126,2,0)/1000000 -> 0.016991 | AD88: =AB88-AC88 -> -0.000434
A89: CNPTHEMPROT | B89: Yes | C89: CNP THEMATIC PROTECTION 80 | D89: Model | E89: On Original Risk List | F89: From Risk - Fund Responsibility - Model Portfolios | G89: Outcome Oriented Strategies | H89: Capital Guaranteed | K89: AMUNDI.IRL/INV/MAS/PMG | L89: BUONO SALVATORE | M89: To be Affected | P89: =VLOOKUP(A89,[3]AUM!$A$3:$B$131,2,0) -> 195364106 | T89: =VLOOKUP(A89,[4]Flows!$A$3:$D$1206,4,0) -> -10521304 | U89: =VLOOKUP(A89,'[3]Last Aum File'!$A$2:$B$1262,2,0) -> 201751089 | V89: =+U89/1000000 -> 201.75109 | W89: =+IF(OR(A89="HF11",A89="PACIFAI"),0,IF(A89="MUSG",P89-U89/2,P89-U89)) -> -6386983 | X89: =+IF(ISNA(W89),0,W89) -> -6386983 | Y89: =P89/1000000 -> 195.36411 | Z89: =X89/1000000 -> -6.386983 | AA89: =T89/1000000 -> -10.521304 | AB89: =VLOOKUP(A89,[3]AUM!$A$3:$B$131,2,0)/1000000 -> 195.36411 | AC89: 0 | AD89: =AB89-AC89 -> 195.36411
A90: CRVTHEMPROT | B90: Yes | C90: CRV THEMATIC PROTECTION 80 | D90: Model | E90: On Original Risk List | F90: From Risk - Fund Responsibility - Model Portfolios | G90: Outcome Oriented Strategies | H90: Capital Guaranteed | K90: AMUNDI.IRL/INV/MAS/PMG | L90: BUONO SALVATORE | M90: To be Affected | P90: =VLOOKUP(A90,[3]AUM!$A$3:$B$131,2,0) -> 307505809 | T90: =VLOOKUP(A90,[4]Flows!$A$3:$D$1206,4,0) -> -11494401 | U90: =VLOOKUP(A90,'[3]Last Aum File'!$A$2:$B$1262,2,0) -> 312423908 | V90: =+U90/1000000 -> 312.42391 | W90: =+IF(OR(A90="HF11",A90="PACIFAI"),0,IF(A90="MUSG",P90-U90/2,P90-U90)) -> -4918099 | X90: =+IF(ISNA(W90),0,W90) -> -4918099 | Y90: =P90/1000000 -> 307.50581 | Z90: =X90/1000000 -> -4.918099 | AA90: =T90/1000000 -> -11.494401 | AB90: =VLOOKUP(A90,[3]AUM!$A$3:$B$131,2,0)/1000000 -> 307.50581 | AC90: 0 | AD90: =AB90-AC90 -> 307.50581
A91: CNPDYNPR80 | B91: Yes | C91: CNP Dynamic Protection 80 | D91: Model | E91: On Original Risk List | F91: =VLOOKUP(A91,'[1]Model portfolios'!$A$2:$L$142,2,FALSE) -> From Risk - Fund Responsibility - Model Portfolios | G91: =VLOOKUP($A91,'[2]Desk mapping'!$G:$L,5,FALSE) -> Outcome Oriented Strategies | H91: =VLOOKUP($A91,'[2]Desk mapping'!$G:$L,6,FALSE) -> Capital Guaranteed | K91: AMUNDI.IRL/INV/MAS/PMG | L91: BUONO SALVATORE | M91: To be Affected | O91: =VLOOKUP(A91,'Audit AUM File'!A:B,2,FALSE) -> 1.1116702e+08 | P91: =VLOOKUP(A91,[3]AUM!$A$3:$B$131,2,0) -> 116832547 | R91: =+IF(D91="",VLOOKUP(A91,'[2]Pivot for Jun AUM'!$A$5:$B$121,2,FALSE)) -> FALSE | T91: =VLOOKUP(A91,[4]Flows!$A$3:$D$1206,4,0) -> -16088829 | U91: =VLOOKUP(A91,'[3]Last Aum File'!$A$2:$B$1262,2,0) -> 132260888 | V91: =+U91/1000000 -> 132.26089 | W91: =+IF(OR(A91="HF11",A91="PACIFAI"),0,IF(A91="MUSG",P91-U91/2,P91-U91)) -> -15428341 | X91: =+IF(ISNA(W91),0,W91) -> -15428341 | Y91: =P91/1000000 -> 116.83255 | Z91: =X91/1000000 -> -15.428341 | AA91: =T91/1000000 -> -16.088829 | AB91: =VLOOKUP(A91,[3]AUM!$A$3:$B$131,2,0)/1000000 -> 116.83255 | AC91: =VLOOKUP(A91,'[3]Last Aum File'!$A$2:$B$126,2,0)/1000000 -> 132.26089 | AD91: =AB91-AC91 -> -15.428341
A92: CRVDYNPR80 | B92: Yes | C92: CRV Dynamic Protection 80 | D92: Model | E92: On Original Risk List | F92: =VLOOKUP(A92,'[1]Model portfolios'!$A$2:$L$142,2,FALSE) -> From Risk - Fund Responsibility - Model Portfolios | G92: =VLOOKUP($A92,'[2]Desk mapping'!$G:$L,5,FALSE) -> Outcome Oriented Strategies | H92: =VLOOKUP($A92,'[2]Desk mapping'!$G:$L,6,FALSE) -> Capital Guaranteed | K92: AMUNDI.IRL/INV/MAS/PMG | L92: BUONO SALVATORE | M92: To be Affected | O92: =VLOOKUP(A92,'Audit AUM File'!A:B,2,FALSE) -> 1.1073481e+08 | P92: =VLOOKUP(A92,[3]AUM!$A$3:$B$131,2,0) -> 279293562 | R92: =+IF(D92="",VLOOKUP(A92,'[2]Pivot for Jun AUM'!$A$5:$B$121,2,FALSE)) -> FALSE | T92: =VLOOKUP(A92,[4]Flows!$A$3:$D$1206,4,0) -> -25728394 | U92: =VLOOKUP(A92,'[3]Last Aum File'!$A$2:$B$1262,2,0) -> 303707882 | V92: =+U92/1000000 -> 303.70788 | W92: =+IF(OR(A92="HF11",A92="PACIFAI"),0,IF(A92="MUSG",P92-U92/2,P92-U92)) -> -24414320 | X92: =+IF(ISNA(W92),0,W92) -> -24414320 | Y92: =P92/1000000 -> 279.29356 | Z92: =X92/1000000 -> -24.41432 | AA92: =T92/1000000 -> -25.728394 | AB92: =VLOOKUP(A92,[3]AUM!$A$3:$B$131,2,0)/1000000 -> 279.29356 | AC92: =VLOOKUP(A92,'[3]Last Aum File'!$A$2:$B$126,2,0)/1000000 -> 303.70788 | AD92: =AB92-AC92 -> -24.41432
A93: CNPPROT80 | B93: Yes | C93: CNP Protection 80 | D93: Model | E93: On Original Risk List | F93: From Risk - Fund Responsibility - Model Portfolios | G93: Outcome Oriented Strategies | H93: Capital Guaranteed | K93: AMUNDI.IRL/INV/MAS/PMG | L93: BUONO SALVATORE | M93: To be Affected | P93: =VLOOKUP(A93,[3]AUM!$A$3:$B$131,2,0) -> 96897819 | R93: =+IF(D93="",VLOOKUP(A93,'[2]Pivot for Jun AUM'!$A$5:$B$121,2,FALSE)) -> FALSE | T93: =VLOOKUP(A93,[4]Flows!$A$3:$D$1206,4,0) -> 367906.54 | U93: =VLOOKUP(A93,'[3]Last Aum File'!$A$2:$B$1262,2,0) -> 92942418 | V93: =+U93/1000000 -> 92.942418 | W93: =+IF(OR(A93="HF11",A93="PACIFAI"),0,IF(A93="MUSG",P93-U93/2,P93-U93)) -> 3955401 | X93: =+IF(ISNA(W93),0,W93) -> 3955401 | Y93: =P93/1000000 -> 96.897819 | Z93: =X93/1000000 -> 3.955401 | AA93: =T93/1000000 -> 0.36790654 | AB93: =VLOOKUP(A93,[3]AUM!$A$3:$B$131,2,0)/1000000 -> 96.897819 | AC93: =VLOOKUP(A93,'[3]Last Aum File'!$A$2:$B$126,2,0)/1000000 -> 92.942418 | AD93: =AB93-AC93 -> 3.955401
A94: CRVPROT80 | B94: Yes | C94: CRV Protection 80 | D94: Model | E94: On Original Risk List | F94: From Risk - Fund Responsibility - Model Portfolios | G94: Outcome Oriented Strategies | H94: Capital Guaranteed | K94: AMUNDI.IRL/INV/MAS/PMG | L94: BUONO SALVATORE | M94: To be Affected | P94: =VLOOKUP(A94,[3]AUM!$A$3:$B$131,2,0) -> 106822030 | R94: =+IF(D94="",VLOOKUP(A94,'[2]Pivot for Jun AUM'!$A$5:$B$121,2,FALSE)) -> FALSE | T94: =VLOOKUP(A94,[4]Flows!$A$3:$D$1206,4,0) -> 1020637.6 | U94: =VLOOKUP(A94,'[3]Last Aum File'!$A$2:$B$1262,2,0) -> 101671056 | V94: =+U94/1000000 -> 101.67106 | W94: =+IF(OR(A94="HF11",A94="PACIFAI"),0,IF(A94="MUSG",P94-U94/2,P94-U94)) -> 5150974 | X94: =+IF(ISNA(W94),0,W94) -> 5150974 | Y94: =P94/1000000 -> 106.82203 | Z94: =X94/1000000 -> 5.150974 | AA94: =T94/1000000 -> 1.0206376 | AB94: =VLOOKUP(A94,[3]AUM!$A$3:$B$131,2,0)/1000000 -> 106.82203 | AC94: =VLOOKUP(A94,'[3]Last Aum File'!$A$2:$B$126,2,0)/1000000 -> 101.67106 | AD94: =AB94-AC94 -> 5.150974
A95: MLINC | B95: Yes | C95: UL Life Income | D95: Model | E95: On Original Risk List | F95: =VLOOKUP(A95,'[1]Model portfolios'!$A$2:$L$142,2,FALSE) -> From Risk - Fund Responsibility - Model Portfolios | G95: =VLOOKUP($A95,'[2]Desk mapping'!$G:$L,5,FALSE) -> Outcome Oriented Strategies | H95: =VLOOKUP($A95,'[2]Desk mapping'!$G:$L,6,FALSE) -> Income | K95: AMUNDI.IRL/INV/MAS/PMG | L95: BUONO SALVATORE | M95: To be Affected | O95: =VLOOKUP(A95,'Audit AUM File'!A:B,2,FALSE) -> 1.2342895e+08 | P95: =VLOOKUP(A95,[3]AUM!$A$3:$B$131,2,0) -> 215406941 | R95: =+IF(D95="",VLOOKUP(A95,'[2]Pivot for Jun AUM'!$A$5:$B$121,2,FALSE)) -> FALSE | T95: =VLOOKUP(A95,[4]Flows!$A$3:$D$1206,4,0) -> -15247023 | U95: =VLOOKUP(A95,'[3]Last Aum File'!$A$2:$B$1262,2,0) -> 230490457 | V95: =+U95/1000000 -> 230.49046 | W95: =+IF(OR(A95="HF11",A95="PACIFAI"),0,IF(A95="MUSG",P95-U95/2,P95-U95)) -> -15083516 | X95: =+IF(ISNA(W95),0,W95) -> -15083516 | Y95: =P95/1000000 -> 215.40694 | Z95: =X95/1000000 -> -15.083516 | AA95: =T95/1000000 -> -15.247023 | AB95: =VLOOKUP(A95,[3]AUM!$A$3:$B$131,2,0)/1000000 -> 215.40694 | AC95: =VLOOKUP(A95,'[3]Last Aum File'!$A$2:$B$126,2,0)/1000000 -> 230.49046 | AD95: =AB95-AC95 -> -15.083516
A96: MULLI360 | B96: Yes | C96: UL Life Income 360 | D96: Model | E96: On Original Risk List | F96: =VLOOKUP(A96,'[1]Model portfolios'!$A$2:$L$142,2,FALSE) -> From Risk - Fund Responsibility - Model Portfolios | G96: =VLOOKUP($A96,'[2]Desk mapping'!$G:$L,5,FALSE) -> Outcome Oriented Strategies | H96: =VLOOKUP($A96,'[2]Desk mapping'!$G:$L,6,FALSE) -> Income | K96: AMUNDI.IRL/INV/MAS/PMG | L96: BUONO SALVATORE | M96: To be Affected | O96: =VLOOKUP(A96,'Audit AUM File'!A:B,2,FALSE) -> 1.2117975e+08 | P96: =VLOOKUP(A96,[3]AUM!$A$3:$B$131,2,0) -> 154991340 | R96: =+IF(D96="",VLOOKUP(A96,'[2]Pivot for Jun AUM'!$A$5:$B$121,2,FALSE)) -> FALSE | T96: =VLOOKUP(A96,[4]Flows!$A$3:$D$1206,4,0) -> -14572498 | U96: =VLOOKUP(A96,'[3]Last Aum File'!$A$2:$B$1262,2,0) -> 170018725 | V96: =+U96/1000000 -> 170.01872 | W96: =+IF(OR(A96="HF11",A96="PACIFAI"),0,IF(A96="MUSG",P96-U96/2,P96-U96)) -> -15027385 | X96: =+IF(ISNA(W96),0,W96) -> -15027385 | Y96: =P96/1000000 -> 154.99134 | Z96: =X96/1000000 -> -15.027385 | AA96: =T96/1000000 -> -14.572498 | AB96: =VLOOKUP(A96,[3]AUM!$A$3:$B$131,2,0)/1000000 -> 154.99134 | AC96: =VLOOKUP(A96,'[3]Last Aum File'!$A$2:$B$126,2,0)/1000000 -> 170.01872 | AD96: =AB96-AC96 -> -15.027385
A97: ULACCO | B97: Yes | C97: Unit Linked Multi Equity Accumulation | D97: Model | E97: On Original Risk List | F97: =VLOOKUP(A97,'[1]Model portfolios'!$A$2:$L$142,2,FALSE) -> From Risk - Fund Responsibility - Model Portfolios | G97: =VLOOKUP($A97,'[2]Desk mapping'!$G:$L,5,FALSE) -> Outcome Oriented Strategies | H97: =VLOOKUP($A97,'[2]Desk mapping'!$G:$L,6,FALSE) -> Risk Accumulation | K97: AMUNDI.IRL/INV/MAS/PMG | L97: BUONO SALVATORE | M97: To be Affected | O97: =VLOOKUP(A97,'Audit AUM File'!A:B,2,FALSE) -> 1.188827e+08 | P97: =VLOOKUP(A97,[3]AUM!$A$3:$B$131,2,0) -> 4704953 | R97: =+IF(D97="",VLOOKUP(A97,'[2]Pivot for Jun AUM'!$A$5:$B$121,2,FALSE)) -> FALSE | T97: =VLOOKUP(A97,[4]Flows!$A$3:$D$1206,4,0) -> -340502.77 | U97: =VLOOKUP(A97,'[3]Last Aum File'!$A$2:$B$1262,2,0) -> 5173858 | V97: =+U97/1000000 -> 5.173858 | W97: =+IF(OR(A97="HF11",A97="PACIFAI"),0,IF(A97="MUSG",P97-U97/2,P97-U97)) -> -468905 | X97: =+IF(ISNA(W97),0,W97) -> -468905 | Y97: =P97/1000000 -> 4.704953 | Z97: =X97/1000000 -> -0.468905 | AA97: =T97/1000000 -> -0.34050277 | AB97: =VLOOKUP(A97,[3]AUM!$A$3:$B$131,2,0)/1000000 -> 4.704953 | AC97: =VLOOKUP(A97,'[3]Last Aum File'!$A$2:$B$126,2,0)/1000000 -> 5.173858 | AD97: =AB97-AC97 -> -0.468905
A98: MUSI | B98: Yes | C98: Univalore Stars Income | D98: Model | E98: On Original Risk List | F98: =VLOOKUP(A98,'[1]Model portfolios'!$A$2:$L$142,2,FALSE) -> From Risk - Fund Responsibility - Model Portfolios | G98: =VLOOKUP($A98,'[2]Desk mapping'!$G:$L,5,FALSE) -> Outcome Oriented Strategies | H98: =VLOOKUP($A98,'[2]Desk mapping'!$G:$L,6,FALSE) -> Income | K98: AMUNDI.IRL/INV/MAS/PMG | L98: BUONO SALVATORE | M98: To be Affected | O98: =VLOOKUP(A98,'Audit AUM File'!A:B,2,FALSE) -> 1.1905565e+08 | P98: =VLOOKUP(A98,[3]AUM!$A$3:$B$131,2,0) -> 239238036 | R98: =+IF(D98="",VLOOKUP(A98,'[2]Pivot for Jun AUM'!$A$5:$B$121,2,FALSE)) -> FALSE | T98: =VLOOKUP(A98,[4]Flows!$A$3:$D$1206,4,0) -> -24530124 | U98: =VLOOKUP(A98,'[3]Last Aum File'!$A$2:$B$1262,2,0) -> 263555955 | V98: =+U98/1000000 -> 263.55595 | W98: =+IF(OR(A98="HF11",A98="PACIFAI"),0,IF(A98="MUSG",P98-U98/2,P98-U98)) -> -24317919 | X98: =+IF(ISNA(W98),0,W98) -> -24317919 | Y98: =P98/1000000 -> 239.23804 | Z98: =X98/1000000 -> -24.317919 | AA98: =T98/1000000 -> -24.530124 | AB98: =VLOOKUP(A98,[3]AUM!$A$3:$B$131,2,0)/1000000 -> 239.23804 | AC98: =VLOOKUP(A98,'[3]Last Aum File'!$A$2:$B$126,2,0)/1000000 -> 263.55595 | AD98: =AB98-AC98 -> -24.317919
A99: PMAI | B99: Yes | C99: CAM Luglio | D99: Model | E99: On Original Risk List | F99: =VLOOKUP(A99,'[1]Model portfolios'!$A$2:$L$142,2,FALSE) -> From Risk - Fund Responsibility - Model Portfolios | G99: =VLOOKUP($A99,'[2]Total AUM Data'!$A:$I,5,FALSE) -> Outcome Oriented Strategies | H99: =VLOOKUP($A99,'[2]Total AUM Data'!$A:$I,6,FALSE) -> Capital Protection | K99: AMUNDI.IRL/INV/MAS/PMG | L99: BUONO SALVATORE | M99: To be Affected | O99: =VLOOKUP(A99,'Audit AUM File'!A:B,2,FALSE) -> 1.0844663e+08 | P99: =VLOOKUP(A99,[3]AUM!$A$3:$B$131,2,0) -> 77561 | R99: =+IF(D99="",VLOOKUP(A99,'[2]Pivot for Jun AUM'!$A$5:$B$121,2,FALSE)) -> FALSE | U99: =VLOOKUP(A99,'[3]Last Aum File'!$A$2:$B$1262,2,0) -> 78336 | V99: =+U99/1000000 -> 0.078336 | W99: =+IF(OR(A99="HF11",A99="PACIFAI"),0,IF(A99="MUSG",P99-U99/2,P99-U99)) -> -775 | X99: =+IF(ISNA(W99),0,W99) -> -775 | Y99: =P99/1000000 -> 0.077561 | Z99: =X99/1000000 -> -0.000775 | AA99: =T99/1000000 -> 0 | AB99: =VLOOKUP(A99,[3]AUM!$A$3:$B$131,2,0)/1000000 -> 0.077561 | AC99: =VLOOKUP(A99,'[3]Last Aum File'!$A$2:$B$126,2,0)/1000000 -> 0.078336 | AD99: =AB99-AC99 -> -0.000775
A100: ULBER- | B100: Yes | C100: UL_Bilanciata_+ERGO | D100: Model | E100: On Original Risk List | F100: =VLOOKUP(A100,'[1]Model portfolios'!$A$2:$L$142,2,FALSE) -> From Risk - Fund Responsibility - Model Portfolios | G100: =VLOOKUP($A100,'[2]Total AUM Data'!$A:$I,5,FALSE) -> Allocation Driven Strategies | H100: =VLOOKUP($A100,'[2]Total AUM Data'!$A:$I,6,FALSE) -> Moderate | K100: AMUNDI.IRL/INV/MAS/PMG | L100: BUONO SALVATORE | M100: To be Affected | O100: =VLOOKUP(A100,'Audit AUM File'!A:B,2,FALSE) -> 2.0770996e+08 | P100: 5017578 | R100: =+IF(D100="",VLOOKUP(A100,'[2]Pivot for Jun AUM'!$A$5:$B$121,2,FALSE)) -> FALSE | U100: 5017578 | V100: =+U100/1000000 -> 5.017578 | W100: =+IF(OR(A100="HF11",A100="PACIFAI"),0,IF(A100="MUSG",P100-U100/2,P100-U100)) -> 0 | X100: =+IF(ISNA(W100),0,W100) -> 0 | Y100: =P100/1000000 -> 5.017578 | Z100: =X100/1000000 -> 0 | AA100: =T100/1000000 -> 0 | AB100: =VLOOKUP(A100,[3]AUM!$A$3:$B$131,2,0)/1000000 -> 0 | AC100: =VLOOKUP(A100,'[3]Last Aum File'!$A$2:$B$126,2,0)/1000000 -> 0 | AD100: =AB100-AC100 -> 0
A101: ULDER | B101: Yes | C101: UL_Dinamica ERGO | D101: Model | E101: On Original Risk List | F101: =VLOOKUP(A101,'[1]Model portfolios'!$A$2:$L$142,2,FALSE) -> From Risk - Fund Responsibility - Model Portfolios | G101: =VLOOKUP($A101,'[2]Total AUM Data'!$A:$I,5,FALSE) -> Allocation Driven Strategies | H101: =VLOOKUP($A101,'[2]Total AUM Data'!$A:$I,6,FALSE) -> Growth | K101: AMUNDI.IRL/INV/MAS/PMG | L101: BUONO SALVATORE | M101: To be Affected | O101: =VLOOKUP(A101,'Audit AUM File'!A:B,2,FALSE) -> 2.5186321e+08 | P101: =VLOOKUP(A101,[3]AUM!$A$3:$B$131,2,0) -> 0 | R101: =+IF(D101="",VLOOKUP(A101,'[2]Pivot for Jun AUM'!$A$5:$B$121,2,FALSE)) -> FALSE | U101: =VLOOKUP(A101,'[3]Last Aum File'!$A$2:$B$1262,2,0) -> 0 | V101: =+U101/1000000 -> 0 | W101: =+IF(OR(A101="HF11",A101="PACIFAI"),0,IF(A101="MUSG",P101-U101/2,P101-U101)) -> 0 | X101: =+IF(ISNA(W101),0,W101) -> 0 | Y101: =P101/1000000 -> 0 | Z101: =X101/1000000 -> 0 | AA101: =T101/1000000 -> 0 | AB101: =VLOOKUP(A101,[3]AUM!$A$3:$B$131,2,0)/1000000 -> 0 | AC101: =VLOOKUP(A101,'[3]Last Aum File'!$A$2:$B$126,2,0)/1000000 -> 0 | AD101: =AB101-AC101 -> 0
A102: ULPER | B102: Yes | C102: UL_Prudente ERGO | D102: Model | E102: On Original Risk List | F102: =VLOOKUP(A102,'[1]Model portfolios'!$A$2:$L$142,2,FALSE) -> From Risk - Fund Responsibility - Model Portfolios | G102: =VLOOKUP($A102,'[2]Total AUM Data'!$A:$I,5,FALSE) -> Allocation Driven Strategies | H102: =VLOOKUP($A102,'[2]Total AUM Data'!$A:$I,6,FALSE) -> Conservative | K102: AMUNDI.IRL/INV/MAS/PMG | L102: BUONO SALVATORE | M102: To be Affected | O102: =VLOOKUP(A102,'Audit AUM File'!A:B,2,FALSE) -> 1.5720934e+08 | P102: =VLOOKUP(A102,[3]AUM!$A$3:$B$131,2,0) -> 0 | R102: =+IF(D102="",VLOOKUP(A102,'[2]Pivot for Jun AUM'!$A$5:$B$121,2,FALSE)) -> FALSE | U102: =VLOOKUP(A102,'[3]Last Aum File'!$A$2:$B$1262,2,0) -> 0 | V102: =+U102/1000000 -> 0 | W102: =+IF(OR(A102="HF11",A102="PACIFAI"),0,IF(A102="MUSG",P102-U102/2,P102-U102)) -> 0 | X102: =+IF(ISNA(W102),0,W102) -> 0 | Y102: =P102/1000000 -> 0 | Z102: =X102/1000000 -> 0 | AA102: =T102/1000000 -> 0 | AB102: =VLOOKUP(A102,[3]AUM!$A$3:$B$131,2,0)/1000000 -> 0 | AC102: =VLOOKUP(A102,'[3]Last Aum File'!$A$2:$B$126,2,0)/1000000 -> 0 | AD102: =AB102-AC102 -> 0
A103: ULP-ER | B103: Yes | C103: UL_Prudente_+ ERGO | D103: Model | E103: On Original Risk List | F103: =VLOOKUP(A103,'[1]Model portfolios'!$A$2:$L$142,2,FALSE) -> From Risk - Fund Responsibility - Model Portfolios | G103: =VLOOKUP($A103,'[2]Total AUM Data'!$A:$I,5,FALSE) -> Allocation Driven Strategies | H103: =VLOOKUP($A103,'[2]Total AUM Data'!$A:$I,6,FALSE) -> Conservative | K103: AMUNDI.IRL/INV/MAS/PMG | L103: BUONO SALVATORE | M103: To be Affected | O103: =VLOOKUP(A103,'Audit AUM File'!A:B,2,FALSE) -> 1.7619796e+08 | P103: =VLOOKUP(A103,[3]AUM!$A$3:$B$131,2,0) -> 0 | R103: =+IF(D103="",VLOOKUP(A103,'[2]Pivot for Jun AUM'!$A$5:$B$121,2,FALSE)) -> FALSE | U103: =VLOOKUP(A103,'[3]Last Aum File'!$A$2:$B$1262,2,0) -> 0 | V103: =+U103/1000000 -> 0 | W103: =+IF(OR(A103="HF11",A103="PACIFAI"),0,IF(A103="MUSG",P103-U103/2,P103-U103)) -> 0 | X103: =+IF(ISNA(W103),0,W103) -> 0 | Y103: =P103/1000000 -> 0 | Z103: =X103/1000000 -> 0 | AA103: =T103/1000000 -> 0 | AB103: =VLOOKUP(A103,[3]AUM!$A$3:$B$131,2,0)/1000000 -> 0
A104: R2M | B104: Yes | C104: =VLOOKUP(A104,'[1]Model portfolios'!$A:$AS,4,FALSE) -> CNP Linea Protetta Dinamica Plus | D104: Model | E104: Added by Ronan | F104: =VLOOKUP(A104,'[1]Model portfolios'!$A$2:$L$142,2,FALSE) -> From Risk - Fund Responsibility - Model Portfolios | G104: =VLOOKUP($A104,'[2]Desk mapping'!$G:$L,5,FALSE) -> Allocation Driven Strategies | H104: =VLOOKUP($A104,'[2]Desk mapping'!$G:$L,6,FALSE) -> Growth | P104: =VLOOKUP(A104,[3]AUM!$A$3:$B$131,2,0) -> 3991454 | R104: =+IF(D104="",VLOOKUP(A104,'[2]Pivot for Jun AUM'!$A$5:$B$121,2,FALSE)) -> FALSE | T104: =VLOOKUP(A104,[4]Flows!$A$3:$D$1206,4,0) -> -34928.27 | U104: =VLOOKUP(A104,'[3]Last Aum File'!$A$2:$B$1262,2,0) -> 3913810 | V104: =+U104/1000000 -> 3.91381 | W104: =+IF(OR(A104="HF11",A104="PACIFAI"),0,IF(A104="MUSG",P104-U104/2,P104-U104)) -> 77644 | X104: =+IF(ISNA(W104),0,W104) -> 77644 | Y104: =P104/1000000 -> 3.991454 | Z104: =X104/1000000 -> 0.077644 | AA104: =T104/1000000 -> -0.03492827 | AB104: =VLOOKUP(A104,[3]AUM!$A$3:$B$131,2,0)/1000000 -> 3.991454 | AC104: =VLOOKUP(A104,'[3]Last Aum File'!$A$2:$B$126,2,0)/1000000 -> 3.91381 | AD104: =AB104-AC104 -> 0.077644
A105: ULC | B105: Yes | C105: UL CAUTA | D105: Model | E105: On Original Risk List | F105: =VLOOKUP(A105,[5]Sheet1!$A:$N,2,FALSE) -> From Risk - Models master - Sheet 1 | G105: =VLOOKUP($A105,'[2]Desk mapping'!$G:$L,5,FALSE) -> Allocation Driven Strategies | H105: =VLOOKUP($A105,'[2]Desk mapping'!$G:$L,6,FALSE) -> Conservative | K105: AMUNDI.IRL/INV/MAS/PMG | L105: BUONO SALVATORE | M105: To be Affected | O105: =VLOOKUP(A105,'Audit AUM File'!A:B,2,FALSE) -> 1.3485478e+08 | P105: =VLOOKUP(A105,[3]AUM!$A$3:$B$131,2,0) -> 27311192 | R105: =+IF(D105="",VLOOKUP(A105,'[2]Pivot for Jun AUM'!$A$5:$B$121,2,FALSE)) -> FALSE | T105: =VLOOKUP(A105,[4]Flows!$A$3:$D$1206,4,0) -> -523806.45 | U105: =VLOOKUP(A105,'[3]Last Aum File'!$A$2:$B$1262,2,0) -> 27597514 | V105: =+U105/1000000 -> 27.597514 | W105: =+IF(OR(A105="HF11",A105="PACIFAI"),0,IF(A105="MUSG",P105-U105/2,P105-U105)) -> -286322 | X105: =+IF(ISNA(W105),0,W105) -> -286322 | Y105: =P105/1000000 -> 27.311192 | Z105: =X105/1000000 -> -0.286322 | AA105: =T105/1000000 -> -0.52380645 | AB105: =VLOOKUP(A105,[3]AUM!$A$3:$B$131,2,0)/1000000 -> 27.311192 | AC105: =VLOOKUP(A105,'[3]Last Aum File'!$A$2:$B$126,2,0)/1000000 -> 27.597514 | AD105: =AB105-AC105 -> -0.286322
A106: UNGOALS | B106: Yes | C106: Unit Linked UN GOALS | D106: Model | G106: Outcome Oriented Strategies | H106: Thematic | P106: =VLOOKUP(A106,[3]AUM!$A$3:$B$131,2,0) -> 909580051 | R106: =+IF(D106="",VLOOKUP(A106,'[2]Pivot for Jun AUM'!$A$5:$B$121,2,FALSE)) -> FALSE | T106: =VLOOKUP(A106,[4]Flows!$A$3:$D$1206,4,0) -> 8885720.7 | U106: =VLOOKUP(A106,'[3]Last Aum File'!$A$2:$B$1262,2,0) -> 869067080 | V106: =+U106/1000000 -> 869.06708 | W106: =+IF(OR(A106="HF11",A106="PACIFAI"),0,IF(A106="MUSG",P106-U106/2,P106-U106)) -> 40512971 | X106: =+IF(ISNA(W106),0,W106) -> 40512971 | Y106: =P106/1000000 -> 909.58005 | Z106: =X106/1000000 -> 40.512971 | AA106: =T106/1000000 -> 8.8857207 | AB106: =VLOOKUP(A106,[3]AUM!$A$3:$B$131,2,0)/1000000 -> 909.58005 | AC106: =VLOOKUP(A106,'[3]Last Aum File'!$A$2:$B$1206,2,0)/1000000 -> 869.06708 | AD106: =AB106-AC106 -> 40.512971
A107: ULMATREND | B107: Yes | C107: Unit Linked Multi Asset Trend | D107: Model | G107: Outcome Oriented Strategies | H107: Thematic | P107: =VLOOKUP(A107,[3]AUM!$A$3:$B$131,2,0) -> 252843377 | R107: =+IF(D107="",VLOOKUP(A107,'[2]Pivot for Jun AUM'!$A$5:$B$121,2,FALSE)) -> FALSE | T107: =VLOOKUP(A107,[4]Flows!$A$3:$D$1206,4,0) -> 6517412.1 | U107: =VLOOKUP(A107,'[3]Last Aum File'!$A$2:$B$1262,2,0) -> 239873847 | V107: =+U107/1000000 -> 239.87385 | W107: =+IF(OR(A107="HF11",A107="PACIFAI"),0,IF(A107="MUSG",P107-U107/2,P107-U107)) -> 12969530 | X107: =+IF(ISNA(W107),0,W107) -> 12969530 | Y107: =P107/1000000 -> 252.84338 | Z107: =X107/1000000 -> 12.96953 | AA107: =T107/1000000 -> 6.5174121 | AB107: =VLOOKUP(A107,[3]AUM!$A$3:$B$131,2,0)/1000000 -> 252.84338 | AC107: =VLOOKUP(A107,'[3]Last Aum File'!$A$2:$B$126,2,0)/1000000 -> 239.87385 | AD107: =AB107-AC107 -> 12.96953
A108: ULFTREND | B108: Yes | C108: Unit Linked Future Trend | D108: Model | G108: Outcome Oriented Strategies | H108: Thematic | P108: =IFERROR(VLOOKUP(A108,[3]AUM!$A$3:$B$131,2,0), "") | R108: =+IF(D108="",VLOOKUP(A108,'[2]Pivot for Jun AUM'!$A$5:$B$121,2,FALSE)) -> FALSE | T108: =VLOOKUP(A108,[4]Flows!$A$3:$D$1206,4,0) -> 226891.29 | U108: =IFERROR(VLOOKUP(A108,'[3]Last Aum File'!$A$2:$B$1262,2,0),"") | V108: =IFERROR(+U108/1000000,"") | W108: =IFERROR(+IF(OR(A108="HF11",A108="PACIFAI"),0,IF(A108="MUSG",P108-U108/2,P108-U108)),"") | X108: =+IF(ISNA(W108),0,W108) | Y108: =IFERROR(P108/1000000, "") | Z108: =IFERROR(X108/1000000, "") | AA108: =IFERROR(T108/1000000, "") -> 0.22689129 | AC108: =IFERROR(VLOOKUP(A108,'[3]Last Aum File'!$A$2:$B$126,2,0)/1000000, "") | AD108: =IFERROR(AB108-AC108, "")
A109: Multhem | B109: Yes | C109: Unit Linked Multi Thematic Global Eq | D109: Model | E109: On Original Risk List | F109: =VLOOKUP(A109,[5]Sheet1!$A:$N,2,FALSE) -> From Risk - Models master - Sheet 1 | G109: =VLOOKUP($A109,'[2]Desk mapping'!$G:$L,5,FALSE) -> Outcome Oriented Strategies | H109: =VLOOKUP($A109,'[2]Desk mapping'!$G:$L,6,FALSE) -> Thematic | R109: =+IF(D109="",VLOOKUP(A109,'[2]Pivot for Jun AUM'!$A$5:$B$121,2,FALSE)) -> FALSE | V109: =+U109/1000000 -> 0 | W109: =+IF(OR(A109="HF11",A109="PACIFAI"),0,IF(A109="MUSG",P109-U109/2,P109-U109)) -> 0 | X109: =+IF(ISNA(W109),0,W109) -> 0 | Y109: =P109/1000000 -> 0 | Z109: =X109/1000000 -> 0 | AA109: =T109/1000000 -> 0 | AB109: =VLOOKUP(A109,[3]AUM!$A$3:$B$131,2,0)/1000000 -> 1795.6708 | AC109: =VLOOKUP(A109,'[3]Last Aum File'!$A$2:$B$126,2,0)/1000000 -> 1777.2551 | AD109: =AB109-AC109 -> 18.415729
A110: AAPROT80 | B110: Yes | C110: =VLOOKUP($A110,'[2]Desk mapping'!$G:$L,3,FALSE) -> ASSET ALLOCATION MODEL PROTETTO 80 | D110: Model | E110: Added by Ronan | F110: =VLOOKUP($A110,'[2]Desk mapping'!$G:$J,2,FALSE) -> Models AUM - Desk Mapping | G110: =VLOOKUP($A110,'[2]Desk mapping'!$G:$L,5,FALSE) -> Outcome Oriented Strategies | H110: =VLOOKUP($A110,'[2]Desk mapping'!$G:$L,6,FALSE) -> Capital Guaranteed | P110: =VLOOKUP(A110,[3]AUM!$A$3:$B$131,2,0) -> 105977735 | R110: =+IF(D110="",VLOOKUP(A110,'[2]Pivot for Jun AUM'!$A$5:$B$121,2,FALSE)) -> FALSE | T110: =VLOOKUP(A110,[4]Flows!$A$3:$D$1206,4,0) -> -3090101.7 | U110: =VLOOKUP(A110,'[3]Last Aum File'!$A$2:$B$1262,2,0) -> 108101631 | V110: =+U110/1000000 -> 108.10163 | W110: =+IF(OR(A110="HF11",A110="PACIFAI"),0,IF(A110="MUSG",P110-U110/2,P110-U110)) -> -2123896 | X110: =+IF(ISNA(W110),0,W110) -> -2123896 | Y110: =P110/1000000 -> 105.97773 | Z110: =X110/1000000 -> -2.123896 | AA110: =T110/1000000 -> -3.0901017 | AB110: =VLOOKUP(A110,[3]AUM!$A$3:$B$131,2,0)/1000000 -> 105.97773 | AC110: =VLOOKUP(A110,'[3]Last Aum File'!$A$2:$B$126,2,0)/1000000 -> 108.10163 | AD110: =AB110-AC110 -> -2.123896
A111: MULSTEP | B111: Yes | C111: STEP CRESCITA | D111: Model | E111: On Original Risk List | F111: Not on another list - but included verbally by Salva | G111: =VLOOKUP($A111,'[2]Desk mapping'!$G:$L,5,FALSE) -> Outcome Oriented Strategies | H111: =VLOOKUP($A111,'[2]Desk mapping'!$G:$L,6,FALSE) -> Risk Accumulation | K111: AMUNDI.IRL/INV/MAS/PMG | L111: BUONO SALVATORE | M111: To be Affected | O111: =VLOOKUP(A111,'Audit AUM File'!A:B,2,FALSE) -> 99030590 | R111: =+IF(D111="",VLOOKUP(A111,'[2]Pivot for Jun AUM'!$A$5:$B$121,2,FALSE)) -> FALSE | T111: =VLOOKUP(A111,[4]Flows!$A$3:$D$1206,4,0) -> -334707.83 | V111: =+U111/1000000 -> 0 | W111: =+IF(OR(A111="HF11",A111="PACIFAI"),0,IF(A111="MUSG",P111-U111/2,P111-U111)) -> 0 | X111: =+IF(ISNA(W111),0,W111) -> 0 | Y111: =P111/1000000 -> 0 | Z111: =X111/1000000 -> 0 | AA111: =T111/1000000 -> -0.33470783 | AB111: =VLOOKUP(A111,[3]AUM!$A$3:$B$131,2,0)/1000000 -> 8.2037 | AC111: =VLOOKUP(A111,'[3]Last Aum File'!$A$2:$B$126,2,0)/1000000 -> 8.373945 | AD111: =AB111-AC111 -> -0.170245
A112: DIOP3 | B112: Yes | C112: DISCRETIONARY INCOME ORIENTED PRODUCTS 3 | D112: Model | E112: On Original Risk List | F112: Not on another list - but included verbally by Salva | G112: Outcome Oriented Strategies | H112: Income | K112: AMUNDI.IRL/INV/MAS/PMG | L112: NICHOLAS POTHIER | M112: To be Affected | O112: =VLOOKUP(A112,'Audit AUM File'!A:B,2,FALSE) -> 1.022207e+08 | P112: 5231379.8 | R112: =+IF(D112="",VLOOKUP(A112,'[2]Pivot for Jun AUM'!$A$5:$B$121,2,FALSE)) -> FALSE | U112: 6968432.6 | V112: =+U112/1000000 -> 6.9684326 | W112: =+IF(OR(A112="HF11",A112="PACIFAI"),0,IF(A112="MUSG",P112-U112/2,P112-U112)) -> -1737052.8 | X112: =+IF(ISNA(W112),0,W112) -> -1737052.8 | Y112: =P112/1000000 -> 5.2313798 | Z112: =X112/1000000 -> -1.7370528 | AA112: =T112/1000000 -> 0 | AD112: =AB112-AC112 -> 0
A113: DIOP4 | B113: Yes | C113: DISCRETIONARY INCOME ORIENTED PRODUCTS 4 | D113: Model | E113: On Original Risk List | F113: Not on another list - but included verbally by Salva | G113: Outcome Oriented Strategies | H113: Thematic | K113: AMUNDI.IRL/INV/MAS/PMG | L113: NICHOLAS POTHIER | M113: To be Affected | O113: =VLOOKUP(A113,'Audit AUM File'!A:B,2,FALSE) -> 1.0284058e+08 | P113: 9542350.5 | R113: =+IF(D113="",VLOOKUP(A113,'[2]Pivot for Jun AUM'!$A$5:$B$121,2,FALSE)) -> FALSE | U113: 14185291 | V113: =+U113/1000000 -> 14.185291 | W113: =+IF(OR(A113="HF11",A113="PACIFAI"),0,IF(A113="MUSG",P113-U113/2,P113-U113)) -> -4642940.7 | X113: =+IF(ISNA(W113),0,W113) -> -4642940.7 | Y113: =P113/1000000 -> 9.5423505 | Z113: =X113/1000000 -> -4.6429407 | AA113: =T113/1000000 -> 0 | AD113: =AB113-AC113 -> 0
A114: BBSECCORE | B114: Yes | C114: BB SECURITIES EURO GOVT CORE | E114: On Original Risk List | F114: Not on another list - but included verbally by Salva | K114: AMUNDI.IRL/INV/MAS/PMG/PMG | L114: CASEY RICHARD | M114: To be Affected | O114: =VLOOKUP(A114,'Audit AUM File'!A:B,2,FALSE) -> 1.0268436e+08 | P114: =VLOOKUP(A114,[6]Sheet1!$A:$H,3,FALSE) -> 0 | R114: =+IF(D114="",VLOOKUP(A114,'[2]Pivot for Jun AUM'!$A$5:$B$121,2,FALSE)) -> #N/A | U114: 0 | V114: =+U114/1000000 -> 0 | W114: =+IF(OR(A114="HF11",A114="PACIFAI"),0,IF(A114="MUSG",P114-U114/2,P114-U114)) -> 0 | X114: =+IF(ISNA(W114),0,W114) -> 0 | Y114: =P114/1000000 -> 0 | Z114: =X114/1000000 -> 0 | AA114: =T114/1000000 -> 0 | AD114: =AB114-AC114 -> 0
A115: BBSECPERIPH | B115: Yes | C115: BB SECURITIES EURO GOVT PERIPHERAL | E115: On Original Risk List | F115: Not on another list - but included verbally by Salva | K115: AMUNDI.IRL/INV/MAS/PMG/PMG | L115: CASEY RICHARD | M115: To be Affected | O115: =VLOOKUP(A115,'Audit AUM File'!A:B,2,FALSE) -> 1.0507304e+08 | P115: =VLOOKUP(A115,[6]Sheet1!$A:$H,3,FALSE) -> 0 | R115: =+IF(D115="",VLOOKUP(A115,'[2]Pivot for Jun AUM'!$A$5:$B$121,2,FALSE)) -> #N/A | U115: 0 | V115: =+U115/1000000 -> 0 | W115: =+IF(OR(A115="HF11",A115="PACIFAI"),0,IF(A115="MUSG",P115-U115/2,P115-U115)) -> 0 | X115: =+IF(ISNA(W115),0,W115) -> 0 | Y115: =P115/1000000 -> 0 | Z115: =X115/1000000 -> 0 | AA115: =T115/1000000 -> 0 | AD115: =AB115-AC115 -> 0
A116: BBSECEURIG | B116: Yes | C116: BB SECURITIES EURO IG CREDIT | E116: On Original Risk List | F116: Not on another list - but included verbally by Salva | K116: AMUNDI.IRL/INV/MAS/PMG/PMG | L116: CASEY RICHARD | M116: To be Affected | O116: =VLOOKUP(A116,'Audit AUM File'!A:B,2,FALSE) -> 1.0295089e+08 | P116: =VLOOKUP(A116,[6]Sheet1!$A:$H,3,FALSE) -> 0 | R116: =+IF(D116="",VLOOKUP(A116,'[2]Pivot for Jun AUM'!$A$5:$B$121,2,FALSE)) -> #N/A | U116: 0 | V116: =+U116/1000000 -> 0 | W116: =+IF(OR(A116="HF11",A116="PACIFAI"),0,IF(A116="MUSG",P116-U116/2,P116-U116)) -> 0 | X116: =+IF(ISNA(W116),0,W116) -> 0 | Y116: =P116/1000000 -> 0 | Z116: =X116/1000000 -> 0 | AA116: =T116/1000000 -> 0 | AD116: =AB116-AC116 -> 0
A117: BBSECUSTBOND | B117: Yes | C117: BB SECURITIES US TREASURY BOND | E117: On Original Risk List | F117: Not on another list - but included verbally by Salva | K117: AMUNDI.IRL/INV/MAS/PMG/PMG | L117: CASEY RICHARD | M117: To be Affected | O117: =VLOOKUP(A117,'Audit AUM File'!A:B,2,FALSE) -> 1.039165e+08 | P117: =VLOOKUP(A117,[6]Sheet1!$A:$H,3,FALSE) -> 0 | R117: =+IF(D117="",VLOOKUP(A117,'[2]Pivot for Jun AUM'!$A$5:$B$121,2,FALSE)) -> #N/A | U117: 0 | V117: =+U117/1000000 -> 0 | W117: =+IF(OR(A117="HF11",A117="PACIFAI"),0,IF(A117="MUSG",P117-U117/2,P117-U117)) -> 0 | X117: =+IF(ISNA(W117),0,W117) -> 0 | Y117: =P117/1000000 -> 0 | Z117: =X117/1000000 -> 0 | AA117: =T117/1000000 -> 0 | AD117: =AB117-AC117 -> 0
...

Sheet List Sheet
A3: Row Labels | B3: Count of Lead PM | C3: Count of Backup PM
A4: Fund | B4: 31 | C4: 29
A5: E118 | B5: 1 | C5: 1
A6: E119 | B6: 1 | C6: 1
A7: E120 | B7: 1 | C7: 1
A8: E142 | B8: 1 | C8: 1
A9: E143 | B9: 1 | C9: 1
A10: E144 | B10: 1 | C10: 1
A11: E193 | B11: 1 | C11: 1
A12: E207 | B12: 1
A13: E208 | B13: 1
A14: E209 | B14: 1 | C14: 1
A15: E224 | B15: 1 | C15: 1
A16: F100123 | B16: 1 | C16: 1
A17: PF101372 | B17: 1 | C17: 1
A18: PF101376 | B18: 1 | C18: 1
A19: PF101380 | B19: 1 | C19: 1
A20: PF103025 | B20: 1 | C20: 1
A21: PF52231 | B21: 1 | C21: 1
A22: PF71664 | B22: 1 | C22: 1
A23: PF76580 | B23: 1 | C23: 1
A24: PF78195 | B24: 1 | C24: 1
A25: PF79139 | B25: 1 | C25: 1
... A36: Model | B36: 83 | C36: 39
A37: 1PM | B37: 1
A38: 1QM | B38: 1
A39: 1RM | B39: 1
A40: AAPROT80 | B40: 1 | C40: 1
A41: BBSECCORE | B41: 1 | C41: 1
A42: BBSECEURIG | B42: 1 | C42: 1
A43: BBSECPERIPH | B43: 1 | C43: 1
A44: BBSECUSTBOND | B44: 1 | C44: 1
A45: CCRESCITA | B45: 1
A46: CMEDIUM | B46: 1
A47: CNPDYNPR80 | B47: 1 | C47: 1
A48: CNPPROT80 | B48: 1 | C48: 1
A49: CNPTHEMPROT | B49: 1 | C49: 1
A50: COBBLEURO | B50: 1
A51: CREDDITO | B51: 1
A52: CRVDYNPR80 | B52: 1 | C52: 1
A53: CRVPROT80 | B53: 1 | C53: 1
A54: CRVTHEMPROT | B54: 1 | C54: 1
A55: CSVILUPPO | B55: 1
A56: CTREND_20 | B56: 1
A57: DINAR1TF | B57: 1
A58: DINAR2TF | B58: 1
A59: DINAR3TF | B59: 1
A60: DIOP 1 | B60: 1 | C60: 1
A61: DIOP 2 | B61: 1 | C61: 1
A62: DIOP3 | B62: 1 | C62: 1
A63: DIOP4 | B63: 1 | C63: 1
A64: MAA | B64: 1 | C64: 1
A65: MAB | B65: 1 | C65: 1
A66: MAC | B66: 1 | C66: 1
A67: MAD | B67: 1 | C67: 1
A68: MAE | B68: 1 | C68: 1
A69: MAF | B69: 1 | C69: 1
A70: MAG | B70: 1 | C70: 1
A71: MAH | B71: 1 | C71: 1
... A74: MAN | B74: 1 | C74: 1
A75: MATRUNIP | B75: 1
A76: MEPF10 | B76: 1
A77: MEPF2N | B77: 1
A78: MEPF4 | B78: 1
A79: MEPF5 | B79: 1
A80: MEPF6 | B80: 1
A81: MEPF8 | B81: 1
A82: MLIFEBND | B82: 1
A83: MLINC | B83: 1 | C83: 1
A84: MLPFLEX | B84: 1
A85: MULLI360 | B85: 1 | C85: 1
A86: MULSTEP | B86: 1
A87: Multhem | B87: 1
A88: MUNIP | B88: 1
A89: MUSG | B89: 1 | C89: 1
A90: MUSI | B90: 1 | C90: 1
A91: PLIC | B91: 1
A92: PMAI | B92: 1
A93: PP1-3Y | B93: 1
A94: PP3Y | B94: 1 | C94: 1
A95: R1M | B95: 1
A96: R2M | B96: 1
A97: SAXO | B97: 1 | C97: 1
A98: STEPONE | B98: 1
A99: UES20 | B99: 1 | C99: 1
A100: UES30 | B100: 1 | C100: 1
A101: UES40 | B101: 1 | C101: 1
A102: UES50 | B102: 1 | C102: 1
A103: UES70 | B103: 1 | C103: 1
A104: ULACCO | B104: 1
A105: ULBER- | B105: 1
A106: ULBIL | B106: 1
A107: ULBILPIU | B107: 1
A108: ULC | B108: 1
A109: ULDER | B109: 1
A110: ULDIN | B110: 1
A111: ULECSTARS | B111: 1 | C111: 1
A112: ULFTREND | B112: 1
A113: ULG4NEW | B113: 1
A114: ULMATREND | B114: 1
...

Sheet Sheet3
A3: Count of Code | B3: Column Labels
A4: Row Labels | B4: Fund | C4: Model | D4: Grand Total
A5: Bond | B5: 1 | D5: 1
A6: PI INVESTMENT FUNDS - TACTICAL ALLOCATION BOND FUND - H | B6: 1 | D6: 1
A7: Capital Guaranteed | C7: 7 | D7: 7
A8: ASSET ALLOCATION MODEL PROTETTO 80 | C8: 1 | D8: 1
A9: CNP Dynamic Protection 80 | C9: 1 | D9: 1
A10: CNP Protection 80 | C10: 1 | D10: 1
A11: CNP THEMATIC PROTECTION 80 | C11: 1 | D11: 1
A12: CRV Dynamic Protection 80 | C12: 1 | D12: 1
A13: CRV Protection 80 | C13: 1 | D13: 1
A14: CRV THEMATIC PROTECTION 80 | C14: 1 | D14: 1
A15: Capital Protection | C15: 12 | D15: 12
A16: CAM Agosto | C16: 1 | D16: 1
A17: CAM Aprile | C17: 1 | D17: 1
A18: CAM Dicembre | C18: 1 | D18: 1
... A27: CAM Settembre | C27: 1 | D27: 1
A28: Conservative | B28: 4 | C28: 17 | D28: 21
A29: AFS ICAV Planet ESG Conservative | B29: 1 | D29: 1
A30: AMUNDI FUND SOLUTIONS - CONSERVATIVE | B30: 1 | D30: 1
A31: AMUNDI FUND SOLUTIONS - SABADELL URQUIJO ACUMULACION | B31: 1 | D31: 1
A32: AMUNDI UNICREDIT PREM PORT- PRUDENTIAL | B32: 1 | D32: 1
A33: CAM ARES RISPARMIO OBBLIGAZ. M | C33: 1 | D33: 1
A34: CAM OBBLIGAZIONARIA EURO | C34: 1 | D34: 1
A35: CAM REDDITO | C35: 1 | D35: 1
A36: CAM STEP ONE | C36: 1 | D36: 1
A37: CAM TREND 20 | C37: 1 | D37: 1
A38: Life Program Bond | C38: 1 | D38: 1
A39: PL Euro Bond 1 to 3 years | C39: 1 | D39: 1
A40: PL Euro Bond over 3 years | C40: 1 | D40: 1
A41: SAXO EUROPE | C41: 1 | D41: 1
A42: UL CAUTA | C42: 1 | D42: 1
A43: UL PRUDENTE | C43: 1 | D43: 1
A44: UL PRUDENTE PIU | C44: 1 | D44: 1
... A49: Unit Linked OLD 4 | C49: 1 | D49: 1
A50: Equity | B50: 2 | C50: 1 | D50: 3
A51: Amundi Env and Climate Change Sol Fund | B51: 1 | D51: 1
A52: PI INVESTMENT FUNDS - TACTICAL ALLOCATION FUND - H | B52: 1 | D52: 1
A53: UL Global Equity Dividend & Subordinated | C53: 1 | D53: 1
A54: Fixed Income | C54: 4 | D54: 4
A55: BB SECURITIES EURO GOVT CORE | C55: 1 | D55: 1
A56: BB SECURITIES EURO GOVT PERIPHERAL | C56: 1 | D56: 1
A57: BB SECURITIES EURO IG CREDIT | C57: 1 | D57: 1
A58: BB SECURITIES US TREASURY BOND | C58: 1 | D58: 1
A59: Flexible | B59: 2 | C59: 8 | D59: 10
A60: Amundi Invensys Broad Bond Portfolio | B60: 1 | D60: 1
A61: Life Program Flessibile | C61: 1 | D61: 1
A62: PI INVESTMENT FUNDS - DYNAMIC ALLOCATION FUND - E | B62: 1 | D62: 1
A63: PL Income Clock | C63: 1 | D63: 1
A64: Unit Linked A TR UNIPLAN | C64: 1 | D64: 1
A65: Univalore E Strategia 20 | C65: 1 | D65: 1
A66: Univalore E Strategia 30 | C66: 1 | D66: 1
A67: Univalore E Strategia 40 | C67: 1 | D67: 1
A68: Univalore E Strategia 70 | C68: 1 | D68: 1
A69: Univalore Stars Balanced | C69: 1 | D69: 1
A70: Growth | B70: 4 | C70: 10 | D70: 14
A71: AFS ICAV Planet ESG Dynamic | B71: 1 | D71: 1
A72: AMUNDI FUND SOLUTIONS - DIVERSIFIED GROWTH - A | B72: 1 | D72: 1
A73: AMUNDI FUND SOLUTIONS - SABADELL URQUIJO CRECIMIENTO | B73: 1 | D73: 1
A74: AMUNDI UNICREDIT PREMIUM PORT - DYNAMIC | B74: 1 | D74: 1
A75: CAM ARES RISPARMIO ATTIVO M | C75: 1 | D75: 1
A76: CAM CNP - LINEA DINAMICA | C76: 1 | D76: 1
A77: CAM CRESCITA | C77: 1 | D77: 1
A78: CAM SVILUPPO | C78: 1 | D78: 1
A79: CNP Linea Protetta Dinamica Plus | C79: 1 | D79: 1
A80: UL DINAMICA | C80: 1 | D80: 1
A81: UL_Dinamica ERGO | C81: 1 | D81: 1
A82: UNIT LINKED E6 NEW | C82: 1 | D82: 1
A83: UNIT LINKED G4 NEW | C83: 1 | D83: 1
A84: UNIT LINKED G5 NEW | C84: 1 | D84: 1
A85: Income | B85: 2 | C85: 6 | D85: 8
A86: Amundi Fund Solutions - Diversified Income Best Select 2022 | B86: 1 | D86: 1
A87: DISCRETIONARY INCOME ORIENTED PRODUCTS 1 | C87: 1 | D87: 1
A88: DISCRETIONARY INCOME ORIENTED PRODUCTS 2 | C88: 1 | D88: 1
A89: DISCRETIONARY INCOME ORIENTED PRODUCTS 3 | C89: 1 | D89: 1
A90: PI INVESTMENT FUNDS - TACTICAL ALLOCATION PILLAR - E | B90: 1 | D90: 1
A91: UL Life Income | C91: 1 | D91: 1
A92: UL Life Income 360 | C92: 1 | D92: 1
A93: Univalore Stars Income | C93: 1 | D93: 1
A94: Moderate | B94: 3 | C94: 10 | D94: 13
A95: AFS ICAV Planet ESG Balanced | B95: 1 | D95: 1
A96: AMUNDI FUND SOLUTIONS - BALANCED | B96: 1 | D96: 1
A97: AMUNDI UNICREDIT PREM PORT- MULTI ASSET | B97: 1 | D97: 1
A98: CAM ARES RISPARMIO BILANCIATO M | C98: 1 | D98: 1
A99: CAM MEDIUM | C99: 1 | D99: 1
A100: UL BILANCIATA | C100: 1 | D100: 1
A101: UL BILANCIATA PIU | C101: 1 | D101: 1
A102: UL_Bilanciata_+ERGO | C102: 1 | D102: 1
A103: UNIFLEX ACTIVE 1 | C103: 1 | D103: 1
A104: UNIFLEX ACTIVE 2 | C104: 1 | D104: 1
A105: UNIFLEX ACTIVE 3 | C105: 1 | D105: 1
A106: Unit Linked AMix UNIPLAN | C106: 1 | D106: 1
A107: UNIT LINKED E4 NEW | C107: 1 | D107: 1
A108: Risk Accumulation | B108: 12 | C108: 2 | D108: 14
A109: AMUNDI SENTIERO SOSTENIBILE | B109: 1 | D109: 1
A110: AMUNDI SOLUZIONI ITALIA - PROGETTO AZIONE CAMBIAMENTO CLIMATICO - E | B110: 1 | D110: 1
A111: AMUNDI SOLUZIONI ITALIA - PROGETTO AZIONE CAMBIAMENTO CLIMATICO (II) - E | B111: 1 | D111: 1
A112: AMUNDI SOLUZIONI ITALIA - PROGETTO AZIONE INFRASTRUTTURE SOSTENIBILI | B112: 1 | D112: 1
A113: AMUNDI SOLUZIONI ITALIA - PROGETTO AZIONE INFRASTRUTTURE SOSTENIBILI (II) | B113: 1 | D113: 1
A114: AMUNDI SOLUZIONI ITALIA - PROGETTO AZIONE MEGATREND - E | B114: 1 | D114: 1
...

Sheet List of Portfolios and AUM
A1: Code | B1: Portfolios name | C1: Fund or Model | D1: Strategy Type | E1: Strategy Detail | F1: Lead PM | G1: Backup PM | H1: AUM 31st Jan 2024
A2: 1PM | B2: CAM ARES RISPARMIO ATTIVO M | C2: Model | D2: =VLOOKUP($A2,'[2]Desk mapping'!$G:$L,5,FALSE) -> Allocation Driven Strategies | E2: =VLOOKUP($A2,'[2]Desk mapping'!$G:$L,6,FALSE) -> Growth | F2: Craig | H2: =VLOOKUP(A2,[3]AUM!$A$1:$B$131,2,0) -> 286172410
A3: 1QM | B3: CAM ARES RISPARMIO BILANCIATO M | C3: Model | D3: =VLOOKUP($A3,'[2]Desk mapping'!$G:$L,5,FALSE) -> Allocation Driven Strategies | E3: =VLOOKUP($A3,'[2]Desk mapping'!$G:$L,6,FALSE) -> Moderate | F3: Craig | H3: =VLOOKUP(A3,[3]AUM!$A$3:$B$131,2,0) -> 44621309
A4: 1RM | B4: CAM ARES RISPARMIO OBBLIGAZ. M | C4: Model | D4: =VLOOKUP($A4,'[2]Desk mapping'!$G:$L,5,FALSE) -> Allocation Driven Strategies | E4: =VLOOKUP($A4,'[2]Desk mapping'!$G:$L,6,FALSE) -> Conservative | F4: Craig | H4: =VLOOKUP(A4,[3]AUM!$A$3:$B$131,2,0) -> 29605967
A5: AAPROT80 | B5: =VLOOKUP($A5,'[2]Desk mapping'!$G:$L,3,FALSE) -> ASSET ALLOCATION MODEL PROTETTO 80 | C5: Model | D5: =VLOOKUP($A5,'[2]Desk mapping'!$G:$L,5,FALSE) -> Outcome Oriented Strategies | E5: =VLOOKUP($A5,'[2]Desk mapping'!$G:$L,6,FALSE) -> Capital Guaranteed | F5: Jen | G5: Craig | H5: =VLOOKUP(A5,[3]AUM!$A$3:$B$131,2,0) -> 105977735
A6: BBSECCORE | B6: BB SECURITIES EURO GOVT CORE | C6: Model | D6: Building Block | E6: Fixed Income | F6: Richard | G6: Alan | H6: =VLOOKUP(A6,[6]Sheet1!$A:$H,3,FALSE) -> 0
A7: BBSECEURIG | B7: BB SECURITIES EURO IG CREDIT | C7: Model | D7: Building Block | E7: Fixed Income | F7: Richard | G7: Alan | H7: =VLOOKUP(A7,[6]Sheet1!$A:$H,3,FALSE) -> 0
A8: BBSECPERIPH | B8: BB SECURITIES EURO GOVT PERIPHERAL | C8: Model | D8: Building Block | E8: Fixed Income | F8: Richard | G8: Alan | H8: =VLOOKUP(A8,[6]Sheet1!$A:$H,3,FALSE) -> 0
A9: BBSECUSTBOND | B9: BB SECURITIES US TREASURY BOND | C9: Model | D9: Building Block | E9: Fixed Income | F9: Richard | G9: Alan | H9: =VLOOKUP(A9,[6]Sheet1!$A:$H,3,FALSE) -> 0
A10: CCRESCITA | B10: CAM CRESCITA | C10: Model | D10: =VLOOKUP($A10,'[2]Desk mapping'!$G:$L,5,FALSE) -> Allocation Driven Strategies | E10: =VLOOKUP($A10,'[2]Desk mapping'!$G:$L,6,FALSE) -> Growth | F10: Craig | H10: =VLOOKUP(A10,[3]AUM!$A$3:$B$131,2,0) -> 1259071
A11: CMEDIUM | B11: CAM MEDIUM | C11: Model | D11: =VLOOKUP($A11,'[2]Desk mapping'!$G:$L,5,FALSE) -> Allocation Driven Strategies | E11: =VLOOKUP($A11,'[2]Desk mapping'!$G:$L,6,FALSE) -> Moderate | F11: Craig | H11: =VLOOKUP(A11,[3]AUM!$A$3:$B$131,2,0) -> 221348
A12: CNPDYNPR80 | B12: CNP Dynamic Protection 80 | C12: Model | D12: =VLOOKUP($A12,'[2]Desk mapping'!$G:$L,5,FALSE) -> Outcome Oriented Strategies | E12: =VLOOKUP($A12,'[2]Desk mapping'!$G:$L,6,FALSE) -> Capital Guaranteed | F12: Jen | G12: Craig | H12: =VLOOKUP(A12,[3]AUM!$A$3:$B$131,2,0) -> 116832547
A13: CNPPROT80 | B13: CNP Protection 80 | C13: Model | D13: Outcome Oriented Strategies | E13: Capital Guaranteed | F13: Jen | G13: Craig | H13: =VLOOKUP(A13,[3]AUM!$A$3:$B$131,2,0) -> 96897819
A14: CNPTHEMPROT | B14: CNP THEMATIC PROTECTION 80 | C14: Model | D14: Outcome Oriented Strategies | E14: Capital Guaranteed | F14: Jen | G14: Craig | H14: =VLOOKUP(A14,[3]AUM!$A$3:$B$131,2,0) -> 195364106
A15: COBBLEURO | B15: CAM OBBLIGAZIONARIA EURO | C15: Model | D15: =VLOOKUP($A15,'[2]Desk mapping'!$G:$L,5,FALSE) -> Allocation Driven Strategies | E15: =VLOOKUP($A15,'[2]Desk mapping'!$G:$L,6,FALSE) -> Conservative | F15: Craig | H15: =VLOOKUP(A15,[3]AUM!$A$3:$B$131,2,0) -> 2649
A16: CREDDITO | B16: CAM REDDITO | C16: Model | D16: =VLOOKUP($A16,'[2]Desk mapping'!$G:$L,5,FALSE) -> Allocation Driven Strategies | E16: =VLOOKUP($A16,'[2]Desk mapping'!$G:$L,6,FALSE) -> Conservative | F16: Craig | H16: =VLOOKUP(A16,[3]AUM!$A$3:$B$131,2,0) -> 83275
A17: CRVDYNPR80 | B17: CRV Dynamic Protection 80 | C17: Model | D17: =VLOOKUP($A17,'[2]Desk mapping'!$G:$L,5,FALSE) -> Outcome Oriented Strategies | E17: =VLOOKUP($A17,'[2]Desk mapping'!$G:$L,6,FALSE) -> Capital Guaranteed | F17: Jen | G17: Craig | H17: =VLOOKUP(A17,[3]AUM!$A$3:$B$131,2,0) -> 279293562
A18: CRVPROT80 | B18: CRV Protection 80 | C18: Model | D18: Outcome Oriented Strategies | E18: Capital Guaranteed | F18: Jen | G18: Craig | H18: =VLOOKUP(A18,[3]AUM!$A$3:$B$131,2,0) -> 106822030
A19: CRVTHEMPROT | B19: CRV THEMATIC PROTECTION 80 | C19: Model | D19: Outcome Oriented Strategies | E19: Capital Guaranteed | F19: Jen | G19: Craig | H19: =VLOOKUP(A19,[3]AUM!$A$3:$B$131,2,0) -> 307505809
A20: CSVILUPPO | B20: CAM SVILUPPO | C20: Model | D20: =VLOOKUP($A20,'[2]Desk mapping'!$G:$L,5,FALSE) -> Allocation Driven Strategies | E20: =VLOOKUP($A20,'[2]Desk mapping'!$G:$L,6,FALSE) -> Growth | F20: Craig | H20: =VLOOKUP(A20,[3]AUM!$A$3:$B$131,2,0) -> 33771
A21: CTREND_20 | B21: CAM TREND 20 | C21: Model | D21: =VLOOKUP($A21,'[2]Desk mapping'!$G:$L,5,FALSE) -> Allocation Driven Strategies | E21: =VLOOKUP($A21,'[2]Desk mapping'!$G:$L,6,FALSE) -> Conservative | F21: Craig | H21: =VLOOKUP(A21,[3]AUM!$A$3:$B$131,2,0) -> 23564
A22: DINAR1TF | B22: UNIFLEX ACTIVE 1 | C22: Model | D22: =VLOOKUP($A22,'[2]Desk mapping'!$G:$L,5,FALSE) -> Allocation Driven Strategies | E22: =VLOOKUP($A22,'[2]Desk mapping'!$G:$L,6,FALSE) -> Moderate | F22: Craig | H22: =VLOOKUP(A22,[3]AUM!$A$3:$B$131,2,0) -> 1363503
A23: DINAR2TF | B23: UNIFLEX ACTIVE 2 | C23: Model | D23: =VLOOKUP($A23,'[2]Desk mapping'!$G:$L,5,FALSE) -> Allocation Driven Strategies | E23: =VLOOKUP($A23,'[2]Desk mapping'!$G:$L,6,FALSE) -> Moderate | F23: Craig | H23: =VLOOKUP(A23,[3]AUM!$A$3:$B$131,2,0) -> 26945800
A24: DINAR3TF | B24: UNIFLEX ACTIVE 3 | C24: Model | D24: =VLOOKUP($A24,'[2]Desk mapping'!$G:$L,5,FALSE) -> Allocation Driven Strategies | E24: =VLOOKUP($A24,'[2]Desk mapping'!$G:$L,6,FALSE) -> Moderate | F24: Craig | H24: =VLOOKUP(A24,[3]AUM!$A$3:$B$131,2,0) -> 795570
A25: DIOP 1 | B25: DISCRETIONARY INCOME ORIENTED PRODUCTS 1 | C25: Model | D25: Outcome Oriented Strategies | E25: Income | F25: Nick | G25: Craig | H25: 9783751.7
A26: DIOP 2 | B26: DISCRETIONARY INCOME ORIENTED PRODUCTS 2 | C26: Model | D26: Outcome Oriented Strategies | E26: Income | F26: Nick | G26: Craig | H26: 3901388.4
A27: DIOP3 | B27: DISCRETIONARY INCOME ORIENTED PRODUCTS 3 | C27: Model | D27: Outcome Oriented Strategies | E27: Income | F27: Craig | G27: Nick | H27: 6968432.6
A28: DIOP4 | B28: DISCRETIONARY INCOME ORIENTED PRODUCTS 4 | C28: Model | D28: Outcome Oriented Strategies | E28: Thematic | F28: Nick | G28: Craig | H28: 14185291
A29: E118 | B29: AMUNDI UNICREDIT PREM PORT- PRUDENTIAL | C29: Fund | D29: =VLOOKUP($A29,'[2]Total AUM Data'!$A:$I,5,FALSE) -> Allocation Driven Strategies | E29: =VLOOKUP($A29,'[2]Total AUM Data'!$A:$I,6,FALSE) -> Conservative | F29: Alan | G29: Jen | H29: =VLOOKUP(A29,[3]AUM!$A$3:$B$131,2,0) -> 7495265.8
A30: E119 | B30: AMUNDI UNICREDIT PREMIUM PORT - DYNAMIC | C30: Fund | D30: =VLOOKUP($A30,'[2]Total AUM Data'!$A:$I,5,FALSE) -> Allocation Driven Strategies | E30: =VLOOKUP($A30,'[2]Total AUM Data'!$A:$I,6,FALSE) -> Growth | F30: Jen | G30: Alan | H30: =VLOOKUP(A30,[3]AUM!$A$3:$B$131,2,0) -> 58236487
A31: E120 | B31: AMUNDI UNICREDIT PREM PORT- MULTI ASSET | C31: Fund | D31: =VLOOKUP($A31,'[2]Total AUM Data'!$A:$I,5,FALSE) -> Allocation Driven Strategies | E31: =VLOOKUP($A31,'[2]Total AUM Data'!$A:$I,6,FALSE) -> Moderate | F31: Alan | G31: Jen | H31: =VLOOKUP(A31,[3]AUM!$A$3:$B$131,2,0) -> 1.2144878e+08
A32: E142 | B32: AMUNDI FUND SOLUTIONS - BALANCED | C32: Fund | D32: =VLOOKUP($A32,'[2]Total AUM Data'!$A:$I,5,FALSE) -> Allocation Driven Strategies | E32: =VLOOKUP($A32,'[2]Total AUM Data'!$A:$I,6,FALSE) -> Moderate | F32: Jen | G32: Alan | H32: =VLOOKUP(A32,[3]AUM!$A$3:$B$131,2,0) -> 3.2400944e+08
A33: E143 | B33: AMUNDI FUND SOLUTIONS - CONSERVATIVE | C33: Fund | D33: =VLOOKUP($A33,'[2]Total AUM Data'!$A:$I,5,FALSE) -> Allocation Driven Strategies | E33: =VLOOKUP($A33,'[2]Total AUM Data'!$A:$I,6,FALSE) -> Conservative | F33: Alan | G33: Jen | H33: =VLOOKUP(A33,[3]AUM!$A$3:$B$131,2,0) -> 2.428063e+08
A34: E144 | B34: AMUNDI FUND SOLUTIONS - DIVERSIFIED GROWTH - A | C34: Fund | D34: =VLOOKUP($A34,'[2]Total AUM Data'!$A:$I,5,FALSE) -> Allocation Driven Strategies | E34: =VLOOKUP($A34,'[2]Total AUM Data'!$A:$I,6,FALSE) -> Growth | F34: Richard | G34: Peter | H34: =VLOOKUP(A34,[3]AUM!$A$3:$B$131,2,0) -> 83823204
A35: E193 | B35: =VLOOKUP(A35,'[1]Dublin funds'!$B:$AY,7,FALSE) -> Amundi Fund Solutions - Diversified Income Best Select 2022 | C35: Fund | D35: =VLOOKUP($A35,'[2]Total AUM Data'!$A:$I,5,FALSE) -> Outcome Oriented Strategies | E35: =VLOOKUP($A35,'[2]Total AUM Data'!$A:$I,6,FALSE) -> Income | F35: Nick | G35: Reinhard | H35: =VLOOKUP(A35,[3]AUM!$A$3:$B$131,2,0) -> 1.3642864e+08
A36: E207 | B36: PI INVESTMENT FUNDS - TACTICAL ALLOCATION FUND - H | C36: Fund | D36: =VLOOKUP($A36,'[2]Total AUM Data'!$A:$I,5,FALSE) -> Service Fund | E36: =VLOOKUP($A36,'[2]Total AUM Data'!$A:$I,6,FALSE) -> Equity | F36: Craig | H36: =VLOOKUP(A36,[3]AUM!$A$3:$B$131,2,0) -> 53160978
A37: E208 | B37: PI INVESTMENT FUNDS - TACTICAL ALLOCATION BOND FUND - H | C37: Fund | D37: =VLOOKUP($A37,'[2]Total AUM Data'!$A:$I,5,FALSE) -> Service Fund | E37: =VLOOKUP($A37,'[2]Total AUM Data'!$A:$I,6,FALSE) -> Bond | F37: Craig | H37: =VLOOKUP(A37,[3]AUM!$A$3:$B$131,2,0) -> 74247836
A38: E209 | B38: PI INVESTMENT FUNDS - DYNAMIC ALLOCATION FUND - E | C38: Fund | D38: =VLOOKUP($A38,'[2]Total AUM Data'!$A:$I,5,FALSE) -> Service Fund | E38: =VLOOKUP($A38,'[2]Total AUM Data'!$A:$I,6,FALSE) -> Flexible | F38: Alan | G38: Richard | H38: =VLOOKUP(A38,[3]AUM!$A$3:$B$131,2,0) -> 1.987592e+08
A39: E224 | B39: PI INVESTMENT FUNDS - TACTICAL ALLOCATION PILLAR - E | C39: Fund | D39: =VLOOKUP($A39,'[2]Total AUM Data'!$A:$I,5,FALSE) -> Service Fund | E39: =VLOOKUP($A39,'[2]Total AUM Data'!$A:$I,6,FALSE) -> Income | F39: Richard | G39: Craig | H39: =VLOOKUP(A39,[3]AUM!$A$3:$B$131,2,0) -> 59556669
A40: F100123 | B40: Amundi Env and Climate Change Sol Fund | C40: Fund | D40: Allocation Driven Strategies | E40: Equity | F40: Nick | G40: Richard | H40: =VLOOKUP(A40,[3]AUM!$A$3:$B$131,2,0)/147 -> 73301177
A41: MAA | B41: CAM Novembre | C41: Model | D41: =VLOOKUP($A41,'[2]Desk mapping'!$G:$L,5,FALSE) -> Outcome Oriented Strategies | E41: =VLOOKUP($A41,'[2]Desk mapping'!$G:$L,6,FALSE) -> Capital Protection | F41: Bertrand | G41: Craig | H41: =VLOOKUP(A41,[3]AUM!$A$3:$B$131,2,0) -> 279016
A42: MAB | B42: CAM Dicembre | C42: Model | D42: =VLOOKUP($A42,'[2]Desk mapping'!$G:$L,5,FALSE) -> Outcome Oriented Strategies | E42: =VLOOKUP($A42,'[2]Desk mapping'!$G:$L,6,FALSE) -> Capital Protection | F42: Bertrand | G42: Craig | H42: =VLOOKUP(A42,[3]AUM!$A$3:$B$131,2,0) -> 4871246
A43: MAC | B43: CAM Gennaio | C43: Model | D43: =VLOOKUP($A43,'[2]Desk mapping'!$G:$L,5,FALSE) -> Outcome Oriented Strategies | E43: =VLOOKUP($A43,'[2]Desk mapping'!$G:$L,6,FALSE) -> Capital Protection | F43: Bertrand | G43: Craig | H43: =VLOOKUP(A43,[3]AUM!$A$3:$B$131,2,0) -> 187778
A44: MAD | B44: CAM Febbraio | C44: Model | D44: =VLOOKUP($A44,'[2]Desk mapping'!$G:$L,5,FALSE) -> Outcome Oriented Strategies | E44: =VLOOKUP($A44,'[2]Desk mapping'!$G:$L,6,FALSE) -> Capital Protection | F44: Bertrand | G44: Craig | H44: =VLOOKUP(A44,[3]AUM!$A$3:$B$131,2,0) -> 341235
A45: MAE | B45: CAM Marzo | C45: Model | D45: =VLOOKUP($A45,'[2]Desk mapping'!$G:$L,5,FALSE) -> Outcome Oriented Strategies | E45: =VLOOKUP($A45,'[2]Desk mapping'!$G:$L,6,FALSE) -> Capital Protection | F45: Bertrand | G45: Craig | H45: =VLOOKUP(A45,[3]AUM!$A$3:$B$131,2,0) -> 154948
A46: MAF | B46: CAM Aprile | C46: Model | D46: =VLOOKUP($A46,'[2]Desk mapping'!$G:$L,5,FALSE) -> Outcome Oriented Strategies | E46: =VLOOKUP($A46,'[2]Desk mapping'!$G:$L,6,FALSE) -> Capital Protection | F46: Bertrand | G46: Craig | H46: =VLOOKUP(A46,[3]AUM!$A$3:$B$131,2,0) -> 87215
A47: MAG | B47: CAM Maggio | C47: Model | D47: =VLOOKUP($A47,'[2]Desk mapping'!$G:$L,5,FALSE) -> Outcome Oriented Strategies | E47: =VLOOKUP($A47,'[2]Desk mapping'!$G:$L,6,FALSE) -> Capital Protection | F47: Bertrand | G47: Craig | H47: =VLOOKUP(A47,[3]AUM!$A$3:$B$131,2,0) -> 134904
A48: MAH | B48: CAM Giugno | C48: Model | D48: =VLOOKUP($A48,'[2]Desk mapping'!$G:$L,5,FALSE) -> Outcome Oriented Strategies | E48: =VLOOKUP($A48,'[2]Desk mapping'!$G:$L,6,FALSE) -> Capital Protection | F48: Bertrand | G48: Craig | H48: =VLOOKUP(A48,[3]AUM!$A$3:$B$131,2,0) -> 634676
A49: MAL | B49: CAM Agosto | C49: Model | D49: =VLOOKUP($A49,'[2]Desk mapping'!$G:$L,5,FALSE) -> Outcome Oriented Strategies | E49: =VLOOKUP($A49,'[2]Desk mapping'!$G:$L,6,FALSE) -> Capital Protection | F49: Bertrand | G49: Craig | H49: =VLOOKUP(A49,[3]AUM!$A$3:$B$131,2,0) -> 142698
A50: MAM | B50: CAM Settembre | C50: Model | D50: =VLOOKUP($A50,'[2]Desk mapping'!$G:$L,5,FALSE) -> Outcome Oriented Strategies | E50: =VLOOKUP($A50,'[2]Desk mapping'!$G:$L,6,FALSE) -> Capital Protection | F50: Bertrand | G50: Craig | H50: =VLOOKUP(A50,[3]AUM!$A$3:$B$131,2,0) -> 16557
A51: MAN | B51: CAM Ottobre | C51: Model | D51: =VLOOKUP($A51,'[2]Desk mapping'!$G:$L,5,FALSE) -> Outcome Oriented Strategies | E51: =VLOOKUP($A51,'[2]Desk mapping'!$G:$L,6,FALSE) -> Capital Protection | F51: Bertrand | G51: Craig | H51: =VLOOKUP(A51,[3]AUM!$A$3:$B$131,2,0) -> 28074
A52: MATRUNIP | B52: Unit Linked A TR UNIPLAN | C52: Model | D52: =VLOOKUP($A52,'[2]Desk mapping'!$G:$L,5,FALSE) -> Allocation Driven Strategies | E52: =VLOOKUP($A52,'[2]Desk mapping'!$G:$L,6,FALSE) -> Flexible | F52: Craig | H52: =VLOOKUP(A52,[3]AUM!$A$3:$B$131,2,0) -> 12280450
A53: MEPF10 | B53: UNIT LINKED G5 NEW | C53: Model | D53: =VLOOKUP($A53,'[2]Desk mapping'!$G:$L,5,FALSE) -> Allocation Driven Strategies | E53: =VLOOKUP($A53,'[2]Desk mapping'!$G:$L,6,FALSE) -> Growth | F53: Craig | H53: =VLOOKUP(A53,[3]AUM!$A$3:$B$131,2,0) -> 395535
A54: MEPF2N | B54: UNIT LINKED E2 NEW | C54: Model | D54: =VLOOKUP($A54,'[2]Desk mapping'!$G:$L,5,FALSE) -> Allocation Driven Strategies | E54: =VLOOKUP($A54,'[2]Desk mapping'!$G:$L,6,FALSE) -> Conservative | F54: Craig | H54: =VLOOKUP(A54,[3]AUM!$A$3:$B$131,2,0) -> 7616069
A55: MEPF4 | B55: Unit Linked OLD 4 | C55: Model | D55: =VLOOKUP($A55,'[2]Desk mapping'!$G:$L,5,FALSE) -> Allocation Driven Strategies | E55: =VLOOKUP($A55,'[2]Desk mapping'!$G:$L,6,FALSE) -> Conservative | F55: Craig | H55: =VLOOKUP(A55,[3]AUM!$A$3:$B$131,2,0) -> 1067361
A56: MEPF5 | B56: UNIT LINKED E3 NEW | C56: Model | D56: =VLOOKUP($A56,'[2]Desk mapping'!$G:$L,5,FALSE) -> Allocation Driven Strategies | E56: =VLOOKUP($A56,'[2]Desk mapping'!$G:$L,6,FALSE) -> Conservative | F56: Craig | H56: =VLOOKUP(A56,[3]AUM!$A$3:$B$131,2,0) -> 72484395
A57: MEPF6 | B57: UNIT LINKED E4 NEW | C57: Model | D57: =VLOOKUP($A57,'[2]Desk mapping'!$G:$L,5,FALSE) -> Allocation Driven Strategies | E57: =VLOOKUP($A57,'[2]Desk mapping'!$G:$L,6,FALSE) -> Moderate | F57: Craig | H57: =VLOOKUP(A57,[3]AUM!$A$3:$B$131,2,0) -> 64408792
A58: MEPF8 | B58: UNIT LINKED E6 NEW | C58: Model | D58: =VLOOKUP($A58,'[2]Desk mapping'!$G:$L,5,FALSE) -> Allocation Driven Strategies | E58: =VLOOKUP($A58,'[2]Desk mapping'!$G:$L,6,FALSE) -> Growth | F58: Craig | H58: =VLOOKUP(A58,[3]AUM!$A$3:$B$131,2,0) -> 128787502
A59: MLIFEBND | B59: Life Program Bond | C59: Model | D59: =VLOOKUP($A59,'[2]Desk mapping'!$G:$L,5,FALSE) -> Allocation Driven Strategies | E59: =VLOOKUP($A59,'[2]Desk mapping'!$G:$L,6,FALSE) -> Conservative | F59: Craig | H59: =VLOOKUP(A59,[3]AUM!$A$3:$B$131,2,0) -> 86278219
A60: MLINC | B60: UL Life Income | C60: Model | D60: =VLOOKUP($A60,'[2]Desk mapping'!$G:$L,5,FALSE) -> Outcome Oriented Strategies | E60: =VLOOKUP($A60,'[2]Desk mapping'!$G:$L,6,FALSE) -> Income | F60: Richard | G60: Craig | H60: =VLOOKUP(A60,[3]AUM!$A$3:$B$131,2,0) -> 215406941
A61: MLPFLEX | B61: Life Program Flessibile | C61: Model | D61: =VLOOKUP($A61,'[2]Desk mapping'!$G:$L,5,FALSE) -> Allocation Driven Strategies | E61: =VLOOKUP($A61,'[2]Desk mapping'!$G:$L,6,FALSE) -> Flexible | F61: Craig | H61: =VLOOKUP(A61,[3]AUM!$A$3:$B$131,2,0) -> 24819922
A62: MULLI360 | B62: UL Life Income 360 | C62: Model | D62: =VLOOKUP($A62,'[2]Desk mapping'!$G:$L,5,FALSE) -> Outcome Oriented Strategies | E62: =VLOOKUP($A62,'[2]Desk mapping'!$G:$L,6,FALSE) -> Income | F62: Richard | G62: Craig | H62: =VLOOKUP(A62,[3]AUM!$A$3:$B$131,2,0) -> 154991340
A63: MULSTEP | B63: STEP CRESCITA | C63: Model | D63: =VLOOKUP($A63,'[2]Desk mapping'!$G:$L,5,FALSE) -> Outcome Oriented Strategies | E63: =VLOOKUP($A63,'[2]Desk mapping'!$G:$L,6,FALSE) -> Risk Accumulation | F63: Craig | H63: =VLOOKUP(A63,[3]AUM!$A$3:$B$131,2,0) -> 8203700
A64: Multhem | B64: Unit Linked Multi Thematic Global Eq | C64: Model | D64: =VLOOKUP($A64,'[2]Desk mapping'!$G:$L,5,FALSE) -> Outcome Oriented Strategies | E64: =VLOOKUP($A64,'[2]Desk mapping'!$G:$L,6,FALSE) -> Thematic | F64: Nick | H64: =VLOOKUP(A64,[3]AUM!$A$3:$B$131,2,0) -> 1795670827
A65: MUNIP | B65: Unit Linked AMix UNIPLAN | C65: Model | D65: =VLOOKUP($A65,'[2]Desk mapping'!$G:$L,5,FALSE) -> Allocation Driven Strategies | E65: =VLOOKUP($A65,'[2]Desk mapping'!$G:$L,6,FALSE) -> Moderate | F65: Craig | H65: =VLOOKUP(A65,[3]AUM!$A$3:$B$131,2,0) -> 255343
A66: MUSG | B66: Univalore Stars Growth - Comanaged with Fund Selection - | C66: Model | D66: =VLOOKUP($A66,'[2]Desk mapping'!$G:$L,5,FALSE) -> Outcome Oriented Strategies | E66: =VLOOKUP($A66,'[2]Desk mapping'!$G:$L,6,FALSE) -> Thematic | F66: Nick | G66: Alfonso | H66: =VLOOKUP(A66,[3]AUM!$A$3:$B$131,2,0) -> 973396645
A67: MUSI | B67: Univalore Stars Income | C67: Model | D67: =VLOOKUP($A67,'[2]Desk mapping'!$G:$L,5,FALSE) -> Outcome Oriented Strategies | E67: =VLOOKUP($A67,'[2]Desk mapping'!$G:$L,6,FALSE) -> Income | F67: Richard | G67: Craig | H67: =VLOOKUP(A67,[3]AUM!$A$3:$B$131,2,0) -> 239238036
A68: PF101372 | B68: AFS ICAV Planet ESG Conservative | C68: Fund | D68: Allocation Driven Strategies | E68: Conservative | F68: Peter | G68: Richard | H68: =VLOOKUP(A68,[3]AUM!$A$3:$B$131,2,0) -> #N/A
A69: PF101376 | B69: AFS ICAV Planet ESG Balanced | C69: Fund | D69: Allocation Driven Strategies | E69: Moderate | F69: Peter | G69: Richard | H69: =VLOOKUP(A69,[3]AUM!$A$3:$B$131,2,0) -> #N/A
A70: PF101380 | B70: AFS ICAV Planet ESG Dynamic | C70: Fund | D70: Allocation Driven Strategies | E70: Growth | F70: Peter | G70: Richard | H70: =VLOOKUP(A70,[3]AUM!$A$3:$B$131,2,0) -> #N/A
A71: PF103025 | B71: ASI - PROGETTO AZIONE FUTURO GREEN | C71: Fund | D71: Outcome Oriented Strategies | E71: Risk Accumulation | F71: Richard | G71: Craig | H71: =VLOOKUP(A71,[3]AUM!$A$3:$B$131,2,0) -> 93538758
A72: PF52231 | B72: AMUNDI SENTIERO SOSTENIBILE | C72: Fund | D72: Outcome Oriented Strategies | E72: Risk Accumulation | F72: Richard | G72: Craig | H72: =VLOOKUP(A72,[3]AUM!$A$3:$B$131,2,0) -> #N/A
A73: PF71664 | B73: AMUNDI SOLUZIONI ITALIA - PROGETTO AZIONE MEGATREND - E | C73: Fund | D73: =VLOOKUP($A73,'[2]Total AUM Data'!$A:$I,5,FALSE) -> Outcome Oriented Strategies | E73: =VLOOKUP($A73,'[2]Total AUM Data'!$A:$I,6,FALSE) -> Risk Accumulation | F73: Nick | G73: Peter | H73: =VLOOKUP(A73,[3]AUM!$A$3:$B$131,2,0) -> #N/A
A74: PF76580 | B74: AMUNDI SOLUZIONI ITALIA - PROGETTO AZIONE MEGATREND (II) - E | C74: Fund | D74: =VLOOKUP($A74,'[2]Total AUM Data'!$A:$I,5,FALSE) -> Outcome Oriented Strategies | E74: =VLOOKUP($A74,'[2]Total AUM Data'!$A:$I,6,FALSE) -> Risk Accumulation | F74: Nick | G74: Peter | H74: =VLOOKUP(A74,[3]AUM!$A$3:$B$131,2,0) -> #N/A
A75: PF78195 | B75: AMUNDI SOLUZIONI ITALIA - PROGETTO AZIONE CAMBIAMENTO CLIMATICO - E | C75: Fund | D75: =VLOOKUP($A75,'[2]Total AUM Data'!$A:$I,5,FALSE) -> Outcome Oriented Strategies | E75: =VLOOKUP($A75,'[2]Total AUM Data'!$A:$I,6,FALSE) -> Risk Accumulation | F75: Nick | G75: Peter | H75: =VLOOKUP(A75,[3]AUM!$A$3:$B$131,2,0) -> #N/A
A76: PF79139 | B76: AMUNDI SOLUZIONI ITALIA - PROGETTO AZIONE CAMBIAMENTO CLIMATICO (II) - E | C76: Fund | D76: =VLOOKUP($A76,'[2]Total AUM Data'!$A:$I,5,FALSE) -> Outcome Oriented Strategies | E76: =VLOOKUP($A76,'[2]Total AUM Data'!$A:$I,6,FALSE) -> Risk Accumulation | F76: Nick | G76: Peter | H76: =VLOOKUP(A76,[3]AUM!$A$3:$B$131,2,0) -> #N/A
A77: PF80513 | B77: ASI - PROGETTO AZION MILLENNIALS | C77: Fund | D77: Outcome Oriented Strategies | E77: Risk Accumulation | F77: Nick | G77: Peter | H77: =VLOOKUP(A77,[3]AUM!$A$3:$B$207,2,0) -> #N/A
A78: PF82304 | B78: ASI - PROGETTO AZION MILLENNIALS II | C78: Fund | D78: Outcome Oriented Strategies | E78: Risk Accumulation | F78: Nick | G78: Peter | H78: =VLOOKUP(A78,[3]AUM!$A$3:$B$207,2,0) -> #N/A
A79: PF87100 | B79: AMUNDI FUND SOLUTIONS - SABADELL URQUIJO ACUMULACION | C79: Fund | D79: Allocation Driven Strategies | E79: Conservative | F79: Alan | G79: Richard | H79: =VLOOKUP(A79,[3]AUM!$A$3:$B$131,2,0) -> 6970226.2
A80: PF87115 | B80: AMUNDI FUND SOLUTIONS - SABADELL URQUIJO CRECIMIENTO | C80: Fund | D80: Allocation Driven Strategies | E80: Growth | F80: Bertrand | G80: Richard | H80: =VLOOKUP(A80,[3]AUM!$A$3:$B$131,2,0) -> 3927561.1
A81: PF88300 | B81: ASI - PROGETTO AZIONE ENERGY TRANSITION | C81: Fund | D81: Outcome Oriented Strategies | E81: Risk Accumulation | F81: Richard | G81: Craig | H81: =VLOOKUP(A81,[3]AUM!$A$3:$B$132,2,0) -> 4.5198023e+08
A82: PF88524 | B82: AMUNDI ELITE THEMATIC MULTI ASSET | C82: Fund | D82: Outcome Oriented Strategies | E82: Thematic | F82: Nick | G82: Richard | H82: =VLOOKUP(A82,[3]AUM!$A$3:$B$131,2,0) -> 6.5152609e+08
A83: PF89408 | B83: ASI - PROGETTO AZIONE ENERGY TRANSITION (II) | C83: Fund | D83: Outcome Oriented Strategies | E83: Risk Accumulation | F83: Richard | G83: Craig | H83: =VLOOKUP(A83,[3]AUM!$A$3:$B$131,2,0) -> 2.7793822e+08
A84: PF92127 | B84: AMUNDI SOLUZIONI ITALIA - PROGETTO AZIONE INFRASTRUTTURE SOSTENIBILI | C84: Fund | D84: Outcome Oriented Strategies | E84: Risk Accumulation | F84: Richard | G84: Craig | H84: =VLOOKUP(A84,[3]AUM!$A$3:$B$131,2,0) -> 3.3514686e+08
A85: PF95239 | B85: AMUNDI SOLUZIONI ITALIA - PROGETTO AZIONE INFRASTRUTTURE SOSTENIBILI (II) | C85: Fund | D85: Outcome Oriented Strategies | E85: Risk Accumulation | F85: Richard | G85: Craig | H85: =VLOOKUP(A85,[3]AUM!$A$3:$B$131,2,0) -> 3.1941249e+08
A86: PLIC | B86: PL Income Clock | C86: Model | D86: =VLOOKUP($A86,'[2]Desk mapping'!$G:$L,5,FALSE) -> Allocation Driven Strategies | E86: =VLOOKUP($A86,'[2]Desk mapping'!$G:$L,6,FALSE) -> Flexible | F86: Craig | H86: =VLOOKUP(A86,[3]AUM!$A$3:$B$131,2,0) -> 33652386
A87: PMAI | B87: CAM Luglio | C87: Model | D87: =VLOOKUP($A87,'[2]Total AUM Data'!$A:$I,5,FALSE) -> Outcome Oriented Strategies | E87: =VLOOKUP($A87,'[2]Total AUM Data'!$A:$I,6,FALSE) -> Capital Protection | F87: Craig | H87: =VLOOKUP(A87,[3]AUM!$A$3:$B$131,2,0) -> 77561
A88: PP1-3Y | B88: PL Euro Bond 1 to 3 years | C88: Model | D88: =VLOOKUP($A88,'[2]Desk mapping'!$G:$L,5,FALSE) -> Allocation Driven Strategies | E88: =VLOOKUP($A88,'[2]Desk mapping'!$G:$L,6,FALSE) -> Conservative | F88: Craig | H88: =VLOOKUP(A88,[3]AUM!$A$3:$B$131,2,0) -> 87573063
A89: PP3Y | B89: PL Euro Bond over 3 years | C89: Model | D89: =VLOOKUP($A89,'[2]Desk mapping'!$G:$L,5,FALSE) -> Allocation Driven Strategies | E89: =VLOOKUP($A89,'[2]Desk mapping'!$G:$L,6,FALSE) -> Conservative | F89: Richard | G89: Craig | H89: =VLOOKUP(A89,[3]AUM!$A$3:$B$131,2,0) -> 122521317
A90: PSUKLD1 | B90: Amundi Invensys Broad Bond Portfolio | C90: Fund | D90: =VLOOKUP($A90,'[2]Total AUM Data'!$A:$I,5,FALSE) -> Allocation Driven Strategies | E90: =VLOOKUP($A90,'[2]Total AUM Data'!$A:$I,6,FALSE) -> Flexible | F90: Richard | G90: Alan | H90: =VLOOKUP(A90,[3]AUM!$A$3:$B$131,2,0)/0.8573 -> 1.6456292e+08
A91: R1M | B91: CAM CNP - LINEA DINAMICA | C91: Model | D91: =VLOOKUP($A91,'[2]Desk mapping'!$G:$L,5,FALSE) -> Allocation Driven Strategies | E91: =VLOOKUP($A91,'[2]Desk mapping'!$G:$L,6,FALSE) -> Growth | F91: Craig | H91: =VLOOKUP(A91,[3]AUM!$A$3:$B$131,2,0) -> 20379176
A92: R2M | B92: =VLOOKUP(A92,'[1]Model portfolios'!$A:$AS,4,FALSE) -> CNP Linea Protetta Dinamica Plus | C92: Model | D92: =VLOOKUP($A92,'[2]Desk mapping'!$G:$L,5,FALSE) -> Allocation Driven Strategies | E92: =VLOOKUP($A92,'[2]Desk mapping'!$G:$L,6,FALSE) -> Growth | F92: Craig | H92: =VLOOKUP(A92,[3]AUM!$A$3:$B$131,2,0) -> 3991454
A93: SAXO | B93: SAXO EUROPE | C93: Model | D93: Allocation Driven Strategies | E93: Conservative | F93: Peter | G93: Richard | H93: 310389062
A94: STEPONE | B94: CAM STEP ONE | C94: Model | D94: =VLOOKUP($A94,'[2]Desk mapping'!$G:$L,5,FALSE) -> Allocation Driven Strategies | E94: =VLOOKUP($A94,'[2]Desk mapping'!$G:$L,6,FALSE) -> Conservative | F94: Craig | H94: =VLOOKUP(A94,[3]AUM!$A$3:$B$131,2,0) -> 78465
A95: UES20 | B95: Univalore E Strategia 20 | C95: Model | D95: =VLOOKUP($A95,'[2]Desk mapping'!$G:$L,5,FALSE) -> Allocation Driven Strategies | E95: =VLOOKUP($A95,'[2]Desk mapping'!$G:$L,6,FALSE) -> Flexible | F95: Alan | G95: Richard | H95: =VLOOKUP(A95,[3]AUM!$A$3:$B$131,2,0) -> 23044548
A96: UES30 | B96: Univalore E Strategia 30 | C96: Model | D96: =VLOOKUP($A96,'[2]Desk mapping'!$G:$L,5,FALSE) -> Allocation Driven Strategies | E96: =VLOOKUP($A96,'[2]Desk mapping'!$G:$L,6,FALSE) -> Flexible | F96: Alan | G96: Richard | H96: =VLOOKUP(A96,[3]AUM!$A$3:$B$131,2,0) -> 234658014
A97: UES40 | B97: Univalore E Strategia 40 | C97: Model | D97: =VLOOKUP($A97,'[2]Desk mapping'!$G:$L,5,FALSE) -> Allocation Driven Strategies | E97: =VLOOKUP($A97,'[2]Desk mapping'!$G:$L,6,FALSE) -> Flexible | F97: Alan | G97: Richard | H97: =VLOOKUP(A97,[3]AUM!$A$3:$B$131,2,0) -> 17723615
A98: UES50 | B98: Univalore Stars Balanced | C98: Model | D98: =VLOOKUP($A98,'[2]Desk mapping'!$G:$L,5,FALSE) -> Allocation Driven Strategies | E98: =VLOOKUP($A98,'[2]Desk mapping'!$G:$L,6,FALSE) -> Flexible | F98: Alan | G98: Richard | H98: =VLOOKUP(A98,[3]AUM!$A$3:$B$131,2,0) -> 550852602
A99: UES70 | B99: Univalore E Strategia 70 | C99: Model | D99: =VLOOKUP($A99,'[2]Desk mapping'!$G:$L,5,FALSE) -> Allocation Driven Strategies | E99: =VLOOKUP($A99,'[2]Desk mapping'!$G:$L,6,FALSE) -> Flexible | F99: Alan | G99: Richard | H99: =VLOOKUP(A99,[3]AUM!$A$3:$B$131,2,0) -> 328851184
A100: ULACCO | B100: Unit Linked Multi Equity Accumulation | C100: Model | D100: =VLOOKUP($A100,'[2]Desk mapping'!$G:$L,5,FALSE) -> Outcome Oriented Strategies | E100: =VLOOKUP($A100,'[2]Desk mapping'!$G:$L,6,FALSE) -> Risk Accumulation | F100: Craig | H100: =VLOOKUP(A100,[3]AUM!$A$3:$B$131,2,0) -> 4704953
...

Sheet Total AUM Sheet
C1: Values
A2: Strategy Type | B2: Strategy Detail | C2: AUM 9th April 2021 file in mln* | D2: AUM 31st Dec 2020 file in mln**
A3: Allocation Driven Strategies | B3: Conservative | C3: 911.70197 | D3: 934.106
B4: Equity | C4: 3287.5175 | D4: 3201.26
B5: Flexible | C5: 1395.0837 | D5: 1512.3925
B6: Growth | C6: 633.43394 | D6: 601.00331
B7: Moderate | C7: 616.85595 | D7: 621.12457
A8: Allocation Driven Strategies Total | C8: 6844.5931 | D8: 6869.8864
A9: Outcome Oriented Strategies | B9: Capital Guaranteed | C9: 1208.6936 | D9: 1252.8589
B10: Capital Protection | C10: 6.955908 | D10: 6.975748
B11: Income | C11: 862.22932 | D11: 920.65793
B12: Risk Accumulation | C12: 1773.0447 | D12: 2194.2822
B13: Thematic | C13: 1823.4919 | D13: 1655.9711 | L13: Diff: €+389m
A14: Outcome Oriented Strategies Total | C14: 5674.4154 | D14: 6030.7459
A15: Service Fund | B15: Bond | C15: 74.247836 | D15: 77.23279
B16: Equity | C16: 53.160978 | D16: 56.764605
B17: Flexible | C17: 198.7592 | D17: 234.21407
B18: Income | C18: 59.556669 | D18: 74.824882
A19: Service Fund Total | C19: 385.72468 | D19: 443.03635
A20: (blank) | B20: (blank) | C20: 0 | D20: 0
A21: (blank) Total | C21: 0 | D21: 0 | F21: 21332 | G21: 21721 | H21: =G21-F21 -> 389
A22: Grand Total | C22: 12904.733 | D22: 13343.669

Sheet This Period AUM by Fund
A3: Portfolios name | B3: Sum of Difference In AUM | C3: Sum of Flows April mln
A4: Unit Linked Multi Thematic Global Eq | B4: 0 | C4: 0
A5: Unit Linked Multi Equity Accumulation | B5: -0.468905 | C5: -0.34050277
A6: SAXO EUROPE | B6: -7.0611691 | C6: -7.0611691
A7: AMUNDI UNICREDIT PREM PORT- PRUDENTIAL | B7: -0.82641419 | C7: -0.79892258
A8: AMUNDI UNICREDIT PREM PORT- MULTI ASSET | B8: -2.4887237 | C8: -5.4248356
A9: AMUNDI SOLUZIONI ITALIA - PROGETTO AZIONE INFRASTRUTTURE SOSTENIBILI (II) | B9: -89.223301 | C9: -68.314788
A10: AMUNDI SOLUZIONI ITALIA - PROGETTO AZIONE INFRASTRUTTURE SOSTENIBILI | B10: -138.67363 | C10: -114.98841
A11: AMUNDI SENTIERO SOSTENIBILE | B11: -7.3314559 | C11: -10.126505
A12: AMUNDI FUND SOLUTIONS - SABADELL URQUIJO CRECIMIENTO | B12: 0 | C12: 0
A13: AMUNDI FUND SOLUTIONS - SABADELL URQUIJO ACUMULACION | B13: 0 | C13: 0
A14: Amundi Fund Solutions - Diversified Income Best Select 2022 | B14: -1.3859767 | C14: -4.8674647
A15: AMUNDI FUND SOLUTIONS - DIVERSIFIED GROWTH - A | B15: -1.8619051 | C15: -1.1998128
... A19: AMUNDI ELITE THEMATIC MULTI ASSET | B19: 118.68122 | C19: -136.91224

Sheet AUM by Fund
A3: Portfolios name
A4: Univalore Stars Income
A5: Univalore Stars Growth - Comanaged with Fund Selection -
A6: Univalore Stars Balanced
A7: Univalore E Strategia 70
A8: Univalore E Strategia 40
A9: Univalore E Strategia 30
A10: Univalore E Strategia 20
A11: Unit Linked Multi Thematic Global Eq
A12: Unit Linked Multi Equity Accumulation
A13: UL Life Income 360
A14: UL Life Income
... A33: AMUNDI FUND SOLUTIONS - BALANCED

Sheet AUM by Model
A3: Portfolios name
A4: Unit Linked OLD 4
A5: UNIT LINKED G5 NEW
A6: UNIT LINKED G4 NEW
A7: UNIT LINKED E6 NEW
A8: UNIT LINKED E4 NEW
A9: UNIT LINKED E3 NEW
A10: UNIT LINKED E2 NEW
A11: Unit Linked AMix UNIPLAN
A12: Unit Linked A TR UNIPLAN
A13: UNIFLEX ACTIVE 3
A14: UNIFLEX ACTIVE 2
... A52: CAM Agosto

Sheet Startegy Changes (2)
B3: Column Labels
B4: Flows mln QTD € | D4: Difference In AUM mln QTD € | F4: Total Flows mln QTD € | G4: Total Difference In AUM mln QTD €
A5: Strategy | B5: Fund | C5: Model | D5: Fund | E5: Model
A6: Bond | B6: -2.9774607 | D6: -2.9849541 | F6: -2.9774607 | G6: -2.9849541
A7: Capital Guaranteed | C7: -65.534486 | E7: -44.165264 | F7: -65.534486 | G7: -44.165264
A8: Capital Protection | C8: -0.0873133 | E8: -0.01984 | F8: -0.0873133 | G8: -0.01984
A9: Conservative | B9: -7.3841967 | C9: -20.27235 | D9: -5.1672111 | E9: -17.236822 | F9: -27.656547 | G9: -22.404033
A10: Equity | B10: -14.921085 | C10: -35.848827 | D10: -18.078061 | E10: 100.7319 | F10: -50.769913 | G10: 82.653837
A11: Flexible | B11: -26.306785 | C11: -130.64609 | D11: -32.02505 | E11: -120.7386 | F11: -156.95288 | G11: -152.76365
A12: Growth | B12: 25.096397 | C12: -11.94981 | D12: 27.735835 | E12: 4.694794 | F12: 13.146587 | G12: 32.430629
A13: Income | B13: -11.006052 | C13: -54.349645 | D13: -16.633531 | E13: -57.063289 | F13: -65.355696 | G13: -73.69682
A14: Moderate | B14: -9.826379 | C14: -3.712064 | D14: -1.6296295 | E14: -2.638989 | F14: -13.538443 | G14: -4.2686185
A15: Risk Accumulation | B15: -335.01257 | C15: -0.6752106 | D15: -420.76862 | E15: -0.468905 | F15: -335.68778 | G15: -421.23752
A16: Thematic | B16: -136.91224 | C16: 15.630024 | D16: 118.68122 | E16: 48.83956 | F16: -121.28221 | G16: 167.52078
A17: Grand Total | B17: -519.25036 | C17: -307.44577 | D17: -350.87 | E17: -88.065456 | F17: -826.69614 | G17: -438.93546

Sheet Fund by Strategy
A3: Sum of Difference final
A4: Strategy Type | B4: Strategy Detail | C4: Decalog ID | D4: Total
A5: Allocation Driven Strategies | B5: Conservative | C5: 1RM | D5: -338342
C6: COBBLEURO | D6: 0
C7: CREDDITO | D7: 323
C8: CTREND_20 | D8: 0
C9: E118 | D9: -826414.19
C10: E143 | D10: -4340796.9
C11: MEPF2N | D11: -304730
C12: MEPF4 | D12: -182213
C13: MEPF5 | D13: -1380437
C14: MLIFEBND | D14: -3214771
C15: PP1-3Y | D15: -3879674
C16: PP3Y | D16: 682015
C17: STEPONE | D17: 1073
... C22: ULPRUD | D22: -613315
C23: PF101372
C24: PF87100 | D24: 0
C25: SAXO | D25: -7061169.1
B26: Conservative Total | D26: -22404033
B27: Equity | D27: 86257464
B28: Flexible | C28: MATRUNIP | D28: -616815
C29: MLPFLEX | D29: -811947
C30: PLIC | D30: -299069
C31: PSUKLD1 | D31: 3429821.8
C32: UES20 | D32: -1465146
C33: UES30 | D33: -16022861
C34: UES40 | D34: -1488772
C35: UES50 | D35: -62412056
C36: UES70 | D36: -37621934
B37: Flexible Total | D37: -1.1730878e+08
B38: Growth | C38: 1PM | D38: 9459997
C39: CCRESCITA | D39: 32879
C40: CSVILUPPO | D40: 0
C41: E119 | D41: 1644961.7
C42: E144 | D42: -1861905.1
C43: MEPF10 | D43: 2361
C44: MEPF8 | D44: -3946471
C45: R1M | D45: 14288
C46: R2M | D46: 77644
C47: ULDER | D47: 0
C48: ULDIN | D48: -950039
C49: ULG4NEW | D49: 4135
C50: PF101380
C51: PF87115 | D51: 0
C52: PF204806 | D52: 27952778
B53: Growth Total | D53: 32430629
B54: Moderate | C54: 1QM | D54: -42336
C55: CMEDIUM | D55: 5450
C56: DINAR1TF | D56: -1129
C57: DINAR2TF | D57: -9927
C58: DINAR3TF | D58: 1046
C59: E120 | D59: -2488723.7
C60: E142 | D60: 859094.12
C61: MEPF6 | D61: -1501878
C62: MUNIP | D62: -17422
C63: ULBER- | D63: 0
C64: ULBIL | D64: -597412
C65: ULBILPIU | D65: -475381
C66: PF101376
B67: Moderate Total | D67: -4268618.5
A68: Allocation Driven Strategies Total | D68: -25293337
A69: Outcome Oriented Strategies | B69: Capital Guaranteed | C69: AAPROT80 | D69: -2123896
C70: CNPDYNPR80 | D70: -15428341
C71: CRVDYNPR80 | D71: -24414320
C72: CNPTHEMPROT | D72: -6386983
C73: CRVTHEMPROT | D73: -4918099
C74: CNPPROT80 | D74: 3955401
C75: CRVPROT80 | D75: 5150974
B76: Capital Guaranteed Total | D76: -44165264
B77: Capital Protection | D77: -19840
B78: Income | C78: DIOP 1 | D78: -341462.86
C79: DIOP 2 | D79: -555952.98
C80: DIOP3 | D80: -1737052.8
C81: E193 | D81: -1385976.7
C82: MLINC | D82: -15083516
C83: MULLI360 | D83: -15027385
C84: MUSI | D84: -24317919
C85: PF115036 | D85: 20657.66
B86: Income Total | D86: -58428608
B87: Risk Accumulation | C87: MULSTEP | D87: 0
C88: PF71664
C89: PF76580
C90: PF78195
C91: PF79139
C92: ULACCO | D92: -468905
C93: PF103025 | D93: -18141244
C94: PF92127 | D94: -1.3867363e+08
C95: PF95239 | D95: -89223301
C96: PF201311 | D96: -7331455.9
C97: PF88300 | D97: -1.0351484e+08
C98: PF89408 | D98: -63884148
B99: Risk Accumulation Total | D99: -4.2123752e+08
B100: Thematic | C100: DIOP4 | D100: -4642940.7
C101: Multhem | D101: 0
C102: MUSG | D102: 0
C103: PF88524 | D103: 1.1868122e+08
C104: UNGOALS | D104: 40512971
C105: ULMATREND | D105: 12969530
C106: ULFTREND | D106: 0
...

Sheet Audit AUM File
A1: Code decalog | B1: Actif net (portefeuille) - EUR
A2: AUS00324 | B2: 27804535
A3: AUS00445 | B3: 849369.14
A4: AUS00093 | B4: 1.3843047e+08
A5: AUS00773 | B5: 32322420
A6: PF54396 | B6: 3946939.7
A7: BPI389 | B7: 13352728
A8: BPI389T | B8: 13352728
A9: PF54404 | B9: 3533283.2
A10: BPI657 | B10: 2.9086597e+08
A11: BPI659 | B11: 2.0662561e+08
A12: BPI780M | B12: 4.427633e+08
A13: BPI782 | B13: 3.789079e+08
A14: AUS00C20
A15: AUS00932 | B15: 38184642
A16: AUS00666 | B16: 27770578
A17: LDSP | B17: 11473666
A18: AUS00650 | B18: 25893408
A19: AUS00937 | B19: 23766298
A20: BPI938 | B20: 3.3634278e+08
A21: BPI938T | B21: 3.3634278e+08
A22: AUS00655 | B22: 36112109
A23: AUS00655T | B23: 36112109
A24: GF17 | B24: 51147818
A25: BPI557 | B25: 8001636
A26: BPI557T | B26: 8001636
... A80: AUS00432 | B80: 42840596
A81: WSTWII
A82: WSTWIV | B82: 4.4925594e+08
A83: AUS00822 | B83: 4.7288194e+08
A84: AUS00437 | B84: 16435820
A85: AUS00444 | B85: 1439291
A86: AUS00270 | B86: 1.0202666e+08
A87: AUS00938 | B87: 28294962
A88: AUS00404 | B88: 16170338
A89: AUS00669 | B89: 22773777
A90: AUS00670 | B90: 11021284
A91: AUS00323A | B91: 13039893
A92: AUS00323 | B92: 13039893
A93: AUS00032C1 | B93: 7.3856945e+08
... A182: FO44713 | B182: 2.0071569e+08
A183: P3D
A184: P3K
A185: PSK
A186: P3B
A187: KOPO
A188: PEF
A189: PF43036
A190: PF44849
A191: PF42801
A192: PF46862
A193: PF46673
A194: PF36764
... A204: M21919
A205: FO240995 | B205: 18935456
A206: PF41679
A207: M21922
A208: PF49709
A209: PF47297
A210: 086BA015
A211: PF47315
A212: FO222866 | B212: 3944080
A213: PF43434
A214: PF35640
A215: PF46465
A216: PF47526
A217: PF50667
A218: PF48280
A219: PF44882
A220: PF47669
A221: PF44846
A222: PF47523
A223: PF43593
A224: PF43723
... A293: PF52208
A294: E156 | B294: 41668274
A295: E183 | B295: 48076001
A296: E90PS | B296: 10109974
A297: E123AE | B297: 4.3398213e+08
A298: E123AEHMD | B298: 4.3398213e+08
A299: E123C2 | B299: 4.3398213e+08
A300: E123AEQD | B300: 4.3398213e+08
A301: E123A | B301: 4.3398213e+08
A302: E123AQD | B302: 4.3398213e+08
A303: E123EED | B303: 4.3398213e+08
A304: E123EEHSD | B304: 4.3398213e+08
A305: E123ED | B305: 4.3398213e+08
... A404: G6583 | B404: 1.1737422e+08
B405: 1.1764714e+08
A406: G0533 | B406: 50282314
A407: G0043 | B407: 61305301
A408: G6585 | B408: 51501099
B409: 5.4235729e+08
A410: G6559 | B410: 5.4149179e+08
A411: G0834 | B411: 64364099
A412: G0834CEC | B412: 64364099
A413: G0834HEC | B413: 64364099
A414: G0834LEC | B414: 64364099
A415: EEC | B415: 1.7859549e+08
A416: EECC2 | B416: 0
...

Sheet Sheet1 (QTD Flows)
A1: Portfolio Names | B1: Flows mln QTD | C1: Difference In AUM
A2: AMUNDI ELITE THEMATIC MA | B2: -136.91224 | C2: 118.68122
A3: Amundi Env and Climate Change Sol Fund | B3: -14.474434 | C3: -14.474434
A4: AMUNDI FUND SOLUTIONS - BALANCED | B4: -4.4015434 | C4: 0.85909412
A5: AMUNDI FUND SOLUTIONS - CONSERVATIVE | B5: -6.5852741 | C5: -4.3407969
A6: AMUNDI FUND SOLUTIONS - DIVERSIFIED GROWTH - A | B6: -1.1998128 | C6: -1.8619051
A7: AMUNDI FUND SOLUTIONS - SABADELL URQUIJO ACUMULACION | B7: 0 | C7: 0
A8: AMUNDI FUND SOLUTIONS - SABADELL URQUIJO CRECIMIENTO | B8: 0 | C8: 0
A9: ASI - PROGETTO AZIONE ENERGY TRANSITION | B9: -75.897228 | C9: -103.51484
A10: UL Life Income | B10: -15.247023 | C10: -15.083516
A11: UL Life Income 360 | B11: -14.572498 | C11: -15.027385
H18: Funds | I18: Flows mln QTD € | J18: Difference mln In AUM€
H19: AMUNDI ELITE THEMATIC MA | I19: 611.23309 | J19: 617.2751
H20: Amundi Env and Climate Change Sol Fund | I20: 246.90822 | J20: 246.90822
H21: AFS - BALANCED | I21: 19.695437 | J21: 28.572971
H22: AFS - CONSERVATIVE | I22: 40.671091 | J22: 48.241027
H23: AFS - DIVERSIFIED GROWTH - A | I23: 1.0390135 | J23: 3.5967358
H24: AFS - SABADELL URQUIJO ACUMULACION | I24: 127.7909 | J24: 127.7909
H25: AFS - SABADELL URQUIJO CRECIMIENTO | I25: 58.188872 | J25: 58.188872
H26: ASI - PROGETTO AZIONE ENERGY TRANSITION | I26: 1003.4215 | J26: 1003.4215
H27: UL Life Income | I27: -46.737384 | J27: -43.708387
H28: UL Life Income 360 | I28: -113.70536 | J28: -116.24129
H29: UNICREDIT EVOLUZIONE - REDDITO - A | I29: -36.652797 | J29: -36.425991
H30: Grand Total | I30: =SUM(I19:I29) -> 1911.8526 | J30: =SUM(J19:J29) -> 1937.6197

Sheet Breakdown by Strategy
A3: Row Labels
A4: Allocation Driven Strategies
A5: Conservative
A6: Equity
A7: Flexible
A8: Growth
A9: Moderate
A10: Outcome Oriented Strategies
A11: Capital Guaranteed
A12: Capital Protection
A13: Income
A14: Risk Accumulation
... A21: (blank)
A22: (blank) | E22: =GETPIVOTDATA("Sum of AUM from our AUM Nov 2019 file",$A$3)-GETPIVOTDATA("Sum of AUM from our AUM Dec 2019 file",$A$3) -> #REF!
A23: Grand Total
